Workbook
Name Resource_Billability: '[1]Control Reference'!$E$13:$E$15
Name Role_Level: '[2]Control Reference'!$G$8:$G$48
Name Type: '[3]Maintenance Work Order'!#REF!

Sheet MainPage
B1: PMWB-Project Name_MonthYear
B4: Template ID | C4: ENPMT18
B6: Template Name | C6: PMWB-Project Name_MonthYear
B8: Template Version | C8: 1.3
B10: Author | C10: QMG
C11: Changes made -
C12: 1. Change in InterraIT logo 2. Restructuring of the document 3. Risk updated as per ISMS
B13: Template Release Date | C13: 45890

Sheet Project Info
A1: Project Information
A2: Project Name
A3: Project Code/PIN | C3: Status
A4: Project Category | C4: Project Type
A6: Customer Name & Address | B6: Mazda North American Operation(MNAO)
A7: Customer's Line of Business | B7: Automotive
A8: Primary Contact Person | B8: Paula Neil(PNeil@mazdausa.com/1-949-727-6305
A10: Project Start Date in SOW | C10: Project Completion Date in SOW
A11: Plan Start Date | C11: Plan Completion Date
A12: Revised Plan Start Date | C12: Revised Plan Completion Date
A13: Actual Start Date | C13: Actual Completion Date
A15: Estimated Effort(Hrs) | C15: Approved Effort(Hrs) | D15: =B15*90% -> 0
A16: Actual Effort Consumed(Hrs) | B16: =PSR!R28+PSR!I28 -> 0 | C16: Remaining Effort | D16: =D15-B16 -> 0
A18: SOW Onsite FTEs | C18: SOW Offshore FTEs
A19: Actual Onsite FTEs | B19: =PSR!R28/8 -> 0 | C19: Actual Offshore FTEs | D19: =PSR!I28/8 -> 0
A23: Date | B23: Version No. | C23: Changes | D23: Updated by

Sheet Project information1
A1: Project Name | C1: Customer name | E1: Links to Sheets | H1: =IF(ISERROR(SMALL('Control panel'!D$3:D$23,ROW())),"",INDIRECT("'Control panel'!B" & SMALL('Control panel'!D$3:D$23,ROW()),2)) -> Hours | I1: Technology | J1: Programming Language | K1: Platform | L1: BU : SAP CS | M1: DE Development | N1: Bangalore - 23 Airport Road
A2: SAP Project Code | C2: Plan start date | D2: =#REF! -> #REF! | E2: Control Panel | H2: =IF(ISERROR(SMALL('Control panel'!D$3:D$23,ROW())),"",INDIRECT("'Control panel'!B" & SMALL('Control panel'!D$3:D$23,ROW()),2)) | I2: Application | J2: 1032/AF | K2: A7/ZSP | L2: BU : SAP Hewitt Associates | M2: MM Maintenance - Migration | N2: Bangalore - 33A Ulsoor Road
A3: Business Unit (SAP) | C3: Plan completion date | D3: =#REF! -> #REF! | E3: Planning | H3: =IF(ISERROR(SMALL('Control panel'!D$3:D$23,ROW())),"",INDIRECT("'Control panel'!B" & SMALL('Control panel'!D$3:D$23,ROW()),2)) | I3: AS/400 | J3: 1st Generation default | K3: AS/400 | L3: BU : SAP AMD | M3: MP Maintenance - Porting | N3: Bangalore - 5 100 Ft Road
A4: Business Model | C4: Revised start date | D4: =#REF! -> #REF! | E4: Metrics plan | H4: =IF(ISERROR(SMALL('Control panel'!D$3:D$23,ROW())),"",INDIRECT("'Control panel'!B" & SMALL('Control panel'!D$3:D$23,ROW()),2)) | I4: Client/Server | J4: 2nd Generation default | K4: Embedded | L4: BU : SAP Dom Projects | M4: MS Maintenance - Small SDLC | N4: Bangalore - 8, 9 GB Palya
A5: Project Type | C5: Revised completion date | D5: =#REF! -> #REF! | E5: Staffing | H5: =IF(ISERROR(SMALL('Control panel'!D$3:D$23,ROW())),"",INDIRECT("'Control panel'!B" & SMALL('Control panel'!D$3:D$23,ROW()),2)) | I5: Embedded | J5: 3rd Generation default | K5: JTAG | L5: BU : SAP NCR Projects | M5: PI Package Implementation | N5: Chennai - 158 Arcot Road
A6: Project Location | C6: Actual start date | D6: =#REF! -> #REF! | E6: Training | H6: =IF(ISERROR(SMALL('Control panel'!D$3:D$23,ROW())),"",INDIRECT("'Control panel'!B" & SMALL('Control panel'!D$3:D$23,ROW()),2)) | I6: Enterprise Data Warehousing | J6: 4th Generation default | K6: Linux | L6: BU : SAP B'lore | M6: PS Product Sales | N6: Chennai - 184 NSK Road
A7: Project Manager | C7: Actual completion date | E7: Subprocess goal tracking | H7: =IF(ISERROR(SMALL('Control panel'!D$3:D$23,ROW())),"",INDIRECT("'Control panel'!B" & SMALL('Control panel'!D$3:D$23,ROW()),2)) | I7: Imaging | J7: 5th Generation default | K7: Mobile | L7: BU : SAP Kolkata | M7: SC Scoping | N7: Chennai - 30 C-in-C Road
A8: Senior Manager | C8: Initial estimated effort | D8: =#REF! -> #REF! | E8: Risk Management | H8: =IF(ISERROR(SMALL('Control panel'!D$3:D$23,ROW())),"",INDIRECT("'Control panel'!B" & SMALL('Control panel'!D$3:D$23,ROW()),2)) | I8: Mainframe | J8: AAS Macro | K8: Nucleus | L8: BU : SAP Chennai - Rockwell | M8: TE Testing | N8: Chennai - 30 Ethiraj Salai
A9: Engineering Staff | C9: Revised effort | D9: =#REF! -> #REF! | E9: Recruitment Plan | H9: =IF(ISERROR(SMALL('Control panel'!D$3:D$23,ROW())),"",INDIRECT("'Control panel'!B" & SMALL('Control panel'!D$3:D$23,ROW()),2)) | I9: Microsoft Technologies | J9: ABAP/4 | K9: Open VMS | L9: BU : SAP Chennai - Others | M9: OT Other | N9: Chennai - 34-35 Haddows Road
A10: Initial estimate size | B10: =#REF! -> #REF! | C10: Actual effort | D10: =#REF! -> #REF! | E10: IT Services Plan | H10: =IF(ISERROR(SMALL('Control panel'!D$3:D$23,ROW())),"",INDIRECT("'Control panel'!B" & SMALL('Control panel'!D$3:D$23,ROW()),2)) | I10: Others | J10: ACCEL | K10: Others | L10: BU : SAP SMH | N10: Chennai - 43-44 Montieth Road
A11: Revised size | B11: =#REF! -> #REF! | C11: Effort unit | E11: Size, Schedule and Effort | H11: =IF(ISERROR(SMALL('Control panel'!D$3:D$23,ROW())),"",INDIRECT("'Control panel'!B" & SMALL('Control panel'!D$3:D$23,ROW()),2)) | J11: Access | K11: UNIX | L11: BU : SAP ANZ | N11: Chennai - 50-53 Greams Road
A12: Actual Size | B12: =#REF! -> #REF! | C12: Estimates revised on | E12: Verification data | H12: =IF(ISERROR(SMALL('Control panel'!D$3:D$23,ROW())),"",INDIRECT("'Control panel'!B" & SMALL('Control panel'!D$3:D$23,ROW()),2)) | J12: ACTOR | K12: Windows | L12: BU : SAP US | N12: Chennai - 51 JN Road
A13: Size Unit | C13: Primary Dev. Language | E13: Verification Summary | H13: =IF(ISERROR(SMALL('Control panel'!D$3:D$23,ROW())),"",INDIRECT("'Control panel'!B" & SMALL('Control panel'!D$3:D$23,ROW()),2)) | J13: Acumen | L13: BU : SAP Europe | N13: Chennai - 35 South Phase (Guindy)
A14: Platform | C14: Project Technology | E14: Quality of work | H14: =IF(ISERROR(SMALL('Control panel'!D$3:D$23,ROW())),"",INDIRECT("'Control panel'!B" & SMALL('Control panel'!D$3:D$23,ROW()),2)) | J14: Ada 83 | L14: BU : SAP COE | N14: Chennai - 602 Tidel Park
A15: Project Status | D15: Guidelines | E15: Phasewise EV-SV | H15: =IF(ISERROR(SMALL('Control panel'!D$3:D$23,ROW())),"",INDIRECT("'Control panel'!B" & SMALL('Control panel'!D$3:D$23,ROW()),2)) | J15: Ada 95 | L15: BU : OU Teradyne | N15: Chennai - 78 South Phase Road (Ambattur)
D16: Accomplishments and Incidents | E16: Charts | H16: =IF(ISERROR(SMALL('Control panel'!D$3:D$23,ROW())),"",INDIRECT("'Control panel'!B" & SMALL('Control panel'!D$3:D$23,ROW()),2)) | J16: ADR/DL | L16: BU : OU Hewitt Associates | N16: Chennai - 84 Greams Road
D17: CR Information | E17: Corrective action | H17: =IF(ISERROR(SMALL('Control panel'!D$3:D$23,ROW())),"",INDIRECT("'Control panel'!B" & SMALL('Control panel'!D$3:D$23,ROW()),2)) | J17: ADR/IDEAL/PDL | L17: BU : OU BFSI | N17: Chennai - 64-66 South Phase Road (Ambattur)
A18: Date | B18: Rev | C18: Changes | D18: Updated by | E18: Tracking effort in hours | J18: ADS/Batch | L18: BU : OU MFG | N18: Chennai - D12 & 12B Industrial Estate (Ambattur)
J19: ADS/Online | L19: BU : OU HI Tech | N19: Chennai - J-16 Anna Nagar
J20: AI shell default | L20: BU : OU MPE | N20: Chennai - NM Road
J21: AI SHELLS | L21: BU : OU Telecon | N21: Chennai - PH Road
J22: ALGOL 68 | L22: BU : OU Retail & Others | N22: Chennai - PM Towers
J23: ALGOL W | L23: BU : OU Life Sciences | N23: Gurgaon (244) - Phase 1
J24: AMBUSH | L24: BU : OU COE/Skill Pool | N24: Gurgaon (3) - Phase 1
J25: AML | L25: BU : MBS | N25: Kolkata - Sector V, Salt Lake
J26: AMPPL II | L26: BU : Placement projects | N26: Noida (A/104) - Sector 58
J27: ANSI BASIC | L27: BU : EAI - (India) | N27: Noida (A-1) - Sector 16
J28: ANSI COBOL 74 | L28: BU : EAI - (Alayance) | N28: Noida (A-10/11) - Sector 3
J29: ANSI COBOL 85 | L29: CBU : PEARSON | N29: Noida (A-11) - Sector 16
J30: ANSI SQL | L30: CBU: LN/ NE | N30: Noida (A-5) - Sector 24
... J35: APPLESOFT BASIC | L35: IS - MPE - ECMP Documentum | N35: Other
J36: Application Builder | L36: IS - MPE - ECMP Others
J37: Application Manager | L37: VERTICAL: ACS-HTM-NOIDA
J38: APS | L38: OBU: TECH SUPORT BGL
J39: APT | L39: OBU: TECH SUPPORT CHENNAI
J40: APTools | L40: OBU: ACS HYD
J41: ARC | L41: IS - HTM - ECMP Documentum
J42: Ariel | L42: IS - HTM - ECMP Others
J43: ARITY | L43: VERTICAL : PHARMA CHENNAI
J44: Arity PROLOG | L44: VERTICAL : HEALTHCARE CHENNAI
J45: ART | L45: IS - LSH - ECMP Documentum
J46: ART Enterprise | L46: IS - LSH - ECMP Others
J47: Artemis | L47: VERTICAL : TRANSPORTATION CHENNAI
... J180: FOXPRO 1 | L180: ERS-SEG-CHN-TECH CoE
J181: FOXPRO 2.5
J182: FRAMEWORK
J183: G2
J184: GAMMA
J185: Genascript
J186: GENER/OL
J187: GENEXUS
J188: GENIFER
J189: GeODE 2.0
J190: GFA Basic
J191: GML
J192: Golden Common LISP
... J503: ZLISP

Sheet Charts
A1: Schedule
A2: Effort
A3: WDD | V3: =COUNT(#REF!) -> 0
A4: Productivity | V4: ='Size, Schedule and Effort'!Z1-1 -> 2
I5: =COUNTA('Size, Schedule and Effort'!A:A)-1 -> 7 | J5: {=MAX(IF('Quality of Work'!E19:E120<>"",ROW('Quality of Work'!E19:E120),0))} -> 23 | K5: =COUNT(#REF!) -> 0 | L5: =COUNT(#REF!) -> 0 | M5: =COUNT('Verification Summary'!Q9:Q24) -> 6
W92: =COUNTA(#REF!)-COUNTBLANK(#REF!) -> #REF!

Sheet PSR
A1: Project Status Review
A2: Planned Productivity ( Till Current period) | B2: =IF(H28=0,"",G47/H28) | C2: Resource Level | D2: No# | E2: Resource Level | F2: No# | G2: Resource Level | H2: No# | I2: Project Start Dt. | K2: ='Project Info'!B12 -> 0
A3: Actual Productivity ( Till Current period) | B3: =IF(I28=0,"",G47/I28) | C3: L1 | D3: =COUNTIF(Resources!$F$18:$F$86,C3) -> 0 | E3: L5 | F3: =COUNTIF(Resources!$F$18:$F$86,E3) -> 0 | G3: L9 | H3: =COUNTIF(Resources!$F$18:$F$86,G3) -> 0 | I3: Project End Dt. | K3: ='Project Info'!D12 -> 0
A4: Current Team Size | B4: =SUMIF(Resources!$P$18:$P$86,"Available ",Resources!$Q$18:$Q$86) -> 0 | C4: L2 | D4: =COUNTIF(Resources!$F$18:$F$86,C4) -> 0 | E4: L6 | F4: =COUNTIF(Resources!$F$18:$F$86,E4) -> 0 | G4: L10 | H4: =COUNTIF(Resources!$F$18:$F$86,G4) -> 0 | I4: Current Date
A5: No. of Persons Resigned | B5: =SUMIF(Resources!$P$18:$P$86,"Resigned",Resources!$R$18:$R$86) -> 0 | C5: L3 | D5: =COUNTIF(Resources!$F$18:$F$86,C5) -> 0 | E5: L7 | F5: =COUNTIF(Resources!$F$18:$F$86,E5) -> 0 | H5: =COUNTIF(Resources!$F$18:$F$86,G5) -> 0
A6: No. of Persons currently Not Available in project | B6: =SUMIF(Resources!$P$18:$P$86,"Not Available",Resources!$S$18:$S$86) -> 0 | C6: L4 | D6: =COUNTIF(Resources!$F$18:$F$86,C6) -> 0 | E6: L8 | F6: =COUNTIF(Resources!$F$18:$F$86,E6) -> 0 | H6: =COUNTIF(Resources!$F$18:$F$86,G6) -> 0
B8: Note - Please put the efforts belonging to the 'current cumulative' blocks to 'Upto last period' block
A13: 1. PROJECT EFFORT
A15: Effort as per Type (Man-hours) | B15: Offshore | K15: Onsite
B16: Upto Last Period | E16: Current Period | H16: Current Cumulative | K16: Upto Last Period | N16: Current Period | Q16: Current Cumulative
B17: Planned | C17: Actual | D17: Deviation (%) | E17: Planned | F17: Actual | G17: Deviation (%) | H17: Planned | I17: Actual | J17: Deviation (%) | K17: Planned | L17: Actual | M17: Deviation (%) | N17: Planned | O17: Actual | P17: Deviation (%) | Q17: Planned | R17: Actual | S17: Deviation (%)
A18: Project Team Effort (Man-Hrs) | D18: =IF(B18=0,0,((B18-C18)/B18)*100) -> 0 | E18: =Resources!G4 -> 0 | F18: =Resources!I4 -> 0 | G18: =IF(E18=0,0,((E18-F18)/E18)*100) -> 0 | H18: =E18+B18 -> 0 | I18: =C18+F18 -> 0 | J18: =IF(H18=0,0,((H18-I18)/H18)*100) -> 0 | K18: 0 | L18: 0 | M18: =IF(K18=0,0,((K18-L18)/K18)*100) -> 0 | N18: =Resources!L4 -> 0 | O18: =Resources!N4 -> 0 | P18: =IF(N18=0,0,((N18-O18)/N18)*100) -> 0 | Q18: =N18+K18 -> 0 | R18: =L18+O18 -> 0 | S18: =IF(Q18=0,0,((Q18-R18)/Q18)*100) -> 0
A19: Testing Team Effort (Man-Hrs) | D19: =IF(B19=0,0,((B19-C19)/B19)*100) -> 0 | E19: =Resources!G5 -> 0 | F19: =Resources!I5 -> 0 | G19: =IF(E19=0,0,((E19-F19)/E19)*100) -> 0 | H19: =E19+B19 -> 0 | I19: =C19+F19 -> 0 | J19: =IF(H19=0,0,((H19-I19)/H19)*100) -> 0 | K19: 0 | L19: 0 | M19: =IF(K19=0,0,((K19-L19)/K19)*100) -> 0 | N19: =Resources!L5 -> 0 | O19: =Resources!N5 -> 0 | P19: =IF(N19=0,0,((N19-O19)/N19)*100) -> 0 | Q19: =N19+K19 -> 0 | R19: =L19+O19 -> 0 | S19: =IF(Q19=0,0,((Q19-R19)/Q19)*100) -> 0
A20: Graphics Efforts (Man-Hrs) | D20: =IF(B20=0,0,((B20-C20)/B20)*100) -> 0 | E20: =Resources!G6 -> 0 | F20: =Resources!I6 -> 0 | G20: =IF(E20=0,0,((E20-F20)/E20)*100) -> 0 | H20: =E20+B20 -> 0 | I20: =C20+F20 -> 0 | J20: =IF(H20=0,0,((H20-I20)/H20)*100) -> 0 | K20: 0 | L20: 0 | M20: =IF(K20=0,0,((K20-L20)/K20)*100) -> 0 | N20: =Resources!L6 -> 0 | O20: =Resources!N6 -> 0 | P20: =IF(N20=0,0,((N20-O20)/N20)*100) -> 0 | Q20: =N20+K20 -> 0 | R20: =L20+O20 -> 0 | S20: =IF(Q20=0,0,((Q20-R20)/Q20)*100) -> 0
A21: Tech. Writer Efforts (Man-Hrs) | D21: =IF(B21=0,0,((B21-C21)/B21)*100) -> 0 | E21: =Resources!G7 -> 0 | F21: =Resources!I7 -> 0 | G21: =IF(E21=0,0,((E21-F21)/E21)*100) -> 0 | H21: =E21+B21 -> 0 | I21: =C21+F21 -> 0 | J21: =IF(H21=0,0,((H21-I21)/H21)*100) -> 0 | K21: 0 | L21: 0 | M21: =IF(K21=0,0,((K21-L21)/K21)*100) -> 0 | N21: =Resources!L7 -> 0 | O21: =Resources!N7 -> 0 | P21: =IF(N21=0,0,((N21-O21)/N21)*100) -> 0 | Q21: =N21+K21 -> 0 | R21: =L21+O21 -> 0 | S21: =IF(Q21=0,0,((Q21-R21)/Q21)*100) -> 0
A22: QA Efforts (Man-Hrs) | D22: =IF(B22=0,0,((B22-C22)/B22)*100) -> 0 | E22: =Resources!G8 -> 0 | F22: =Resources!I8 -> 0 | G22: =IF(E22=0,0,((E22-F22)/E22)*100) -> 0 | H22: =E22+B22 -> 0 | I22: =C22+F22 -> 0 | J22: =IF(H22=0,0,((H22-I22)/H22)*100) -> 0 | K22: 0 | L22: 0 | M22: =IF(K22=0,0,((K22-L22)/K22)*100) -> 0 | N22: =Resources!L8 -> 0 | O22: =Resources!N8 -> 0 | P22: =IF(N22=0,0,((N22-O22)/N22)*100) -> 0 | Q22: =N22+K22 -> 0 | R22: =L22+O22 -> 0 | S22: =IF(Q22=0,0,((Q22-R22)/Q22)*100) -> 0
A23: Organizational Efforts (Man-Hrs) | D23: =IF(B23=0,0,((B23-C23)/B23)*100) -> 0 | E23: =Resources!G9 -> 0 | F23: =Resources!I9 -> 0 | G23: =IF(E23=0,0,((E23-F23)/E23)*100) -> 0 | H23: =E23+B23 -> 0 | I23: =C23+F23 -> 0 | J23: =IF(H23=0,0,((H23-I23)/H23)*100) -> 0 | K23: 0 | L23: 0 | M23: =IF(K23=0,0,((K23-L23)/K23)*100) -> 0 | N23: =Resources!L9 -> 0 | O23: =Resources!N9 -> 0 | P23: =IF(N23=0,0,((N23-O23)/N23)*100) -> 0 | Q23: =N23+K23 -> 0 | R23: =L23+O23 -> 0 | S23: =IF(Q23=0,0,((Q23-R23)/Q23)*100) -> 0
A24: PM Efforts (Man-Hrs) | D24: =IF(B24=0,0,((B24-C24)/B24)*100) -> 0 | E24: =Resources!G10 -> 0 | F24: =Resources!I10 -> 0 | G24: =IF(E24=0,0,((E24-F24)/E24)*100) -> 0 | H24: =E24+B24 -> 0 | I24: =C24+F24 -> 0 | J24: =IF(H24=0,0,((H24-I24)/H24)*100) -> 0 | K24: 0 | L24: 0 | M24: =IF(K24=0,0,((K24-L24)/K24)*100) -> 0 | N24: =Resources!L10 -> 0 | O24: =Resources!N10 -> 0 | P24: =IF(N24=0,0,((N24-O24)/N24)*100) -> 0 | Q24: =N24+K24 -> 0 | R24: =L24+O24 -> 0 | S24: =IF(Q24=0,0,((Q24-R24)/Q24)*100) -> 0
A25: Architecture (Man-Hrs) | D25: =IF(B25=0,0,((B25-C25)/B25)*100) -> 0 | E25: =Resources!G11 -> 0 | F25: =Resources!I11 -> 0 | G25: =IF(E25=0,0,((E25-F25)/E25)*100) -> 0 | H25: =E25+B25 -> 0 | I25: =C25+F25 -> 0 | J25: =IF(H25=0,0,((H25-I25)/H25)*100) -> 0 | K25: 0 | L25: 0 | M25: =IF(K25=0,0,((K25-L25)/K25)*100) -> 0 | N25: =Resources!L11 -> 0 | O25: =Resources!N11 -> 0 | P25: =IF(N25=0,0,((N25-O25)/N25)*100) -> 0 | Q25: =N25+K25 -> 0 | R25: =L25+O25 -> 0 | S25: =IF(Q25=0,0,((Q25-R25)/Q25)*100) -> 0
A26: Business Analyst Efforts (Man-Hrs) | D26: =IF(B26=0,0,((B26-C26)/B26)*100) -> 0 | E26: =Resources!G12 -> 0 | F26: =Resources!I12 -> 0 | G26: =IF(E26=0,0,((E26-F26)/E26)*100) -> 0 | H26: =E26+B26 -> 0 | I26: =C26+F26 -> 0 | J26: =IF(H26=0,0,((H26-I26)/H26)*100) -> 0 | K26: 0 | L26: 0 | M26: =IF(K26=0,0,((K26-L26)/K26)*100) -> 0 | N26: =Resources!L12 -> 0 | O26: =Resources!N12 -> 0 | P26: =IF(N26=0,0,((N26-O26)/N26)*100) -> 0 | Q26: =N26+K26 -> 0 | R26: =L26+O26 -> 0 | S26: =IF(Q26=0,0,((Q26-R26)/Q26)*100) -> 0
A27: PMO Efforts (Man-Hrs) | D27: =IF(B27=0,0,((B27-C27)/B27)*100) -> 0 | E27: =Resources!G13 -> 0 | F27: =Resources!I13 -> 0 | G27: =IF(E27=0,0,((E27-F27)/E27)*100) -> 0 | H27: =E27+B27 -> 0 | I27: =C27+F27 -> 0 | J27: =IF(H27=0,0,((H27-I27)/H27)*100) -> 0 | K27: 0 | L27: 0 | M27: =IF(K27=0,0,((K27-L27)/K27)*100) -> 0 | N27: =Resources!L13 -> 0 | O27: =Resources!N13 -> 0 | P27: =IF(N27=0,0,((N27-O27)/N27)*100) -> 0 | Q27: =N27+K27 -> 0 | R27: =L27+O27 -> 0 | S27: =IF(Q27=0,0,((Q27-R27)/Q27)*100) -> 0
A28: Total Project Efforts (Man-Hrs) | B28: =SUM(B18:B27) -> 0 | C28: =SUM(C18:C27) -> 0 | D28: =SUM(D18:D27) -> 0 | E28: =SUM(E18:E27) -> 0 | F28: =SUM(F18:F27) -> 0 | G28: =SUM(G18:G27) -> 0 | H28: =SUM(H18:H27) -> 0 | I28: =SUM(I18:I27) -> 0 | ... S28: =SUM(S18:S27) -> 0
A30: Effort as per Resource Level (Man-hours) | B30: Offshore | K30: Onsite
B31: Upto Last Period | E31: Current Period | H31: Current Cumulative | K31: Upto Last Period | N31: Current Period | Q31: Current Cumulative
B32: Planned | C32: Actual | D32: Deviation (%) | E32: Planned | F32: Actual | G32: Deviation (%) | H32: Planned | I32: Actual | J32: Deviation (%) | K32: Planned | L32: Actual | M32: Deviation (%) | N32: Planned | O32: Actual | P32: Deviation (%) | Q32: Planned | R32: Actual | S32: Deviation (%)
A33: L1 | D33: =IF(B33=0,0,((B33-C33)/B33)*100) -> 0 | E33: =Resources!Z4 -> 0 | F33: =Resources!AB4 -> 0 | G33: =IF(E33=0,0,((E33-F33)/E33)*100) -> 0 | H33: =E33+B33 -> 0 | I33: =C33+F33 -> 0 | J33: =IF(H33=0,0,((H33-I33)/H33)*100) -> 0 | K33: 0 | L33: 0 | M33: =IF(K33=0,0,((K33-L33)/K33)*100) -> 0 | N33: =Resources!AE4 -> 0 | O33: =Resources!AG4 -> 0 | P33: =IF(N33=0,0,((N33-O33)/N33)*100) -> 0 | Q33: =N33+K33 -> 0 | R33: =L33+O33 -> 0 | S33: =IF(Q33=0,0,((Q33-R33)/Q33)*100) -> 0
A34: L2 | D34: =IF(B34=0,0,((B34-C34)/B34)*100) -> 0 | E34: =Resources!Z5 -> 0 | F34: =Resources!AB5 -> 0 | G34: =IF(E34=0,0,((E34-F34)/E34)*100) -> 0 | H34: =E34+B34 -> 0 | I34: =C34+F34 -> 0 | J34: =IF(H34=0,0,((H34-I34)/H34)*100) -> 0 | K34: 0 | L34: 0 | M34: =IF(K34=0,0,((K34-L34)/K34)*100) -> 0 | N34: =Resources!AE5 -> 0 | O34: =Resources!AG5 -> 0 | P34: =IF(N34=0,0,((N34-O34)/N34)*100) -> 0 | Q34: =N34+K34 -> 0 | R34: =L34+O34 -> 0 | S34: =IF(Q34=0,0,((Q34-R34)/Q34)*100) -> 0
A35: L3 | D35: =IF(B35=0,0,((B35-C35)/B35)*100) -> 0 | E35: =Resources!Z6 -> 0 | F35: =Resources!AB6 -> 0 | G35: =IF(E35=0,0,((E35-F35)/E35)*100) -> 0 | H35: =E35+B35 -> 0 | I35: =C35+F35 -> 0 | J35: =IF(H35=0,0,((H35-I35)/H35)*100) -> 0 | K35: 0 | L35: 0 | M35: =IF(K35=0,0,((K35-L35)/K35)*100) -> 0 | N35: =Resources!AE6 -> 0 | O35: =Resources!AG6 -> 0 | P35: =IF(N35=0,0,((N35-O35)/N35)*100) -> 0 | Q35: =N35+K35 -> 0 | R35: =L35+O35 -> 0 | S35: =IF(Q35=0,0,((Q35-R35)/Q35)*100) -> 0
A36: L4 | D36: =IF(B36=0,0,((B36-C36)/B36)*100) -> 0 | E36: =Resources!Z7 -> 0 | F36: =Resources!AB7 -> 0 | G36: =IF(E36=0,0,((E36-F36)/E36)*100) -> 0 | H36: =E36+B36 -> 0 | I36: =C36+F36 -> 0 | J36: =IF(H36=0,0,((H36-I36)/H36)*100) -> 0 | K36: 0 | L36: 0 | M36: =IF(K36=0,0,((K36-L36)/K36)*100) -> 0 | N36: =Resources!AE7 -> 0 | O36: =Resources!AG7 -> 0 | P36: =IF(N36=0,0,((N36-O36)/N36)*100) -> 0 | Q36: =N36+K36 -> 0 | R36: =L36+O36 -> 0 | S36: =IF(Q36=0,0,((Q36-R36)/Q36)*100) -> 0
A37: L5 | D37: =IF(B37=0,0,((B37-C37)/B37)*100) -> 0 | E37: =Resources!Z8 -> 0 | F37: =Resources!AB8 -> 0 | G37: =IF(E37=0,0,((E37-F37)/E37)*100) -> 0 | H37: =E37+B37 -> 0 | I37: =C37+F37 -> 0 | J37: =IF(H37=0,0,((H37-I37)/H37)*100) -> 0 | K37: 0 | L37: 0 | M37: =IF(K37=0,0,((K37-L37)/K37)*100) -> 0 | N37: =Resources!AE8 -> 0 | O37: =Resources!AG8 -> 0 | P37: =IF(N37=0,0,((N37-O37)/N37)*100) -> 0 | Q37: =N37+K37 -> 0 | R37: =L37+O37 -> 0 | S37: =IF(Q37=0,0,((Q37-R37)/Q37)*100) -> 0
A38: L6 | D38: =IF(B38=0,0,((B38-C38)/B38)*100) -> 0 | E38: =Resources!Z9 -> 0 | F38: =Resources!AB9 -> 0 | G38: =IF(E38=0,0,((E38-F38)/E38)*100) -> 0 | H38: =E38+B38 -> 0 | I38: =C38+F38 -> 0 | J38: =IF(H38=0,0,((H38-I38)/H38)*100) -> 0 | K38: 0 | L38: 0 | M38: =IF(K38=0,0,((K38-L38)/K38)*100) -> 0 | N38: =Resources!AE9 -> 0 | O38: =Resources!AG9 -> 0 | P38: =IF(N38=0,0,((N38-O38)/N38)*100) -> 0 | Q38: =N38+K38 -> 0 | R38: =L38+O38 -> 0 | S38: =IF(Q38=0,0,((Q38-R38)/Q38)*100) -> 0
A39: L7 | D39: =IF(B39=0,0,((B39-C39)/B39)*100) -> 0 | E39: =Resources!Z10 -> 0 | F39: =Resources!AB10 -> 0 | G39: =IF(E39=0,0,((E39-F39)/E39)*100) -> 0 | H39: =E39+B39 -> 0 | I39: =C39+F39 -> 0 | J39: =IF(H39=0,0,((H39-I39)/H39)*100) -> 0 | K39: 0 | L39: 0 | M39: =IF(K39=0,0,((K39-L39)/K39)*100) -> 0 | N39: =Resources!AE10 -> 0 | O39: =Resources!AG10 -> 0 | P39: =IF(N39=0,0,((N39-O39)/N39)*100) -> 0 | Q39: =N39+K39 -> 0 | R39: =L39+O39 -> 0 | S39: =IF(Q39=0,0,((Q39-R39)/Q39)*100) -> 0
A40: L8 | D40: =IF(B40=0,0,((B40-C40)/B40)*100) -> 0 | E40: =Resources!Z11 -> 0 | F40: =Resources!AB11 -> 0 | G40: =IF(E40=0,0,((E40-F40)/E40)*100) -> 0 | H40: =E40+B40 -> 0 | I40: =C40+F40 -> 0 | J40: =IF(H40=0,0,((H40-I40)/H40)*100) -> 0 | K40: 0 | L40: 0 | M40: =IF(K40=0,0,((K40-L40)/K40)*100) -> 0 | N40: =Resources!AE11 -> 0 | O40: =Resources!AG11 -> 0 | P40: =IF(N40=0,0,((N40-O40)/N40)*100) -> 0 | Q40: =N40+K40 -> 0 | R40: =L40+O40 -> 0 | S40: =IF(Q40=0,0,((Q40-R40)/Q40)*100) -> 0
A41: L9 | D41: =IF(B41=0,0,((B41-C41)/B41)*100) -> 0 | E41: =Resources!Z12 -> 0 | F41: =Resources!AB12 -> 0 | G41: =IF(E41=0,0,((E41-F41)/E41)*100) -> 0 | H41: =E41+B41 -> 0 | I41: =C41+F41 -> 0 | J41: =IF(H41=0,0,((H41-I41)/H41)*100) -> 0 | K41: 0 | L41: 0 | M41: =IF(K41=0,0,((K41-L41)/K41)*100) -> 0 | N41: =Resources!AE12 -> 0 | O41: =Resources!AG12 -> 0 | P41: =IF(N41=0,0,((N41-O41)/N41)*100) -> 0 | Q41: =N41+K41 -> 0 | R41: =L41+O41 -> 0 | S41: =IF(Q41=0,0,((Q41-R41)/Q41)*100) -> 0
A42: L10 | D42: =IF(B42=0,0,((B42-C42)/B42)*100) -> 0 | E42: =Resources!Z13 -> 0 | F42: =Resources!AB13 -> 0 | G42: =IF(E42=0,0,((E42-F42)/E42)*100) -> 0 | H42: =E42+B42 -> 0 | I42: =C42+F42 -> 0 | J42: =IF(H42=0,0,((H42-I42)/H42)*100) -> 0 | K42: 4 | L42: 4 | M42: =IF(K42=0,0,((K42-L42)/K42)*100) -> 0 | N42: =Resources!AE13 -> 0 | O42: =Resources!AG13 -> 0 | P42: =IF(N42=0,0,((N42-O42)/N42)*100) -> 0 | Q42: =N42+K42 -> 4 | R42: =L42+O42 -> 4 | S42: =IF(Q42=0,0,((Q42-R42)/Q42)*100) -> 0
A43: Total Project Efforts (Man-Hrs) | B43: =SUM(B33:B42) -> 0 | C43: =SUM(C33:C42) -> 0 | D43: =SUM(D33:D42) -> 0 | E43: =SUM(E33:E42) -> 0 | F43: =SUM(F33:F42) -> 0 | G43: =SUM(G33:G42) -> 0 | H43: =SUM(H33:H42) -> 0 | I43: =SUM(I33:I42) -> 0 | ... S43: =SUM(S33:S42) -> 0
A45: 2. PROJECT SIZE (FP / Other count)
A46: Project Size in FP/ other-Count | C46: Initial | E46: Last Calculated | G46: Current Calculated | I46: Deviation
A47: Value (FP/ Other-Count) | C47: ='Project Info'!B15 -> 0 | E47: ='Project Info'!D15 -> 0 | G47: ='Project Info'!D15 -> 0 | I47: =IF(G47=0,0,100*(G47-C47)/G47) -> 0

Sheet Control Sheet
A1: Resource Type | B1: Type Description | H1: Resource Level | J1: Availibility Status | L1: Issue Status | N1: Project Category | P1: Vertical
N2: A | P2: ISV
A3: SEG | B3: Project Team Effort (Man-Hrs) (SEG) | H3: L1 | J3: Not Available | L3: Open | N3: B | P3: CSP
A4: CTT | B4: Testing Team Effort (Man-Hrs) (CTT) | H4: L2 | J4: Resigned | L4: Closed | N4: C | P4: Manufacturing
A5: GRA | B5: Graphics Efforts (Man-Hrs) (GRA) | H5: L3 | J5: Available | L5: In Progress | N5: D | P5: Retail
A6: TWR | B6: Tech. Writer Efforts (Man-Hrs) (TWR) | H6: L4 | P6: FS
A7: QAG | B7: QAG Efforts (Man-Hrs) (QAG) | H7: L5 | P7: Emerging Business
A8: ORG | B8: Organizational Efforts (Man-Hrs) (ORG) | H8: L6 | P8: SSDG
A9: PMS | B9: PM Efforts (Man-Hrs) (PMS) | H9: L7 | P9: Public Sector
A10: ARC | B10: Architecture (Man-Hrs) (ARC) | H10: L8
A11: BAS | B11: Business Analyst Efforts (Man-Hrs) (BAS) | H11: L9
A12: PMO | B12: PMO Efforts (Man-Hrs) (PMO) | H12: L10

Sheet Training
A1: S. No. | B1: Training Requirement | C1: Type of training | D1: No. of people to be trained | E1: People to be trained (names) | F1: People trained (names) | G1: Training completion date | H1: Training effort in person hours | I1: Status | J1: Remarks

Sheet Resources
A1: Current Manpower Status Report ( Resource Type Wise) | T1: Current Manpower Status Report ( Resource Level Wise)
A2: Effort Type(Man-hours) | G2: Offshore | K2: Deviation (%) | L2: Onsite | O2: Deviation (%) | T2: Resource Level (Man-hours) | Z2: Offshore | AD2: Deviation (%) | AE2: Onsite | AH2: Deviation (%)
G3: Planned | I3: Actual | L3: Planned | N3: Actual | Z3: Planned | AB3: Actual | AE3: Planned | AG3: Actual
A4: Project Team Effort (Man-Hrs) (SEG) | G4: =SUMIF($G$18:$G$86,"SEG",$H$18:$H$86) -> 0 | I4: =SUMIF($G$18:$G$86,"SEG",$J$18:$J$86) -> 0 | K4: =IF(G4=0,"",100*(G4-I4)/G4) | L4: =SUMIF($G$18:$G$86,"SEG",$L$18:$L$86) -> 0 | N4: =SUMIF($G$18:$G$86,"SEG",$N$18:$N$86) -> 0 | O4: =IF(L4=0,"",100*(L4-N4)/L4) | T4: L1 | Z4: =SUMIF($F$18:$F$86,"L1",$H$18:$H$86) -> 0 | AB4: =SUMIF($F$18:$F$86,"L1",$J$18:$J$86) -> 0 | AD4: =IF(Z4=0,"",100*(Z4-AB4)/Z4) | AE4: =SUMIF($F$18:$F$86,"L1",$L$18:$L$86) -> 0 | AG4: =SUMIF($F$18:$F$86,"L1",$N$18:$N$86) -> 0 | AH4: =IF(AE4=0,"",100*(AE4-AG4)/AE4)
A5: Testing Team Effort (Man-Hrs) (CTT) | G5: =SUMIF($G$18:$G$86,"CTT",$H$18:$H$86) -> 0 | I5: =SUMIF($G$18:$G$86,"CTT",$J$18:$J$86) -> 0 | K5: =IF(G5=0,"",100*(G5-I5)/G5) | L5: =SUMIF($G$18:$G$86,"CTT",$L$18:$L$86) -> 0 | N5: =SUMIF($G$18:$G$86,"CTT",$N$18:$N$86) -> 0 | O5: =IF(L5=0,"",100*(L5-N5)/L5) | T5: L2 | Z5: =SUMIF($F$18:$F$86,"L2",$H$18:$H$86) -> 0 | AB5: =SUMIF($F$18:$F$86,"L2",$J$18:$J$86) -> 0 | AD5: =IF(Z5=0,"",100*(Z5-AB5)/Z5) | AE5: =SUMIF($F$18:$F$86,"L2",$L$18:$L$86) -> 0 | AG5: =SUMIF($F$18:$F$86,"L2",$N$18:$N$86) -> 0 | AH5: =IF(AE5=0,"",100*(AE5-AG5)/AE5)
A6: Graphics Efforts (Man-Hrs) (GRA) | G6: =SUMIF($G$18:$G$86,"GRA",$H$18:$H$86) -> 0 | I6: =SUMIF($G$18:$G$86,"GRA",$J$18:$J$86) -> 0 | K6: =IF(G6=0,"",100*(G6-I6)/G6) | L6: =SUMIF($G$18:$G$86,"GRA",$L$18:$L$86) -> 0 | N6: =SUMIF($G$18:$G$86,"GRA",$N$18:$N$86) -> 0 | O6: =IF(L6=0,"",100*(L6-N6)/L6) | T6: L3 | Z6: =SUMIF($F$18:$F$86,"L3",$H$18:$H$86) -> 0 | AB6: =SUMIF($F$18:$F$86,"L3",$J$18:$J$86) -> 0 | AD6: =IF(Z6=0,"",100*(Z6-AB6)/Z6) | AE6: =SUMIF($F$18:$F$86,"L3",$L$18:$L$86) -> 0 | AG6: =SUMIF($F$18:$F$86,"L3",$N$18:$N$86) -> 0 | AH6: =IF(AE6=0,"",100*(AE6-AG6)/AE6)
A7: Tech. Writer Efforts (Man-Hrs) (TWR) | G7: =SUMIF($G$18:$G$86,"TWR",$H$18:$H$86) -> 0 | I7: =SUMIF($G$18:$G$86,"TWR",$J$18:$J$86) -> 0 | K7: =IF(G7=0,"",100*(G7-I7)/G7) | L7: =SUMIF($G$18:$G$86,"TWR",$L$18:$L$86) -> 0 | N7: =SUMIF($G$18:$G$86,"TWR",$N$18:$N$86) -> 0 | O7: =IF(L7=0,"",100*(L7-N7)/L7) | T7: L4 | Z7: =SUMIF($F$18:$F$86,"L4",$H$18:$H$86) -> 0 | AB7: =SUMIF($F$18:$F$86,"L4",$J$18:$J$86) -> 0 | AD7: =IF(Z7=0,"",100*(Z7-AB7)/Z7) | AE7: =SUMIF($F$18:$F$86,"L4",$L$18:$L$86) -> 0 | AG7: =SUMIF($F$18:$F$86,"L4",$N$18:$N$86) -> 0 | AH7: =IF(AE7=0,"",100*(AE7-AG7)/AE7)
A8: QAG Efforts (Man-Hrs) (QAG) | G8: =SUMIF($G$18:$G$86,"QAG",$H$18:$H$86) -> 0 | I8: =SUMIF($G$18:$G$86,"QAG",$J$18:$J$86) -> 0 | K8: =IF(G8=0,"",100*(G8-I8)/G8) | L8: =SUMIF($G$18:$G$86,"QAG",$L$18:$L$86) -> 0 | N8: =SUMIF($G$18:$G$86,"QAG",$N$18:$N$86) -> 0 | O8: =IF(L8=0,"",100*(L8-N8)/L8) | T8: L5 | Z8: =SUMIF($F$18:$F$86,"L5",$H$18:$H$86) -> 0 | AB8: =SUMIF($F$18:$F$86,"L5",$J$18:$J$86) -> 0 | AD8: =IF(Z8=0,"",100*(Z8-AB8)/Z8) | AE8: =SUMIF($F$18:$F$86,"L5",$L$18:$L$86) -> 0 | AG8: =SUMIF($F$18:$F$86,"L5",$N$18:$N$86) -> 0 | AH8: =IF(AE8=0,"",100*(AE8-AG8)/AE8) | AK8: Resource Type | AL8: Type Description | AR8: Resource Level | AT8: Availibility Status
A9: Organizational Efforts (Man-Hrs) (ORG) | G9: =SUMIF($G$18:$G$86,"ORG",$H$18:$H$86) -> 0 | I9: =SUMIF($G$18:$G$86,"ORG",$J$18:$J$86) -> 0 | K9: =IF(G9=0,"",100*(G9-I9)/G9) | L9: =SUMIF($G$18:$G$86,"ORG",$L$18:$L$86) -> 0 | N9: =SUMIF($G$18:$G$86,"ORG",$N$18:$N$86) -> 0 | O9: =IF(L9=0,"",100*(L9-N9)/L9) | T9: L6 | Z9: =SUMIF($F$18:$F$86,"L6",$H$18:$H$86) -> 0 | AB9: =SUMIF($F$18:$F$86,"L6",$J$18:$J$86) -> 0 | AD9: =IF(Z9=0,"",100*(Z9-AB9)/Z9) | AE9: =SUMIF($F$18:$F$86,"L6",$L$18:$L$86) -> 0 | AG9: =SUMIF($F$18:$F$86,"L6",$N$18:$N$86) -> 0 | AH9: =IF(AE9=0,"",100*(AE9-AG9)/AE9)
A10: PM Efforts (Man-Hrs) (PMS) | G10: =SUMIF($G$18:$G$86,"PMS",$H$18:$H$86) -> 0 | I10: =SUMIF($G$18:$G$86,"PMS",$J$18:$J$86) -> 0 | K10: =IF(G10=0,"",100*(G10-I10)/G10) | L10: =SUMIF($G$18:$G$86,"PMS",$L$18:$L$86) -> 0 | N10: =SUMIF($G$18:$G$86,"PMS",$N$18:$N$86) -> 0 | O10: =IF(L10=0,"",100*(L10-N10)/L10) | T10: L7 | Z10: =SUMIF($F$18:$F$86,"L7",$H$18:$H$86) -> 0 | AB10: =SUMIF($F$18:$F$86,"L7",$J$18:$J$86) -> 0 | AD10: =IF(Z10=0,"",100*(Z10-AB10)/Z10) | AE10: =SUMIF($F$18:$F$86,"L7",$L$18:$L$86) -> 0 | AG10: =SUMIF($F$18:$F$86,"L7",$N$18:$N$86) -> 0 | AH10: =IF(AE10=0,"",100*(AE10-AG10)/AE10) | AK10: SEG | AL10: Project Team Effort (Man-Hrs) (SEG) | AR10: L1 | AT10: Not Available
A11: Architecture (Man-Hrs) (ARC) | G11: =SUMIF($G$18:$G$86,"ARC",$H$18:$H$86) -> 0 | I11: =SUMIF($G$18:$G$86,"ARC",$J$18:$J$86) -> 0 | K11: =IF(G11=0,"",100*(G11-I11)/G11) | L11: =SUMIF($G$18:$G$86,"ARC",$L$18:$L$86) -> 0 | N11: =SUMIF($G$18:$G$86,"ARC",$N$18:$N$86) -> 0 | O11: =IF(L11=0,"",100*(L11-N11)/L11) | T11: L8 | Z11: =SUMIF($F$18:$F$86,"L8",$H$18:$H$86) -> 0 | AB11: =SUMIF($F$18:$F$86,"L8",$J$18:$J$86) -> 0 | AD11: =IF(Z11=0,"",100*(Z11-AB11)/Z11) | AE11: =SUMIF($F$18:$F$86,"L8",$L$18:$L$86) -> 0 | AG11: =SUMIF($F$18:$F$86,"L8",$N$18:$N$86) -> 0 | AH11: =IF(AE11=0,"",100*(AE11-AG11)/AE11) | AK11: CTT | AL11: Testing Team Effort (Man-Hrs) (CTT) | AR11: L2 | AT11: Resigned
A12: Business Analyst Efforts (Man-Hrs) (BAS) | G12: =SUMIF($G$18:$G$86,"BAS",$H$18:$H$86) -> 0 | I12: =SUMIF($G$18:$G$86,"BAS",$J$18:$J$86) -> 0 | K12: =IF(G12=0,"",100*(G12-I12)/G12) | L12: =SUMIF($G$18:$G$86,"BAS",$L$18:$L$86) -> 0 | N12: =SUMIF($G$18:$G$86,"BAS",$N$18:$N$86) -> 0 | O12: =IF(L12=0,"",100*(L12-N12)/L12) | T12: L9 | Z12: =SUMIF($F$18:$F$86,"L9",$H$18:$H$86) -> 0 | AB12: =SUMIF($F$18:$F$86,"L9",$J$18:$J$86) -> 0 | AD12: =IF(Z12=0,"",100*(Z12-AB12)/Z12) | AE12: =SUMIF($F$18:$F$86,"L9",$L$18:$L$86) -> 0 | AG12: =SUMIF($F$18:$F$86,"L9",$N$18:$N$86) -> 0 | AH12: =IF(AE12=0,"",100*(AE12-AG12)/AE12) | AK12: GRA | AL12: Graphics Efforts (Man-Hrs) (GRA) | AR12: L3 | AT12: Available
A13: PMO Efforts (Man-Hrs) (PMO) | G13: =SUMIF($G$18:$G$86,"PMO",$H$18:$H$86) -> 0 | I13: =SUMIF($G$18:$G$86,"PMO",$J$18:$J$86) -> 0 | K13: =IF(G13=0,"",100*(G13-I13)/G13) | L13: =SUMIF($G$18:$G$86,"PMO",$L$18:$L$86) -> 0 | N13: =SUMIF($G$18:$G$29,"PMO",$N$18:$N$29) -> 0 | O13: =IF(L13=0,"",100*(L13-N13)/L13) | T13: L10 | Z13: =SUMIF($F$18:$F$86,"L10",$H$18:$H$86) -> 0 | AB13: =SUMIF($F$18:$F$86,"L10",$J$18:$J$86) -> 0 | AD13: =IF(Z13=0,"",100*(Z13-AB13)/Z13) | AE13: =SUMIF($F$18:$F$86,"L10",$L$18:$L$86) -> 0 | AG13: =SUMIF($F$18:$F$86,"L10",$N$18:$N$86) -> 0 | AH13: =IF(AE13=0,"",100*(AE13-AG13)/AE13) | AK13: TWR | AL13: Tech. Writer Efforts (Man-Hrs) (TWR) | AR13: L4
A14: Total Project Efforts | G14: =SUM(G4:G13) -> 0 | I14: =SUM(I4:I13) -> 0 | K14: =IF(G14=0,"",100*((G14-I14)/G14)) | L14: =SUM(L4:L13) -> 0 | N14: =SUM(N4:N13) -> 0 | O14: =IF(L14=0,"",100*(L14-N14)/L14) | T14: Total Project Efforts | Z14: =SUM(Z4:Z13) -> 0 | AB14: =SUM(AB4:AB13) -> 0 | AD14: =IF(Z14=0,"",100*((Z14-AB14)/Z14)) | AE14: =SUM(AE4:AE13) -> 0 | AG14: =SUM(AG4:AG13) -> 0 | AH14: =IF(AE14=0,"",100*(AE14-AG14)/AE14) | AK14: QAG | AL14: QAG Efforts (Man-Hrs) (QAG) | AR14: L5
AK15: ORG | AL15: Organizational Efforts (Man-Hrs) (ORG) | AR15: L6
A16: Employee Code | B16: Name of Resource | F16: Level | G16: Type | H16: Offshore Effort (Current Month) | K16: Deviation (%) | L16: Onsite (Current Month) | O16: Deviation (%) | P16: Availibility Status | T16: %Billable (Planned in Current Month) | Z16: %Billable (Actual in Current Month) | AK16: PMS | AL16: PM Efforts (Man-Hrs) (PMS) | AR16: L7
H17: Effort Planned | J17: Effort Spent | K17: Deviation (%) | L17: Effort Planned | N17: Effort Spent | O17: Deviation (%) | AK17: ARC | AL17: Architecture (Man-Hrs) (ARC) | AR17: L8
K18: =IF(H18="","",100*((H18-J18)/H18)) | O18: =IF(L18="","",100*((L18-N18)/L18)) | P18: Available | Q18: =IF(P18<>"Available ",0,1) -> 0 | R18: =IF(P18<>"Resigned",0,1) -> 0 | S18: =IF(P18<>"Not Available",0,1) -> 0 | T18: =(H18+L18)*100/160 -> 0 | Z18: =(J18+N18)*100/160 -> 0 | AK18: BAS | AL18: Business Analyst Efforts (Man-Hrs) (BAS) | AR18: L9
K19: =IF(H19="","",100*((H19-J19)/H19)) | O19: =IF(L19="","",100*((L19-N19)/L19)) | P19: Available | Q19: =IF(P19<>"Available ",0,1) -> 0 | R19: =IF(P19<>"Resigned",0,1) -> 0 | S19: =IF(P19<>"Not Available",0,1) -> 0 | T19: =(H19+L19)*100/160 -> 0 | Z19: =(J19+N19)*100/160 -> 0 | AK19: PMO | AL19: PMO Efforts (Man-Hrs) (PMO) | AR19: L10
K20: =IF(H20="","",100*((H20-J20)/H20)) | O20: =IF(L20="","",100*((L20-N20)/L20)) | P20: Available | Q20: =IF(P20<>"Available ",0,1) -> 0 | R20: =IF(P20<>"Resigned",0,1) -> 0 | S20: =IF(P20<>"Not Available",0,1) -> 0 | T20: =(H20+L20)*100/160 -> 0 | Z20: =(J20+N20)*100/160 -> 0
K21: =IF(H21="","",100*((H21-J21)/H21)) | O21: =IF(L21="","",100*((L21-N21)/L21)) | P21: Available | Q21: =IF(P21<>"Available ",0,1) -> 0 | R21: =IF(P21<>"Resigned",0,1) -> 0 | S21: =IF(P21<>"Not Available",0,1) -> 0 | T21: =(H21+L21)*100/160 -> 0 | Z21: =(J21+N21)*100/160 -> 0
K22: =IF(H22="","",100*((H22-J22)/H22)) | O22: =IF(L22="","",100*((L22-N22)/L22)) | P22: Available | Q22: =IF(P22<>"Available ",0,1) -> 0 | R22: =IF(P22<>"Resigned",0,1) -> 0 | S22: =IF(P22<>"Not Available",0,1) -> 0 | T22: =(H22+L22)*100/160 -> 0 | Z22: =(J22+N22)*100/160 -> 0
K23: =IF(H23="","",100*((H23-J23)/H23)) | O23: =IF(L23="","",100*((L23-N23)/L23)) | P23: Available | Q23: =IF(P23<>"Available ",0,1) -> 0 | R23: =IF(P23<>"Resigned",0,1) -> 0 | S23: =IF(P23<>"Not Available",0,1) -> 0 | T23: =(H23+L23)*100/160 -> 0 | Z23: =(J23+N23)*100/160 -> 0
K24: =IF(H24="","",100*((H24-J24)/H24)) | O24: =IF(L24="","",100*((L24-N24)/L24)) | P24: Available | Q24: =IF(P24<>"Available ",0,1) -> 0 | R24: =IF(P24<>"Resigned",0,1) -> 0 | S24: =IF(P24<>"Not Available",0,1) -> 0 | T24: =(H24+L24)*100/160 -> 0 | Z24: =(J24+N24)*100/160 -> 0
K25: =IF(H25="","",100*((H25-J25)/H25)) | O25: =IF(L25="","",100*((L25-N25)/L25)) | P25: Available | Q25: =IF(P25<>"Available ",0,1) -> 0 | R25: =IF(P25<>"Resigned",0,1) -> 0 | S25: =IF(P25<>"Not Available",0,1) -> 0 | T25: =(H25+L25)*100/160 -> 0 | Z25: =(J25+N25)*100/160 -> 0
K26: =IF(H26="","",100*((H26-J26)/H26)) | O26: =IF(L26="","",100*((L26-N26)/L26)) | P26: Available | Q26: =IF(P26<>"Available ",0,1) -> 0 | R26: =IF(P26<>"Resigned",0,1) -> 0 | S26: =IF(P26<>"Not Available",0,1) -> 0 | T26: =(H26+L26)*100/160 -> 0 | Z26: =(J26+N26)*100/160 -> 0
K27: =IF(H27="","",100*((H27-J27)/H27)) | O27: =IF(L27="","",100*((L27-N27)/L27)) | P27: Available | Q27: =IF(P27<>"Available ",0,1) -> 0 | R27: =IF(P27<>"Resigned",0,1) -> 0 | S27: =IF(P27<>"Not Available",0,1) -> 0 | T27: =(H27+L27)*100/160 -> 0 | Z27: =(J27+N27)*100/160 -> 0
K28: =IF(H28="","",100*((H28-J28)/H28)) | O28: =IF(L28="","",100*((L28-N28)/L28)) | P28: Available | Q28: =IF(P28<>"Available ",0,1) -> 0 | R28: =IF(P28<>"Resigned",0,1) -> 0 | S28: =IF(P28<>"Not Available",0,1) -> 0 | T28: =(H28+L28)*100/160 -> 0 | Z28: =(J28+N28)*100/160 -> 0
K29: =IF(H29="","",100*((H29-J29)/H29)) | O29: =IF(L29="","",100*((L29-N29)/L29)) | P29: Available | Q29: =IF(P29<>"Available ",0,1) -> 0 | R29: =IF(P29<>"Resigned",0,1) -> 0 | S29: =IF(P29<>"Not Available",0,1) -> 0 | T29: =(H29+L29)*100/160 -> 0 | Z29: =(J29+N29)*100/160 -> 0
K30: =IF(H30="","",100*((H30-J30)/H30)) | O30: =IF(L30="","",100*((L30-N30)/L30)) | Q30: =IF(P30<>"Available ",0,1) -> 0 | R30: =IF(P30<>"Resigned",0,1) -> 0 | S30: =IF(P30<>"Not Available",0,1) -> 0 | T30: =(H30+L30)*100/160 -> 0 | Z30: =(J30+N30)*100/160 -> 0
K31: =IF(H31="","",100*((H31-J31)/H31)) | O31: =IF(L31="","",100*((L31-N31)/L31)) | Q31: =IF(P31<>"Available ",0,1) -> 0 | R31: =IF(P31<>"Resigned",0,1) -> 0 | S31: =IF(P31<>"Not Available",0,1) -> 0 | T31: =(H31+L31)*100/160 -> 0 | Z31: =(J31+N31)*100/160 -> 0
K32: =IF(H32="","",100*((H32-J32)/H32)) | O32: =IF(L32="","",100*((L32-N32)/L32)) | Q32: =IF(P32<>"Available ",0,1) -> 0 | R32: =IF(P32<>"Resigned",0,1) -> 0 | S32: =IF(P32<>"Not Available",0,1) -> 0 | T32: =(H32+L32)*100/160 -> 0 | Z32: =(J32+N32)*100/160 -> 0
K33: =IF(H33="","",100*((H33-J33)/H33)) | O33: =IF(L33="","",100*((L33-N33)/L33)) | Q33: =IF(P33<>"Available ",0,1) -> 0 | R33: =IF(P33<>"Resigned",0,1) -> 0 | S33: =IF(P33<>"Not Available",0,1) -> 0 | T33: =(H33+L33)*100/160 -> 0 | Z33: =(J33+N33)*100/160 -> 0
K34: =IF(H34="","",100*((H34-J34)/H34)) | O34: =IF(L34="","",100*((L34-N34)/L34)) | Q34: =IF(P34<>"Available ",0,1) -> 0 | R34: =IF(P34<>"Resigned",0,1) -> 0 | S34: =IF(P34<>"Not Available",0,1) -> 0 | T34: =(H34+L34)*100/160 -> 0 | Z34: =(J34+N34)*100/160 -> 0
K35: =IF(H35="","",100*((H35-J35)/H35)) | O35: =IF(L35="","",100*((L35-N35)/L35)) | Q35: =IF(P35<>"Available ",0,1) -> 0 | R35: =IF(P35<>"Resigned",0,1) -> 0 | S35: =IF(P35<>"Not Available",0,1) -> 0 | T35: =(H35+L35)*100/160 -> 0 | Z35: =(J35+N35)*100/160 -> 0
K36: =IF(H36="","",100*((H36-J36)/H36)) | O36: =IF(L36="","",100*((L36-N36)/L36)) | Q36: =IF(P36<>"Available ",0,1) -> 0 | R36: =IF(P36<>"Resigned",0,1) -> 0 | S36: =IF(P36<>"Not Available",0,1) -> 0 | T36: =(H36+L36)*100/160 -> 0 | Z36: =(J36+N36)*100/160 -> 0
K37: =IF(H37="","",100*((H37-J37)/H37)) | O37: =IF(L37="","",100*((L37-N37)/L37)) | Q37: =IF(P37<>"Available ",0,1) -> 0 | R37: =IF(P37<>"Resigned",0,1) -> 0 | S37: =IF(P37<>"Not Available",0,1) -> 0 | T37: =(H37+L37)*100/160 -> 0 | Z37: =(J37+N37)*100/160 -> 0
K38: =IF(H38="","",100*((H38-J38)/H38)) | O38: =IF(L38="","",100*((L38-N38)/L38)) | Q38: =IF(P38<>"Available ",0,1) -> 0 | R38: =IF(P38<>"Resigned",0,1) -> 0 | S38: =IF(P38<>"Not Available",0,1) -> 0 | T38: =(H38+L38)*100/160 -> 0 | Z38: =(J38+N38)*100/160 -> 0
K39: =IF(H39="","",100*((H39-J39)/H39)) | O39: =IF(L39="","",100*((L39-N39)/L39)) | Q39: =IF(P39<>"Available ",0,1) -> 0 | R39: =IF(P39<>"Resigned",0,1) -> 0 | S39: =IF(P39<>"Not Available",0,1) -> 0 | T39: =(H39+L39)*100/160 -> 0 | Z39: =(J39+N39)*100/160 -> 0
K40: =IF(H40="","",100*((H40-J40)/H40)) | O40: =IF(L40="","",100*((L40-N40)/L40)) | Q40: =IF(P40<>"Available ",0,1) -> 0 | R40: =IF(P40<>"Resigned",0,1) -> 0 | S40: =IF(P40<>"Not Available",0,1) -> 0 | T40: =(H40+L40)*100/160 -> 0 | Z40: =(J40+N40)*100/160 -> 0
K41: =IF(H41="","",100*((H41-J41)/H41)) | O41: =IF(L41="","",100*((L41-N41)/L41)) | Q41: =IF(P41<>"Available ",0,1) -> 0 | R41: =IF(P41<>"Resigned",0,1) -> 0 | S41: =IF(P41<>"Not Available",0,1) -> 0 | T41: =(H41+L41)*100/160 -> 0 | Z41: =(J41+N41)*100/160 -> 0
... K86: =IF(H86="","",100*((H86-J86)/H86)) | O86: =IF(L86="","",100*((L86-N86)/L86)) | Q86: =IF(P86<>"Available ",0,1) -> 0 | R86: =IF(P86<>"Resigned",0,1) -> 0 | S86: =IF(P86<>"Not Available",0,1) -> 0 | T86: =(H86+L86)*100/160 -> 0 | Z86: =(J86+N86)*100/160 -> 0

Sheet Metrics planning and tracking
A1: Id. | B1: Objective | C1: Source of Objective | D1: Metric | E1: Unit | F1: Required measures | G1: Definition | H1: Priority | I1: Organization baseline (if applicable) | J1: SDC / Centre baseline | K1: Project Goal | L1: Upper specification limit | M1: Lower specification limit | N1: Current Value | O1: Analysis model / methodologies | P1: Tracking remarks
A2: 1 | B2: Improve Delivery Variances | C2: Organizational Measurement Objectives | D2: Effort Variation - Initial | E2: % | F2: Initial effort estimated and Actual effort | G2: (Actual effort - Estimated effort) x 100 Estimated effort | H2: Medium | I2: 0.1 | J2: 0.1 | K2: 10 | L2: 15 | M2: 0 | N2: =IF(S2<>0,IF(U2<>0,(U2-S2)/S2%,"Not Available"),"Not Available") -> Not Available | S2: =SUMIF('Size, Schedule and Effort'!O3:O496,"Completed",'Size, Schedule and Effort'!H3:H496) -> 0 | T2: =SUMIF('Size, Schedule and Effort'!O3:O496,"Completed",'Size, Schedule and Effort'!W3:W496) -> 0 | U2: =SUMIF('Size, Schedule and Effort'!O3:O496,"Completed",'Size, Schedule and Effort'!J3:J496) -> 0
A3: 2 | B3: Improve Delivery Variances | C3: Organizational Measurement Objectives | D3: Effort Variation - Baselined | E3: % | F3: Last baselined effort estimate and Actual effort | G3: (Actual effort - Baselined effort) x 100 Baslined effort | H3: High | I3: 0.05 | J3: 0.05 | K3: 5 | L3: 10 | M3: 0 | N3: =IF(T2<>0,IF(U2<>0,(U2-T2)/T2%,"Not Available"),"Not Available") -> Not Available
A4: 3 | B4: Improve Delivery Variances | C4: Organizational Measurement Objectives | D4: Schedule Variation - Initial | E4: % | F4: Schedule | G4: (Actual completion date - Estimated completion date) x 100 / (Estimated duration) | H4: Medium | I4: 0.1 | J4: 0.1 | K4: 10 | L4: 15 | M4: 0 | N4: {=IF(COUNT('Project information1'!D2:D3,'Project information1'!D6:D7)<4,IF(COUNT('Size, Schedule and Effort'!K$3:K$496)>0,MAX(IF('Size, Schedule and Effort'!G$3:G$496 = MAX('Size, Schedule and Effort'!G$3:G$496),'Size, Schedule and Effort'!K$3:K$496,"")),"Not Available"),('Project information1'!D7-'Project information1'!D3)/('Project information1'!D3-'Project information1'!D2+1)*100)} -> Not Available
A5: 4 | B5: Improve Delivery Variances | C5: Organizational Measurement Objectives | D5: Schedule Variation - Baselined | E5: % | F5: Schedule | G5: (Actual completion date - Last Baselined completion date) x 100 / (Last baselined duration) | H5: High | I5: 0.05 | J5: 0.05 | K5: 5 | L5: 10 | M5: 0 | N5: {=IF(COUNT('Project information1'!D4:D5,'Project information1'!D6:D7)<4,IF(COUNT('Size, Schedule and Effort'!L$3:L$496)>0,MAX(IF('Size, Schedule and Effort'!G$3:G$496 = MAX('Size, Schedule and Effort'!G$3:G$496),'Size, Schedule and Effort'!L$3:L$496,"")),"Not Available"),('Project information1'!D7-'Project information1'!D5)/('Project information1'!D5-'Project information1'!D4+1)*100)} -> Not Available
A6: 5 | B6: Improve Productivity and reduce Cost of Software Production | C6: Organizational Measurement Objectives | D6: Productivity | E6: ='Project information1'!B13 & " / " & 'Project information1'!D11 -> / | F6: Actual Size and effort data | G6: Actual Size Actual Effort | H6: High | I6: 0.17 | J6: 0.17 | K6: 0.16 | L6: 0.18 | M6: 0.15 | N6: =IF('Project information1'!B16<>"",IF(AND('Project information1'!B150<>"",'Project information1'!D10<>0),'Project information1'!B16/'Project information1'!B15,"NA"),"Not Available") -> Not Available
A7: 6 | B7: Reduce Pre and Post Delivery Defects in all Deliveries | C7: Organizational Measurement Objectives | D7: Weighted Defect density | E7: ="Weighted defects / " & 'Project information1'!B13 -> Weighted defects / | F7: Actual Size, Review issues and test defects | G7: Total Weighted Defects found / Actual project size | H7: High | I7: 0.002 | J7: 0.002 | K7: 0.002 | L7: 0.003 | M7: 0 | N7: =IF(AND(SUM(S7:X7)>0,Y7<>"NA"),((S7+V7)+0.33*(T7+W7)+0.2*(U7+X7))/(Y7),"Not Available") -> #REF! | S7: =SUM('Verification Summary'!E10:E24) -> 0 | T7: =SUM('Verification Summary'!F10:F24) -> 0 | U7: =SUM('Verification Summary'!G10:G24) -> 0 | V7: =SUM('Verification Summary'!K10:K24) -> 0 | W7: =SUM('Verification Summary'!L10:L24) -> 0 | X7: =SUM('Verification Summary'!M10:M24) -> 0 | Y7: =IF('Project information1'!B12<>"",'Project information1'!B12,IF('Project information1'!B11<>"",'Project information1'!B11,IF('Project information1'!B10<>"",'Project information1'!B10,"NA"))) -> #REF! | Z7: =IF('Project information1'!B12<>"","A",IF('Project information1'!B11<>"","R",IF('Project information1'!B10<>"","P","NA"))) -> #REF!
A8: 7 | B8: Reduce Pre and Post Delivery Defects in all Deliveries | C8: Organizational Measurement Objectives | D8: Review efficiency | E8: % | F8: Total review issues and testing issues | G8: [(No. of Weighted Defects found in Review) / Total No. of Weighted Defects found before Delivery (both Reviews and Testing) ]* 100 | H8: High | I8: 0.7 | J8: 0.7 | K8: 0.7 | L8: 0.95 | M8: 0.6 | N8: =IF(SUM(S7:X7)>0,(1*S7+0.33*T7+0.2*U7)/(1*(S7+V7)+0.33*(T7+W7)+0.2*(U7+X7))%,"Not Available") -> Not Available
A9: 8 | B9: Reduce Pre and Post Delivery Defects in all Deliveries | C9: Organizational Measurement Objectives | D9: Defect removal efficiency | E9: % | F9: Defects detected before release and post release defects | G9: DRE= (E/ E+D) x 100 where E = weighted Pre-delivery errors (detected during all QC / QA) activities D= weighted Post –delivery Defects | H9: High | I9: 0.9 | J9: 0.9 | K9: 0.9 | L9: 1 | M9: 0.8 | N9: =IF(SUM(S7:X7,S9:X9)>0,(1*(S7+V7)+0.33*(T7+W7)+0.2*(U7+X7))/(1*(S7+V7+S9+V9)+0.33*(T7+W7+T9+W9)+0.2*(U7+X7+U9+X9))*100,"Not Available") -> Not Available | S9: =SUM('Verification Summary'!E29:E43) -> 0 | T9: =SUM('Verification Summary'!F29:F43) -> 0 | U9: =SUM('Verification Summary'!G29:G43) -> 0 | V9: =SUM('Verification Summary'!K29:K43) -> 0 | W9: =SUM('Verification Summary'!L29:L43) -> 0 | X9: =SUM('Verification Summary'!M29:M43) -> 0

Sheet Risk Management
J1: Initial | R1: Current
A2: Date identified | B2: Risk Category | C2: Risk Source | D2: Process where Identified | E2: Risk Title | F2: Risk description | G2: Relevant ISMS Control | H2: Relevance (ISMS, QMS, Both) | I2: Owner | J2: Probability | K2: Impact on Cost | L2: Impact on Schedule | M2: Impact on Scope | N2: Impact on Quality | O2: Regulatory Impact | P2: Normalized Impact | Q2: Risk Index - Initial | R2: Probability | S2: Impact on Cost | T2: Impact on Schedule | U2: Impact on Scope | V2: Impact on Quality | W2: Regulatory Impact | X2: Normalized Impact | Y2: Risk Index - Current | Z2: Risk Treatment Plan (Accept, Mitigate, Avoid, Transfer) | AA2: Cost of Risk | AB2: Cost of Mitigation Plan | AC2: Cost / Benefit ratio | AD2: Escalation threshold | AE2: Mitigation plan | AF2: Contingency plan | AG2: External (Impacts customer) / Internal | AH2: Remarks | AI2: Update date | AJ2: Status | AK2: Rev Prob | AL2: Rev Impact | AM2: Rev Risk index | AN2: Status-1
AK3: =IF(R3<>"",R3,IF(J3,J3,"")) | AL3: =IF(X3<>"",X3,IF(P3=1,P3,"")) | AM3: =IF(Y3<>"",Y3,IF(Q3=1,Q3,"")) | AN3: =IF(COUNT(AK3:AM3)>2,IF(AJ3<>"",IF(ISERROR(SEARCH("open",AJ3,1)),"Closed","Open"),"Open"),"") | AP3: =IF(ISERROR(SMALL(#REF!,ROW()-2)),"",INDIRECT("'Control panel'!A" & SMALL(#REF!,ROW()-2),1))
AK4: =IF(R4<>"",R4,IF(J4,J4,"")) | AL4: =IF(X4<>"",X4,IF(P4=1,P4,"")) | AM4: =IF(Y4<>"",Y4,IF(Q4=1,Q4,"")) | AN4: =IF(COUNT(AK4:AM4)>2,IF(AJ4<>"",IF(ISERROR(SEARCH("open",AJ4,1)),"Closed","Open"),"Open"),"") | AP4: =IF(ISERROR(SMALL(#REF!,ROW()-2)),"",INDIRECT("'Control panel'!A" & SMALL(#REF!,ROW()-2),1))
AK5: =IF(R5<>"",R5,IF(J5,J5,"")) | AL5: =IF(X5<>"",X5,IF(P5=1,P5,"")) | AM5: =IF(Y5<>"",Y5,IF(Q5=1,Q5,"")) | AN5: =IF(COUNT(AK5:AM5)>2,IF(AJ5<>"",IF(ISERROR(SEARCH("open",AJ5,1)),"Closed","Open"),"Open"),"") | AP5: =IF(ISERROR(SMALL(#REF!,ROW()-2)),"",INDIRECT("'Control panel'!A" & SMALL(#REF!,ROW()-2),1))
AK6: =IF(R6<>"",R6,IF(J6,J6,"")) | AL6: =IF(X6<>"",X6,IF(P6=1,P6,"")) | AM6: =IF(Y6<>"",Y6,IF(Q6=1,Q6,"")) | AN6: =IF(COUNT(AK6:AM6)>2,IF(AJ6<>"",IF(ISERROR(SEARCH("open",AJ6,1)),"Closed","Open"),"Open"),"") | AP6: =IF(ISERROR(SMALL(#REF!,ROW()-2)),"",INDIRECT("'Control panel'!A" & SMALL(#REF!,ROW()-2),1))
AK7: =IF(R7<>"",R7,IF(J7,J7,"")) | AL7: =IF(X7<>"",X7,IF(P7=1,P7,"")) | AM7: =IF(Y7<>"",Y7,IF(Q7=1,Q7,"")) | AN7: =IF(COUNT(AK7:AM7)>2,IF(AJ7<>"",IF(ISERROR(SEARCH("open",AJ7,1)),"Closed","Open"),"Open"),"") | AP7: =IF(ISERROR(SMALL(#REF!,ROW()-2)),"",INDIRECT("'Control panel'!A" & SMALL(#REF!,ROW()-2),1))
AK8: =IF(R8<>"",R8,IF(J8,J8,"")) | AL8: =IF(X8<>"",X8,IF(P8=1,P8,"")) | AM8: =IF(Y8<>"",Y8,IF(Q8=1,Q8,"")) | AN8: =IF(COUNT(AK8:AM8)>2,IF(AJ8<>"",IF(ISERROR(SEARCH("open",AJ8,1)),"Closed","Open"),"Open"),"") | AP8: =IF(ISERROR(SMALL(#REF!,ROW()-2)),"",INDIRECT("'Control panel'!A" & SMALL(#REF!,ROW()-2),1))
AK9: =IF(R9<>"",R9,IF(J9,J9,"")) | AL9: =IF(X9<>"",X9,IF(P9=1,P9,"")) | AM9: =IF(Y9<>"",Y9,IF(Q9=1,Q9,"")) | AN9: =IF(COUNT(AK9:AM9)>2,IF(AJ9<>"",IF(ISERROR(SEARCH("open",AJ9,1)),"Closed","Open"),"Open"),"") | AP9: =IF(ISERROR(SMALL(#REF!,ROW()-2)),"",INDIRECT("'Control panel'!A" & SMALL(#REF!,ROW()-2),1))
AK10: =IF(R10<>"",R10,IF(J10,J10,"")) | AL10: =IF(X10<>"",X10,IF(P10=1,P10,"")) | AM10: =IF(Y10<>"",Y10,IF(Q10=1,Q10,"")) | AN10: =IF(COUNT(AK10:AM10)>2,IF(AJ10<>"",IF(ISERROR(SEARCH("open",AJ10,1)),"Closed","Open"),"Open"),"") | AP10: =IF(ISERROR(SMALL(#REF!,ROW()-2)),"",INDIRECT("'Control panel'!A" & SMALL(#REF!,ROW()-2),1))
AK11: =IF(R11<>"",R11,IF(J11,J11,"")) | AL11: =IF(X11<>"",X11,IF(P11=1,P11,"")) | AM11: =IF(Y11<>"",Y11,IF(Q11=1,Q11,"")) | AN11: =IF(COUNT(AK11:AM11)>2,IF(AJ11<>"",IF(ISERROR(SEARCH("open",AJ11,1)),"Closed","Open"),"Open"),"") | AP11: =IF(ISERROR(SMALL(#REF!,ROW()-2)),"",INDIRECT("'Control panel'!A" & SMALL(#REF!,ROW()-2),1))
AK12: =IF(R12<>"",R12,IF(J12,J12,"")) | AL12: =IF(X12<>"",X12,IF(P12=1,P12,"")) | AM12: =IF(Y12<>"",Y12,IF(Q12=1,Q12,"")) | AN12: =IF(COUNT(AK12:AM12)>2,IF(AJ12<>"",IF(ISERROR(SEARCH("open",AJ12,1)),"Closed","Open"),"Open"),"") | AP12: =IF(ISERROR(SMALL(#REF!,ROW()-2)),"",INDIRECT("'Control panel'!A" & SMALL(#REF!,ROW()-2),1))
AK13: =IF(R13<>"",R13,IF(J13,J13,"")) | AL13: =IF(X13<>"",X13,IF(P13=1,P13,"")) | AM13: =IF(Y13<>"",Y13,IF(Q13=1,Q13,"")) | AN13: =IF(COUNT(AK13:AM13)>2,IF(AJ13<>"",IF(ISERROR(SEARCH("open",AJ13,1)),"Closed","Open"),"Open"),"") | AP13: =IF(ISERROR(SMALL(#REF!,ROW()-2)),"",INDIRECT("'Control panel'!A" & SMALL(#REF!,ROW()-2),1))
AK14: =IF(R14<>"",R14,IF(J14,J14,"")) | AL14: =IF(X14<>"",X14,IF(P14=1,P14,"")) | AM14: =IF(Y14<>"",Y14,IF(Q14=1,Q14,"")) | AN14: =IF(COUNT(AK14:AM14)>2,IF(AJ14<>"",IF(ISERROR(SEARCH("open",AJ14,1)),"Closed","Open"),"Open"),"") | AP14: =IF(ISERROR(SMALL(#REF!,ROW()-2)),"",INDIRECT("'Control panel'!A" & SMALL(#REF!,ROW()-2),1))
... AK45: =IF(R45<>"",R45,IF(J45,J45,"")) | AL45: =IF(X45<>"",X45,IF(P45=1,P45,"")) | AM45: =IF(Y45<>"",Y45,IF(Q45=1,Q45,"")) | AN45: =IF(COUNT(AK45:AM45)>2,IF(AJ45<>"",IF(ISERROR(SEARCH("open",AJ45,1)),"Closed","Open"),"Open"),"") | AP45: =IF(ISERROR(SMALL(#REF!,ROW()-2)),"",INDIRECT("'Control panel'!A" & SMALL(#REF!,ROW()-2),1))
P46: =IF(COUNT(K46:O46)>0,AVERAGE(K46:O46),"") | Q46: =IF(P46<>"",IF(J46<>"",P46*J46,"Probability?"),"") | X46: =IF(COUNT(S46:W46)>0,AVERAGE(S46:W46),"") | Y46: =IF(X46<>"",IF(R46<>"",X46*R46,"Probability?"),"") | AC46: =IF(AA46<>"",IF(AB46<>"",AB46/AA46,""),"") | AK46: =IF(R46<>"",R46,IF(J46,J46,"")) | AL46: =IF(X46<>"",X46,IF(P46=1,P46,"")) | AM46: =IF(Y46<>"",Y46,IF(Q46=1,Q46,"")) | AN46: =IF(COUNT(AK46:AM46)>2,IF(AJ46<>"",IF(ISERROR(SEARCH("open",AJ46,1)),"Closed","Open"),"Open"),"") | AP46: =IF(ISERROR(SMALL(#REF!,ROW()-2)),"",INDIRECT("'Control panel'!A" & SMALL(#REF!,ROW()-2),1))
P47: =IF(COUNT(K47:O47)>0,AVERAGE(K47:O47),"") | Q47: =IF(P47<>"",IF(J47<>"",P47*J47,"Probability?"),"") | X47: =IF(COUNT(S47:W47)>0,AVERAGE(S47:W47),"") | Y47: =IF(X47<>"",IF(R47<>"",X47*R47,"Probability?"),"") | AK47: =IF(R47<>"",R47,IF(J47,J47,"")) | AL47: =IF(X47<>"",X47,IF(P47=1,P47,"")) | AM47: =IF(Y47<>"",Y47,IF(Q47=1,Q47,"")) | AN47: =IF(COUNT(AK47:AM47)>2,IF(AJ47<>"",IF(ISERROR(SEARCH("open",AJ47,1)),"Closed","Open"),"Open"),"")
P48: =IF(COUNT(K48:O48)>0,AVERAGE(K48:O48),"") | Q48: =IF(P48<>"",IF(J48<>"",P48*J48,"Probability?"),"") | X48: =IF(COUNT(S48:W48)>0,AVERAGE(S48:W48),"") | Y48: =IF(X48<>"",IF(R48<>"",X48*R48,"Probability?"),"") | AK48: =IF(R48<>"",R48,IF(J48,J48,"")) | AL48: =IF(X48<>"",X48,IF(P48=1,P48,"")) | AM48: =IF(Y48<>"",Y48,IF(Q48=1,Q48,"")) | AN48: =IF(COUNT(AK48:AM48)>2,IF(AJ48<>"",IF(ISERROR(SEARCH("open",AJ48,1)),"Closed","Open"),"Open"),"") | AP48: =IF(ISERROR(SMALL(#REF!,ROW()-2)),"",INDIRECT("'Control panel'!A" & SMALL(#REF!,ROW()-2),1))
P49: =IF(COUNT(K49:O49)>0,AVERAGE(K49:O49),"") | Q49: =IF(P49<>"",IF(J49<>"",P49*J49,"Probability?"),"") | X49: =IF(COUNT(S49:W49)>0,AVERAGE(S49:W49),"") | Y49: =IF(X49<>"",IF(R49<>"",X49*R49,"Probability?"),"") | AK49: =IF(R49<>"",R49,IF(J49,J49,"")) | AL49: =IF(X49<>"",X49,IF(P49=1,P49,"")) | AM49: =IF(Y49<>"",Y49,IF(Q49=1,Q49,"")) | AN49: =IF(COUNT(AK49:AM49)>2,IF(AJ49<>"",IF(ISERROR(SEARCH("open",AJ49,1)),"Closed","Open"),"Open"),"")
P50: =IF(COUNT(K50:O50)>0,AVERAGE(K50:O50),"") | Q50: =IF(P50<>"",IF(J50<>"",P50*J50,"Probability?"),"") | X50: =IF(COUNT(S50:W50)>0,AVERAGE(S50:W50),"") | Y50: =IF(X50<>"",IF(R50<>"",X50*R50,"Probability?"),"")
P51: =IF(COUNT(K51:O51)>0,AVERAGE(K51:O51),"") | Q51: =IF(P51<>"",IF(J51<>"",P51*J51,"Probability?"),"") | X51: =IF(COUNT(S51:W51)>0,AVERAGE(S51:W51),"") | Y51: =IF(X51<>"",IF(R51<>"",X51*R51,"Probability?"),"")
P52: =IF(COUNT(K52:O52)>0,AVERAGE(K52:O52),"") | Q52: =IF(P52<>"",IF(J52<>"",P52*J52,"Probability?"),"") | X52: =IF(COUNT(S52:W52)>0,AVERAGE(S52:W52),"") | Y52: =IF(X52<>"",IF(R52<>"",X52*R52,"Probability?"),"")
P53: =IF(COUNT(K53:O53)>0,AVERAGE(K53:O53),"") | Q53: =IF(P53<>"",IF(J53<>"",P53*J53,"Probability?"),"") | X53: =IF(COUNT(S53:W53)>0,AVERAGE(S53:W53),"") | Y53: =IF(X53<>"",IF(R53<>"",X53*R53,"Probability?"),"")
P54: =IF(COUNT(K54:O54)>0,AVERAGE(K54:O54),"") | Q54: =IF(P54<>"",IF(J54<>"",P54*J54,"Probability?"),"") | X54: =IF(COUNT(S54:W54)>0,AVERAGE(S54:W54),"") | Y54: =IF(X54<>"",IF(R54<>"",X54*R54,"Probability?"),"")
P55: =IF(COUNT(K55:O55)>0,AVERAGE(K55:O55),"") | Q55: =IF(P55<>"",IF(J55<>"",P55*J55,"Probability?"),"") | X55: =IF(COUNT(S55:W55)>0,AVERAGE(S55:W55),"") | Y55: =IF(X55<>"",IF(R55<>"",X55*R55,"Probability?"),"")
P56: =IF(COUNT(K56:O56)>0,AVERAGE(K56:O56),"") | Q56: =IF(P56<>"",IF(J56<>"",P56*J56,"Probability?"),"") | X56: =IF(COUNT(S56:W56)>0,AVERAGE(S56:W56),"") | Y56: =IF(X56<>"",IF(R56<>"",X56*R56,"Probability?"),"")
P57: =IF(COUNT(K57:O57)>0,AVERAGE(K57:O57),"") | Q57: =IF(P57<>"",IF(J57<>"",P57*J57,"Probability?"),"") | X57: =IF(COUNT(S57:W57)>0,AVERAGE(S57:W57),"") | Y57: =IF(X57<>"",IF(R57<>"",X57*R57,"Probability?"),"")
P58: =IF(COUNT(K58:O58)>0,AVERAGE(K58:O58),"") | Q58: =IF(P58<>"",IF(J58<>"",P58*J58,"Probability?"),"") | X58: =IF(COUNT(S58:W58)>0,AVERAGE(S58:W58),"") | Y58: =IF(X58<>"",IF(R58<>"",X58*R58,"Probability?"),"")
P59: =IF(COUNT(K59:O59)>0,AVERAGE(K59:O59),"") | Q59: =IF(P59<>"",IF(J59<>"",P59*J59,"Probability?"),"") | X59: =IF(COUNT(S59:W59)>0,AVERAGE(S59:W59),"") | Y59: =IF(X59<>"",IF(R59<>"",X59*R59,"Probability?"),"")
P60: =IF(COUNT(K60:O60)>0,AVERAGE(K60:O60),"") | Q60: =IF(P60<>"",IF(J60<>"",P60*J60,"Probability?"),"") | X60: =IF(COUNT(S60:W60)>0,AVERAGE(S60:W60),"") | Y60: =IF(X60<>"",IF(R60<>"",X60*R60,"Probability?"),"")
P61: =IF(COUNT(K61:O61)>0,AVERAGE(K61:O61),"") | Q61: =IF(P61<>"",IF(J61<>"",P61*J61,"Probability?"),"") | X61: =IF(COUNT(S61:W61)>0,AVERAGE(S61:W61),"") | Y61: =IF(X61<>"",IF(R61<>"",X61*R61,"Probability?"),"")
P62: =IF(COUNT(K62:O62)>0,AVERAGE(K62:O62),"") | X62: =IF(COUNT(S62:W62)>0,AVERAGE(S62:W62),"") | Y62: =IF(X62<>"",IF(R62<>"",X62*R62,"Probability?"),"")
P63: =IF(COUNT(K63:O63)>0,AVERAGE(K63:O63),"") | X63: =IF(COUNT(S63:W63)>0,AVERAGE(S63:W63),"") | Y63: =IF(X63<>"",IF(R63<>"",X63*R63,"Probability?"),"")
P64: =IF(COUNT(K64:O64)>0,AVERAGE(K64:O64),"") | X64: =IF(COUNT(S64:W64)>0,AVERAGE(S64:W64),"") | Y64: =IF(X64<>"",IF(R64<>"",X64*R64,"Probability?"),"")
P65: =IF(COUNT(K65:O65)>0,AVERAGE(K65:O65),"") | X65: =IF(COUNT(S65:W65)>0,AVERAGE(S65:W65),"") | Y65: =IF(X65<>"",IF(R65<>"",X65*R65,"Probability?"),"")
P66: =IF(COUNT(K66:O66)>0,AVERAGE(K66:O66),"") | X66: =IF(COUNT(S66:W66)>0,AVERAGE(S66:W66),"") | Y66: =IF(X66<>"",IF(R66<>"",X66*R66,"Probability?"),"")
P67: =IF(COUNT(K67:O67)>0,AVERAGE(K67:O67),"") | X67: =IF(COUNT(S67:W67)>0,AVERAGE(S67:W67),"") | Y67: =IF(X67<>"",IF(R67<>"",X67*R67,"Probability?"),"")
P68: =IF(COUNT(K68:O68)>0,AVERAGE(K68:O68),"") | X68: =IF(COUNT(S68:W68)>0,AVERAGE(S68:W68),"") | Y68: =IF(X68<>"",IF(R68<>"",X68*R68,"Probability?"),"")
P69: =IF(COUNT(K69:O69)>0,AVERAGE(K69:O69),"") | X69: =IF(COUNT(S69:W69)>0,AVERAGE(S69:W69),"") | Y69: =IF(X69<>"",IF(R69<>"",X69*R69,"Probability?"),"")
P70: =IF(COUNT(K70:O70)>0,AVERAGE(K70:O70),"") | X70: =IF(COUNT(S70:W70)>0,AVERAGE(S70:W70),"") | Y70: =IF(X70<>"",IF(R70<>"",X70*R70,"Probability?"),"")
P71: =IF(COUNT(K71:O71)>0,AVERAGE(K71:O71),"") | X71: =IF(COUNT(S71:W71)>0,AVERAGE(S71:W71),"") | Y71: =IF(X71<>"",IF(R71<>"",X71*R71,"Probability?"),"")
P72: =IF(COUNT(K72:O72)>0,AVERAGE(K72:O72),"") | X72: =IF(COUNT(S72:W72)>0,AVERAGE(S72:W72),"") | Y72: =IF(X72<>"",IF(R72<>"",X72*R72,"Probability?"),"")

Sheet Size, Schedule and Effort
A1: Project Phases | B1: Schedule | H1: Effort | K1: Schedule Metrics | M1: Effort Metrics | O1: Status | Q1: Remarks | U1: Not started | V1: In progress | W1: Waiting for inputs | X1: Deferred | Y1: Completed | Z1: {=MAX(IF(O3:O496="Completed",V3:V496,0))} -> 3
A2: Milestone Completion | B2: Estimated Start Date | C2: Estimated Completion Date | D2: Last Baselined Start Date | E2: Last Baselined Completion Date | F2: Actual Start Date | G2: Actual Completion Date | H2: Estimated Effort in Person hours | I2: Revised Effort in Person hours | J2: Actual Effort in Person hours | K2: SVA (Cumulative) | L2: SVB (Cumulative) | M2: EVA (Cumulative) | N2: EVB (Cumulative) | O2: Activity Status | P2: Customer Deliverable | R2: Est Effort Cumulative | S2: Rev. Effort Cumulative | T2: Act Effort - Cumulative | U2: Customer deliverable? | V2: Row num | X2: Applicable phases | Y2: Size Units | Z2: Project SVA goal | AA2: Project SVB Goal | AB2: Project EVA goal | AC2: Project EVB Goal | AD2: Actual Vs. Initial estimated productivity | AE2: Actual Vs. Last baselined productivity | AF2: Rev. St Date | AG2: Rev. End Date | AH2: Sch. Variance | AI2: Size unit1 | AJ2: Size unit2 | AK2: Size unit3 | AL2: Size unit4 | AM2: Size unit5 | AN2: EVA | AP2: EVB | AR2: SVA | AT2: SVB | AV2: QOW Index
A3: Analysis and Design-Rel1 | K3: =IF(AND(COUNTA(B3:C3)>1,COUNTA(F3:G3)>1,O3="Completed"),(G3-F3)/(C3-B3+1)%,"") | L3: =IF(AND(COUNTA(D3:E3)>1,COUNTA(F3:G3)>1,O3="Completed"),(G3-F3)/(E3-D3+1)%,"") | M3: =(H3-I3)/H3 -> #DIV/0! | N3: =(I3-J3)/I3 -> #DIV/0! | O3: Completed | P3: Yes | R3: =IF(H3<>"",SUMIF(H$3:H3,"<>" & "",H$3:H3),"") | S3: {=IF(O3="Completed",SUMIF(W$3:W3,"<>" & "",W$3:W3),"")} -> 0 | T3: {=IF(AND(J3<>"",O3="Completed"),SUM(IF(O$3:O3="Completed",J$3:J3,0)),"")} | U3: =IF(AND(A3<>"",P3="Yes"),ROW(),"") -> 3 | V3: =ROW() -> 3 | W3: =IF(O3="Completed",IF(COUNT($I$3:$I$596)>0,IF(I3<>"",I3,H3),""),"") | X3: =IF(ISERROR(SMALL('Control panel'!E$3:E$23,ROW()-2)),"",INDIRECT("'Control panel'!A" & SMALL('Control panel'!E$3:E$23,ROW()-2),1)) -> Analysis and design | Y3: =IF(ISERROR(SMALL('Control panel'!D$3:D$23,ROW()-2)),"",INDIRECT("'Control panel'!B" & SMALL('Control panel'!D$3:D$23,ROW()-2),2)) -> Hours | Z3: =IF(A3<>"",'Metrics planning and tracking'!$K$4,"") -> 10 | AA3: =IF(A3<>"",'Metrics planning and tracking'!$K$5,"") -> 5 | AB3: =IF(A3<>"",'Metrics planning and tracking'!$K$2,"") -> 10 | AC3: =IF(A3<>"",'Metrics planning and tracking'!$K$3,"") -> 5 | AD3: =IF(A3<>"",IF(AND(#REF!<>"",#REF!<>"",#REF!<>0),#REF!/#REF!*100,"NA"),"") -> #REF! | AE3: =IF(A3<>"",IF(AND(#REF!<>"",#REF!<>"",#REF!<>0),#REF!/#REF!*100,"NA"),"") -> #REF! | AF3: =IF($O3="Completed",IF(#REF!<>"",#REF!,IF(#REF!<>"",#REF!,"")),"") -> #REF! | AG3: =IF($O3="Completed",IF(#REF!<>"",#REF!,IF(#REF!<>"",#REF!,"")),"") -> #REF! | AH3: =IF(O3="Completed",IF(L3<>"",L3,IF(K3<>"",K3,"")),"") | AI3: Analysis | AJ3: {=IF(AND(COUNTIF('Control panel'!$A$4:$A$23,$X3)>=COLUMN(#REF!),$X3<>""),INDIRECT("'Control panel'!B" & SMALL(IF('Control panel'!$A$4:$A$23=$X3,'Control panel'!$C$4:$C$23,100),COLUMN(#REF!)),1),"")} -> #REF! | AK3: {=IF(AND(COUNTIF('Control panel'!$A$4:$A$23,$X3)>=COLUMN(#REF!),$X3<>""),INDIRECT("'Control panel'!B" & SMALL(IF('Control panel'!$A$4:$A$23=$X3,'Control panel'!$C$4:$C$23,100),COLUMN(#REF!)),1),"")} -> #REF! | AL3: {=IF(AND(COUNTIF('Control panel'!$A$4:$A$23,$X3)>=COLUMN(#REF!),$X3<>""),INDIRECT("'Control panel'!B" & SMALL(IF('Control panel'!$A$4:$A$23=$X3,'Control panel'!$C$4:$C$23,100),COLUMN(#REF!)),1),"")} -> #REF! | AM3: {=IF(AND(COUNTIF('Control panel'!$A$4:$A$23,$X3)>=COLUMN(#REF!),$X3<>""),INDIRECT("'Control panel'!B" & SMALL(IF('Control panel'!$A$4:$A$23=$X3,'Control panel'!$C$4:$C$23,100),COLUMN(#REF!)),1),"")} -> #REF! | AN3: =IF(A$3<>"",'Metrics planning and tracking'!$L$2,"") -> 15 | AO3: =IF(A$3<>"",'Metrics planning and tracking'!$M$2,"") -> 0 | AP3: =IF(A$3<>"",'Metrics planning and tracking'!$L$3,"") -> 10 | AQ3: =IF(A$3<>"",'Metrics planning and tracking'!$M$3,"") -> 0 | AR3: =IF(A$3<>"",'Metrics planning and tracking'!$L$4,"") -> 15 | AS3: =IF(A$3<>"",'Metrics planning and tracking'!$M$4,"") -> 0 | AT3: =IF(A$3<>"",'Metrics planning and tracking'!$L$5,"") -> 10 | AU3: =IF(A$3<>"",'Metrics planning and tracking'!$M$5,"") -> 0 | AV3: =IF(A3<>"",A3 & "-" &#REF! & ROW(),"") -> #REF!
A4: Development and Unit Testing-Rel-1 | K4: =IF(AND(COUNTA(B4:C4)>1,COUNTA(F4:G4)>1,O4="Completed"),(G4-F4)/(C4-B4+1)%,"") | L4: =IF(AND(COUNTA(D4:E4)>1,COUNTA(F4:G4)>1,O4="Completed"),(G4-F4)/(E4-D4+1)%,"") | M4: =(H4-I4)/H4 -> #DIV/0! | N4: =(I4-J4)/I4 -> #DIV/0! | O4: In progress | P4: Yes | R4: =IF(H4<>"",SUMIF(H$3:H4,"<>" & "",H$3:H4),"") | S4: {=IF(O4="Completed",SUMIF(W$3:W4,"<>" & "",W$3:W4),"")} | T4: {=IF(AND(J4<>"",O4="Completed"),SUM(IF(O$3:O4="Completed",J$3:J4,0)),"")} | U4: =IF(AND(A4<>"",P4="Yes"),ROW(),"") -> 4 | V4: =ROW() -> 4 | W4: =IF(O4="Completed",IF(COUNT($I$3:$I$596)>0,IF(I4<>"",I4,H4),""),"") | X4: =IF(ISERROR(SMALL('Control panel'!E$3:E$23,ROW()-2)),"",INDIRECT("'Control panel'!A" & SMALL('Control panel'!E$3:E$23,ROW()-2),1)) -> Coding and unit testing | Y4: =IF(ISERROR(SMALL('Control panel'!D$3:D$23,ROW()-2)),"",INDIRECT("'Control panel'!B" & SMALL('Control panel'!D$3:D$23,ROW()-2),2)) | Z4: =IF(A4<>"",'Metrics planning and tracking'!$K$4,"") -> 10 | AA4: =IF(A4<>"",'Metrics planning and tracking'!$K$5,"") -> 5 | AB4: =IF(A4<>"",'Metrics planning and tracking'!$K$2,"") -> 10 | AC4: =IF(A4<>"",'Metrics planning and tracking'!$K$3,"") -> 5 | AD4: =IF(A4<>"",IF(AND(#REF!<>"",#REF!<>"",#REF!<>0),#REF!/#REF!*100,"NA"),"") -> #REF! | AE4: =IF(A4<>"",IF(AND(#REF!<>"",#REF!<>"",#REF!<>0),#REF!/#REF!*100,"NA"),"") -> #REF! | AF4: =IF($O4="Completed",IF(#REF!<>"",#REF!,IF(B3<>"",B3,"")),"") | AG4: =IF($O4="Completed",IF(#REF!<>"",#REF!,IF(C3<>"",C3,"")),"") | AH4: =IF(O4="Completed",IF(L4<>"",L4,IF(K4<>"",K4,"")),"") | AI4: Build | AJ4: {=IF(AND(COUNTIF('Control panel'!$A$4:$A$23,$X4)>=COLUMN(#REF!),$X4<>""),INDIRECT("'Control panel'!B" & SMALL(IF('Control panel'!$A$4:$A$23=$X4,'Control panel'!$C$4:$C$23,100),COLUMN(#REF!)),1),"")} -> #REF! | AK4: {=IF(AND(COUNTIF('Control panel'!$A$4:$A$23,$X4)>=COLUMN(#REF!),$X4<>""),INDIRECT("'Control panel'!B" & SMALL(IF('Control panel'!$A$4:$A$23=$X4,'Control panel'!$C$4:$C$23,100),COLUMN(#REF!)),1),"")} -> #REF! | AL4: {=IF(AND(COUNTIF('Control panel'!$A$4:$A$23,$X4)>=COLUMN(#REF!),$X4<>""),INDIRECT("'Control panel'!B" & SMALL(IF('Control panel'!$A$4:$A$23=$X4,'Control panel'!$C$4:$C$23,100),COLUMN(#REF!)),1),"")} -> #REF! | AM4: {=IF(AND(COUNTIF('Control panel'!$A$4:$A$23,$X4)>=COLUMN(#REF!),$X4<>""),INDIRECT("'Control panel'!B" & SMALL(IF('Control panel'!$A$4:$A$23=$X4,'Control panel'!$C$4:$C$23,100),COLUMN(#REF!)),1),"")} -> #REF! | AV4: =IF(A4<>"",A4 & "-" &#REF! & ROW(),"") -> #REF!
A5: System Integration Testing - Rel-1 | K5: =IF(AND(COUNTA(B5:C5)>1,COUNTA(F5:G5)>1,O5="Completed"),(G5-F5)/(C5-B5+1)%,"") | L5: =IF(AND(COUNTA(D5:E5)>1,COUNTA(F5:G5)>1,O5="Completed"),(G5-F5)/(E5-D5+1)%,"") | M5: =(H5-I5)/H5 -> #DIV/0! | N5: =(I5-J5)/I5 -> #DIV/0! | O5: Not started | P5: No | R5: =IF(H5<>"",SUMIF(H$3:H5,"<>" & "",H$3:H5),"") | S5: {=IF(O5="Completed",SUMIF(W$3:W5,"<>" & "",W$3:W5),"")} | T5: {=IF(AND(J5<>"",O5="Completed"),SUM(IF(O$3:O5="Completed",J$3:J5,0)),"")} | U5: =IF(AND(A5<>"",P5="Yes"),ROW(),"") | V5: =ROW() -> 5 | W5: =IF(O5="Completed",IF(COUNT($I$3:$I$596)>0,IF(I5<>"",I5,H5),""),"") | X5: =IF(ISERROR(SMALL('Control panel'!E$3:E$23,ROW()-2)),"",INDIRECT("'Control panel'!A" & SMALL('Control panel'!E$3:E$23,ROW()-2),1)) -> System integration testing | Y5: =IF(ISERROR(SMALL('Control panel'!D$3:D$23,ROW()-2)),"",INDIRECT("'Control panel'!B" & SMALL('Control panel'!D$3:D$23,ROW()-2),2)) | Z5: =IF(A5<>"",'Metrics planning and tracking'!$K$4,"") -> 10 | AA5: =IF(A5<>"",'Metrics planning and tracking'!$K$5,"") -> 5 | AB5: =IF(A5<>"",'Metrics planning and tracking'!$K$2,"") -> 10 | AC5: =IF(A5<>"",'Metrics planning and tracking'!$K$3,"") -> 5 | AD5: =IF(A5<>"",IF(AND(#REF!<>"",#REF!<>"",#REF!<>0),#REF!/#REF!*100,"NA"),"") -> #REF! | AE5: =IF(A5<>"",IF(AND(#REF!<>"",#REF!<>"",#REF!<>0),#REF!/#REF!*100,"NA"),"") -> #REF! | AF5: =IF($O5="Completed",IF(D4<>"",D4,IF(#REF!<>"",#REF!,"")),"") | AG5: =IF($O5="Completed",IF(E4<>"",E4,IF(#REF!<>"",#REF!,"")),"") | AH5: =IF(O5="Completed",IF(L5<>"",L5,IF(K5<>"",K5,"")),"") | AI5: Code Modification | AJ5: {=IF(AND(COUNTIF('Control panel'!$A$4:$A$23,$X5)>=COLUMN(#REF!),$X5<>""),INDIRECT("'Control panel'!B" & SMALL(IF('Control panel'!$A$4:$A$23=$X5,'Control panel'!$C$4:$C$23,100),COLUMN(#REF!)),1),"")} -> #REF! | AK5: {=IF(AND(COUNTIF('Control panel'!$A$4:$A$23,$X5)>=COLUMN(#REF!),$X5<>""),INDIRECT("'Control panel'!B" & SMALL(IF('Control panel'!$A$4:$A$23=$X5,'Control panel'!$C$4:$C$23,100),COLUMN(#REF!)),1),"")} -> #REF! | AL5: {=IF(AND(COUNTIF('Control panel'!$A$4:$A$23,$X5)>=COLUMN(#REF!),$X5<>""),INDIRECT("'Control panel'!B" & SMALL(IF('Control panel'!$A$4:$A$23=$X5,'Control panel'!$C$4:$C$23,100),COLUMN(#REF!)),1),"")} -> #REF! | AM5: {=IF(AND(COUNTIF('Control panel'!$A$4:$A$23,$X5)>=COLUMN(#REF!),$X5<>""),INDIRECT("'Control panel'!B" & SMALL(IF('Control panel'!$A$4:$A$23=$X5,'Control panel'!$C$4:$C$23,100),COLUMN(#REF!)),1),"")} -> #REF! | AV5: =IF(A5<>"",A5 & "-" &#REF! & ROW(),"") -> #REF!
A6: User Acceptance Testing - Rel-1 | K6: =IF(AND(COUNTA(B6:C6)>1,COUNTA(F6:G6)>1,O6="Completed"),(G6-F6)/(C6-B6+1)%,"") | L6: =IF(AND(COUNTA(D6:E6)>1,COUNTA(F6:G6)>1,O6="Completed"),(G6-F6)/(E6-D6+1)%,"") | M6: =(H6-I6)/H6 -> #DIV/0! | N6: =(I6-J6)/I6 -> #DIV/0! | O6: Not started | P6: Yes | R6: =IF(H6<>"",SUMIF(H$3:H6,"<>" & "",H$3:H6),"") | S6: {=IF(O6="Completed",SUMIF(W$3:W6,"<>" & "",W$3:W6),"")} | T6: {=IF(AND(J6<>"",O6="Completed"),SUM(IF(O$3:O6="Completed",J$3:J6,0)),"")} | U6: =IF(AND(A6<>"",P6="Yes"),ROW(),"") -> 6 | V6: =ROW() -> 6 | W6: =IF(O6="Completed",IF(COUNT($I$3:$I$596)>0,IF(I6<>"",I6,H6),""),"") | X6: =IF(ISERROR(SMALL('Control panel'!E$3:E$23,ROW()-2)),"",INDIRECT("'Control panel'!A" & SMALL('Control panel'!E$3:E$23,ROW()-2),1)) -> User acceptance testing | Y6: =IF(ISERROR(SMALL('Control panel'!D$3:D$23,ROW()-2)),"",INDIRECT("'Control panel'!B" & SMALL('Control panel'!D$3:D$23,ROW()-2),2)) | Z6: =IF(A6<>"",'Metrics planning and tracking'!$K$4,"") -> 10 | AA6: =IF(A6<>"",'Metrics planning and tracking'!$K$5,"") -> 5 | AB6: =IF(A6<>"",'Metrics planning and tracking'!$K$2,"") -> 10 | AC6: =IF(A6<>"",'Metrics planning and tracking'!$K$3,"") -> 5 | AD6: =IF(A6<>"",IF(AND(#REF!<>"",#REF!<>"",#REF!<>0),#REF!/#REF!*100,"NA"),"") -> #REF! | AE6: =IF(A6<>"",IF(AND(#REF!<>"",#REF!<>"",#REF!<>0),#REF!/#REF!*100,"NA"),"") -> #REF! | AF6: =IF($O6="Completed",IF(D5<>"",D5,IF(B4<>"",B4,"")),"") | AG6: =IF($O6="Completed",IF(E5<>"",E5,IF(C4<>"",C4,"")),"") | AH6: =IF(O6="Completed",IF(L6<>"",L6,IF(K6<>"",K6,"")),"") | AI6: Code Study | AJ6: {=IF(AND(COUNTIF('Control panel'!$A$4:$A$23,$X6)>=COLUMN(#REF!),$X6<>""),INDIRECT("'Control panel'!B" & SMALL(IF('Control panel'!$A$4:$A$23=$X6,'Control panel'!$C$4:$C$23,100),COLUMN(#REF!)),1),"")} -> #REF! | AK6: {=IF(AND(COUNTIF('Control panel'!$A$4:$A$23,$X6)>=COLUMN(#REF!),$X6<>""),INDIRECT("'Control panel'!B" & SMALL(IF('Control panel'!$A$4:$A$23=$X6,'Control panel'!$C$4:$C$23,100),COLUMN(#REF!)),1),"")} -> #REF! | AL6: {=IF(AND(COUNTIF('Control panel'!$A$4:$A$23,$X6)>=COLUMN(#REF!),$X6<>""),INDIRECT("'Control panel'!B" & SMALL(IF('Control panel'!$A$4:$A$23=$X6,'Control panel'!$C$4:$C$23,100),COLUMN(#REF!)),1),"")} -> #REF! | AM6: {=IF(AND(COUNTIF('Control panel'!$A$4:$A$23,$X6)>=COLUMN(#REF!),$X6<>""),INDIRECT("'Control panel'!B" & SMALL(IF('Control panel'!$A$4:$A$23=$X6,'Control panel'!$C$4:$C$23,100),COLUMN(#REF!)),1),"")} -> #REF! | AV6: =IF(A6<>"",A6 & "-" &#REF! & ROW(),"") -> #REF!
A7: Production Deployment Rel-1 | K7: =IF(AND(COUNTA(B7:C7)>1,COUNTA(F7:G7)>1,O7="Completed"),(G7-F7)/(C7-B7+1)%,"") | L7: =IF(AND(COUNTA(D7:E7)>1,COUNTA(F7:G7)>1,O7="Completed"),(G7-F7)/(E7-D7+1)%,"") | M7: =(H7-I7)/H7 -> #DIV/0! | N7: =(I7-J7)/I7 -> #DIV/0! | O7: Not started | P7: Yes | R7: =IF(H7<>"",SUMIF(H$3:H7,"<>" & "",H$3:H7),"") | S7: {=IF(O7="Completed",SUMIF(W$3:W7,"<>" & "",W$3:W7),"")} | T7: {=IF(AND(J7<>"",O7="Completed"),SUM(IF(O$3:O7="Completed",J$3:J7,0)),"")} | U7: =IF(AND(A7<>"",P7="Yes"),ROW(),"") -> 7 | V7: =ROW() -> 7 | W7: =IF(O7="Completed",IF(COUNT($I$3:$I$596)>0,IF(I7<>"",I7,H7),""),"") | X7: =IF(ISERROR(SMALL('Control panel'!E$3:E$23,ROW()-2)),"",INDIRECT("'Control panel'!A" & SMALL('Control panel'!E$3:E$23,ROW()-2),1)) -> Production Deployment | Y7: =IF(ISERROR(SMALL('Control panel'!D$3:D$23,ROW()-2)),"",INDIRECT("'Control panel'!B" & SMALL('Control panel'!D$3:D$23,ROW()-2),2)) | Z7: =IF(A7<>"",'Metrics planning and tracking'!$K$4,"") -> 10 | AA7: =IF(A7<>"",'Metrics planning and tracking'!$K$5,"") -> 5 | AB7: =IF(A7<>"",'Metrics planning and tracking'!$K$2,"") -> 10 | AC7: =IF(A7<>"",'Metrics planning and tracking'!$K$3,"") -> 5 | AD7: =IF(A7<>"",IF(AND(#REF!<>"",#REF!<>"",#REF!<>0),#REF!/#REF!*100,"NA"),"") -> #REF! | AE7: =IF(A7<>"",IF(AND(#REF!<>"",#REF!<>"",#REF!<>0),#REF!/#REF!*100,"NA"),"") -> #REF! | AF7: =IF($O7="Completed",IF(D6<>"",D6,IF(B5<>"",B5,"")),"") | AG7: =IF($O7="Completed",IF(E6<>"",E6,IF(C5<>"",C5,"")),"") | AH7: =IF(O7="Completed",IF(L7<>"",L7,IF(K7<>"",K7,"")),"") | AI7: Coding | AJ7: {=IF(AND(COUNTIF('Control panel'!$A$4:$A$23,$X7)>=COLUMN(#REF!),$X7<>""),INDIRECT("'Control panel'!B" & SMALL(IF('Control panel'!$A$4:$A$23=$X7,'Control panel'!$C$4:$C$23,100),COLUMN(#REF!)),1),"")} -> #REF! | AK7: {=IF(AND(COUNTIF('Control panel'!$A$4:$A$23,$X7)>=COLUMN(#REF!),$X7<>""),INDIRECT("'Control panel'!B" & SMALL(IF('Control panel'!$A$4:$A$23=$X7,'Control panel'!$C$4:$C$23,100),COLUMN(#REF!)),1),"")} -> #REF! | AL7: {=IF(AND(COUNTIF('Control panel'!$A$4:$A$23,$X7)>=COLUMN(#REF!),$X7<>""),INDIRECT("'Control panel'!B" & SMALL(IF('Control panel'!$A$4:$A$23=$X7,'Control panel'!$C$4:$C$23,100),COLUMN(#REF!)),1),"")} -> #REF! | AM7: {=IF(AND(COUNTIF('Control panel'!$A$4:$A$23,$X7)>=COLUMN(#REF!),$X7<>""),INDIRECT("'Control panel'!B" & SMALL(IF('Control panel'!$A$4:$A$23=$X7,'Control panel'!$C$4:$C$23,100),COLUMN(#REF!)),1),"")} -> #REF! | AV7: =IF(A7<>"",A7 & "-" &#REF! & ROW(),"") -> #REF!
A8: Post Production Deployment Support - Rel-1 | K8: =IF(AND(COUNTA(B8:C8)>1,COUNTA(F8:G8)>1,O8="Completed"),(G8-F8)/(C8-B8+1)%,"") | L8: =IF(AND(COUNTA(D8:E8)>1,COUNTA(F8:G8)>1,O8="Completed"),(G8-F8)/(E8-D8+1)%,"") | M8: =(H8-I8)/H8 -> #DIV/0! | N8: =(I8-J8)/I8 -> #DIV/0! | O8: Not started | P8: No | U8: =IF(AND(A8<>"",P8="Yes"),ROW(),"") | W8: =IF(O8="Completed",IF(COUNT($I$3:$I$596)>0,IF(I8<>"",I8,H8),""),"") | AD8: =IF(A8<>"",IF(AND(#REF!<>"",#REF!<>"",#REF!<>0),#REF!/#REF!*100,"NA"),"") -> #REF! | AE8: =IF(A8<>"",IF(AND(#REF!<>"",#REF!<>"",#REF!<>0),#REF!/#REF!*100,"NA"),"") -> #REF! | AH8: =IF(O8="Completed",IF(L8<>"",L8,IF(K8<>"",K8,"")),"") | AI8: Post Production Deployment Support
U9: =IF(AND(A9<>"",P9="Yes"),ROW(),"") | AI9: Fix testing
R10: =IF(H10<>"",SUMIF(H$3:H10,"<>" & "",H$3:H10),"") | S10: {=IF(O10="Completed",SUMIF(W$3:W10,"<>" & "",W$3:W10),"")} | T10: {=IF(AND(J10<>"",O10="Completed"),SUM(IF(O$3:O10="Completed",J$3:J10,0)),"")} | U10: =IF(AND(A10<>"",P10="Yes"),ROW(),"") | V10: =ROW() -> 10 | W10: =IF(O10="Completed",IF(COUNT($I$3:$I$596)>0,IF(I10<>"",I10,H10),""),"") | X10: =IF(ISERROR(SMALL('Control panel'!E$3:E$23,ROW()-2)),"",INDIRECT("'Control panel'!A" & SMALL('Control panel'!E$3:E$23,ROW()-2),1)) | Y10: =IF(ISERROR(SMALL('Control panel'!D$3:D$23,ROW()-2)),"",INDIRECT("'Control panel'!B" & SMALL('Control panel'!D$3:D$23,ROW()-2),2)) | Z10: =IF(A10<>"",'Metrics planning and tracking'!$K$4,"") | AA10: =IF(A10<>"",'Metrics planning and tracking'!$K$5,"") | AB10: =IF(A10<>"",'Metrics planning and tracking'!$K$2,"") | AC10: =IF(A10<>"",'Metrics planning and tracking'!$K$3,"") | AD10: =IF(A10<>"",IF(AND(#REF!<>"",#REF!<>"",#REF!<>0),#REF!/#REF!*100,"NA"),"") | AE10: =IF(A10<>"",IF(AND(#REF!<>"",#REF!<>"",#REF!<>0),#REF!/#REF!*100,"NA"),"") | AF10: =IF($O10="Completed",IF(D10<>"",D10,IF(B10<>"",B10,"")),"") | AG10: =IF($O10="Completed",IF(E10<>"",E10,IF(C10<>"",C10,"")),"") | AH10: =IF(O10="Completed",IF(L10<>"",L10,IF(K10<>"",K10,"")),"") | AI10: Func Spec | AJ10: {=IF(AND(COUNTIF('Control panel'!$A$4:$A$23,$X10)>=COLUMN(#REF!),$X10<>""),INDIRECT("'Control panel'!B" & SMALL(IF('Control panel'!$A$4:$A$23=$X10,'Control panel'!$C$4:$C$23,100),COLUMN(#REF!)),1),"")} -> #REF! | AK10: {=IF(AND(COUNTIF('Control panel'!$A$4:$A$23,$X10)>=COLUMN(#REF!),$X10<>""),INDIRECT("'Control panel'!B" & SMALL(IF('Control panel'!$A$4:$A$23=$X10,'Control panel'!$C$4:$C$23,100),COLUMN(#REF!)),1),"")} -> #REF! | AL10: {=IF(AND(COUNTIF('Control panel'!$A$4:$A$23,$X10)>=COLUMN(#REF!),$X10<>""),INDIRECT("'Control panel'!B" & SMALL(IF('Control panel'!$A$4:$A$23=$X10,'Control panel'!$C$4:$C$23,100),COLUMN(#REF!)),1),"")} -> #REF! | AM10: {=IF(AND(COUNTIF('Control panel'!$A$4:$A$23,$X10)>=COLUMN(#REF!),$X10<>""),INDIRECT("'Control panel'!B" & SMALL(IF('Control panel'!$A$4:$A$23=$X10,'Control panel'!$C$4:$C$23,100),COLUMN(#REF!)),1),"")} -> #REF! | AV10: =IF(A10<>"",A10 & "-" &#REF! & ROW(),"")
R11: =IF(H11<>"",SUMIF(H$3:H11,"<>" & "",H$3:H11),"") | S11: {=IF(O11="Completed",SUMIF(W$3:W11,"<>" & "",W$3:W11),"")} | T11: {=IF(AND(J11<>"",O11="Completed"),SUM(IF(O$3:O11="Completed",J$3:J11,0)),"")} | U11: =IF(AND(A11<>"",P11="Yes"),ROW(),"") | V11: =ROW() -> 11 | W11: =IF(O11="Completed",IF(COUNT($I$3:$I$596)>0,IF(I11<>"",I11,H11),""),"") | X11: =IF(ISERROR(SMALL('Control panel'!E$3:E$23,ROW()-2)),"",INDIRECT("'Control panel'!A" & SMALL('Control panel'!E$3:E$23,ROW()-2),1)) | Y11: =IF(ISERROR(SMALL('Control panel'!D$3:D$23,ROW()-2)),"",INDIRECT("'Control panel'!B" & SMALL('Control panel'!D$3:D$23,ROW()-2),2)) | Z11: =IF(A11<>"",'Metrics planning and tracking'!$K$4,"") | AA11: =IF(A11<>"",'Metrics planning and tracking'!$K$5,"") | AB11: =IF(A11<>"",'Metrics planning and tracking'!$K$2,"") | AC11: =IF(A11<>"",'Metrics planning and tracking'!$K$3,"") | AD11: =IF(A11<>"",IF(AND(#REF!<>"",#REF!<>"",#REF!<>0),#REF!/#REF!*100,"NA"),"") | AE11: =IF(A11<>"",IF(AND(#REF!<>"",#REF!<>"",#REF!<>0),#REF!/#REF!*100,"NA"),"") | AF11: =IF($O11="Completed",IF(D11<>"",D11,IF(B11<>"",B11,"")),"") | AG11: =IF($O11="Completed",IF(E11<>"",E11,IF(C11<>"",C11,"")),"") | AH11: =IF(O11="Completed",IF(L11<>"",L11,IF(K11<>"",K11,"")),"") | AI11: Gerber Generation | AJ11: {=IF(AND(COUNTIF('Control panel'!$A$4:$A$23,$X11)>=COLUMN(#REF!),$X11<>""),INDIRECT("'Control panel'!B" & SMALL(IF('Control panel'!$A$4:$A$23=$X11,'Control panel'!$C$4:$C$23,100),COLUMN(#REF!)),1),"")} -> #REF! | AK11: {=IF(AND(COUNTIF('Control panel'!$A$4:$A$23,$X11)>=COLUMN(#REF!),$X11<>""),INDIRECT("'Control panel'!B" & SMALL(IF('Control panel'!$A$4:$A$23=$X11,'Control panel'!$C$4:$C$23,100),COLUMN(#REF!)),1),"")} -> #REF! | AL11: {=IF(AND(COUNTIF('Control panel'!$A$4:$A$23,$X11)>=COLUMN(#REF!),$X11<>""),INDIRECT("'Control panel'!B" & SMALL(IF('Control panel'!$A$4:$A$23=$X11,'Control panel'!$C$4:$C$23,100),COLUMN(#REF!)),1),"")} -> #REF! | AM11: {=IF(AND(COUNTIF('Control panel'!$A$4:$A$23,$X11)>=COLUMN(#REF!),$X11<>""),INDIRECT("'Control panel'!B" & SMALL(IF('Control panel'!$A$4:$A$23=$X11,'Control panel'!$C$4:$C$23,100),COLUMN(#REF!)),1),"")} -> #REF! | AV11: =IF(A11<>"",A11 & "-" &#REF! & ROW(),"")
R12: =IF(H12<>"",SUMIF(H$3:H12,"<>" & "",H$3:H12),"") | S12: {=IF(O12="Completed",SUMIF(W$3:W12,"<>" & "",W$3:W12),"")} | T12: {=IF(AND(J12<>"",O12="Completed"),SUM(IF(O$3:O12="Completed",J$3:J12,0)),"")} | U12: =IF(AND(A12<>"",P12="Yes"),ROW(),"") | V12: =ROW() -> 12 | W12: =IF(O12="Completed",IF(COUNT($I$3:$I$596)>0,IF(I12<>"",I12,H12),""),"") | X12: =IF(ISERROR(SMALL('Control panel'!E$3:E$23,ROW()-2)),"",INDIRECT("'Control panel'!A" & SMALL('Control panel'!E$3:E$23,ROW()-2),1)) | Y12: =IF(ISERROR(SMALL('Control panel'!D$3:D$23,ROW()-2)),"",INDIRECT("'Control panel'!B" & SMALL('Control panel'!D$3:D$23,ROW()-2),2)) | Z12: =IF(A12<>"",'Metrics planning and tracking'!$K$4,"") | AA12: =IF(A12<>"",'Metrics planning and tracking'!$K$5,"") | AB12: =IF(A12<>"",'Metrics planning and tracking'!$K$2,"") | AC12: =IF(A12<>"",'Metrics planning and tracking'!$K$3,"") | AD12: =IF(A12<>"",IF(AND(#REF!<>"",#REF!<>"",#REF!<>0),#REF!/#REF!*100,"NA"),"") | AE12: =IF(A12<>"",IF(AND(#REF!<>"",#REF!<>"",#REF!<>0),#REF!/#REF!*100,"NA"),"") | AF12: =IF($O12="Completed",IF(D12<>"",D12,IF(B12<>"",B12,"")),"") | AG12: =IF($O12="Completed",IF(E12<>"",E12,IF(C12<>"",C12,"")),"") | AH12: =IF(O12="Completed",IF(L12<>"",L12,IF(K12<>"",K12,"")),"") | AI12: HD and PS | AJ12: {=IF(AND(COUNTIF('Control panel'!$A$4:$A$23,$X12)>=COLUMN(#REF!),$X12<>""),INDIRECT("'Control panel'!B" & SMALL(IF('Control panel'!$A$4:$A$23=$X12,'Control panel'!$C$4:$C$23,100),COLUMN(#REF!)),1),"")} -> #REF! | AK12: {=IF(AND(COUNTIF('Control panel'!$A$4:$A$23,$X12)>=COLUMN(#REF!),$X12<>""),INDIRECT("'Control panel'!B" & SMALL(IF('Control panel'!$A$4:$A$23=$X12,'Control panel'!$C$4:$C$23,100),COLUMN(#REF!)),1),"")} -> #REF! | AL12: {=IF(AND(COUNTIF('Control panel'!$A$4:$A$23,$X12)>=COLUMN(#REF!),$X12<>""),INDIRECT("'Control panel'!B" & SMALL(IF('Control panel'!$A$4:$A$23=$X12,'Control panel'!$C$4:$C$23,100),COLUMN(#REF!)),1),"")} -> #REF! | AM12: {=IF(AND(COUNTIF('Control panel'!$A$4:$A$23,$X12)>=COLUMN(#REF!),$X12<>""),INDIRECT("'Control panel'!B" & SMALL(IF('Control panel'!$A$4:$A$23=$X12,'Control panel'!$C$4:$C$23,100),COLUMN(#REF!)),1),"")} -> #REF! | AV12: =IF(A12<>"",A12 & "-" &#REF! & ROW(),"")
R13: =IF(H13<>"",SUMIF(H$3:H13,"<>" & "",H$3:H13),"") | S13: {=IF(O13="Completed",SUMIF(W$3:W13,"<>" & "",W$3:W13),"")} | T13: {=IF(AND(J13<>"",O13="Completed"),SUM(IF(O$3:O13="Completed",J$3:J13,0)),"")} | U13: =IF(AND(A13<>"",P13="Yes"),ROW(),"") | V13: =ROW() -> 13 | W13: =IF(O13="Completed",IF(COUNT($I$3:$I$596)>0,IF(I13<>"",I13,H13),""),"") | X13: =IF(ISERROR(SMALL('Control panel'!E$3:E$23,ROW()-2)),"",INDIRECT("'Control panel'!A" & SMALL('Control panel'!E$3:E$23,ROW()-2),1)) | Y13: =IF(ISERROR(SMALL('Control panel'!D$3:D$23,ROW()-2)),"",INDIRECT("'Control panel'!B" & SMALL('Control panel'!D$3:D$23,ROW()-2),2)) | Z13: =IF(A13<>"",'Metrics planning and tracking'!$K$4,"") | AA13: =IF(A13<>"",'Metrics planning and tracking'!$K$5,"") | AB13: =IF(A13<>"",'Metrics planning and tracking'!$K$2,"") | AC13: =IF(A13<>"",'Metrics planning and tracking'!$K$3,"") | AD13: =IF(A13<>"",IF(AND(#REF!<>"",#REF!<>"",#REF!<>0),#REF!/#REF!*100,"NA"),"") | AE13: =IF(A13<>"",IF(AND(#REF!<>"",#REF!<>"",#REF!<>0),#REF!/#REF!*100,"NA"),"") | AF13: =IF($O13="Completed",IF(D13<>"",D13,IF(B13<>"",B13,"")),"") | AG13: =IF($O13="Completed",IF(E13<>"",E13,IF(C13<>"",C13,"")),"") | AH13: =IF(O13="Completed",IF(L13<>"",L13,IF(K13<>"",K13,"")),"") | AI13: High level design | AJ13: {=IF(AND(COUNTIF('Control panel'!$A$4:$A$23,$X13)>=COLUMN(#REF!),$X13<>""),INDIRECT("'Control panel'!B" & SMALL(IF('Control panel'!$A$4:$A$23=$X13,'Control panel'!$C$4:$C$23,100),COLUMN(#REF!)),1),"")} -> #REF! | AK13: {=IF(AND(COUNTIF('Control panel'!$A$4:$A$23,$X13)>=COLUMN(#REF!),$X13<>""),INDIRECT("'Control panel'!B" & SMALL(IF('Control panel'!$A$4:$A$23=$X13,'Control panel'!$C$4:$C$23,100),COLUMN(#REF!)),1),"")} -> #REF! | AL13: {=IF(AND(COUNTIF('Control panel'!$A$4:$A$23,$X13)>=COLUMN(#REF!),$X13<>""),INDIRECT("'Control panel'!B" & SMALL(IF('Control panel'!$A$4:$A$23=$X13,'Control panel'!$C$4:$C$23,100),COLUMN(#REF!)),1),"")} -> #REF! | AM13: {=IF(AND(COUNTIF('Control panel'!$A$4:$A$23,$X13)>=COLUMN(#REF!),$X13<>""),INDIRECT("'Control panel'!B" & SMALL(IF('Control panel'!$A$4:$A$23=$X13,'Control panel'!$C$4:$C$23,100),COLUMN(#REF!)),1),"")} -> #REF! | AV13: =IF(A13<>"",A13 & "-" &#REF! & ROW(),"")
K14: =IF(AND(COUNTA(B14:C14)>1,COUNTA(F14:G14)>1,O14="Completed"),(G14-F14)/(C14-B14+1)%,"") | L14: =IF(AND(COUNTA(D14:E14)>1,COUNTA(F14:G14)>1,O14="Completed"),(G14-F14)/(E14-D14+1)%,"") | R14: =IF(H14<>"",SUMIF(H$3:H14,"<>" & "",H$3:H14),"") | S14: {=IF(O14="Completed",SUMIF(W$3:W14,"<>" & "",W$3:W14),"")} | T14: {=IF(AND(J14<>"",O14="Completed"),SUM(IF(O$3:O14="Completed",J$3:J14,0)),"")} | U14: =IF(AND(A14<>"",P14="Yes"),ROW(),"") | V14: =ROW() -> 14 | W14: =IF(O14="Completed",IF(COUNT($I$3:$I$596)>0,IF(I14<>"",I14,H14),""),"") | X14: =IF(ISERROR(SMALL('Control panel'!E$3:E$23,ROW()-2)),"",INDIRECT("'Control panel'!A" & SMALL('Control panel'!E$3:E$23,ROW()-2),1)) | Y14: =IF(ISERROR(SMALL('Control panel'!D$3:D$23,ROW()-2)),"",INDIRECT("'Control panel'!B" & SMALL('Control panel'!D$3:D$23,ROW()-2),2)) | Z14: =IF(A14<>"",'Metrics planning and tracking'!$K$4,"") | AA14: =IF(A14<>"",'Metrics planning and tracking'!$K$5,"") | AB14: =IF(A14<>"",'Metrics planning and tracking'!$K$2,"") | AC14: =IF(A14<>"",'Metrics planning and tracking'!$K$3,"") | AD14: =IF(A14<>"",IF(AND(#REF!<>"",#REF!<>"",#REF!<>0),#REF!/#REF!*100,"NA"),"") | AE14: =IF(A14<>"",IF(AND(#REF!<>"",#REF!<>"",#REF!<>0),#REF!/#REF!*100,"NA"),"") | AF14: =IF($O14="Completed",IF(D14<>"",D14,IF(B14<>"",B14,"")),"") | AG14: =IF($O14="Completed",IF(E14<>"",E14,IF(C14<>"",C14,"")),"") | AH14: =IF(O14="Completed",IF(L14<>"",L14,IF(K14<>"",K14,"")),"") | AI14: Integration testing | AJ14: {=IF(AND(COUNTIF('Control panel'!$A$4:$A$23,$X14)>=COLUMN(#REF!),$X14<>""),INDIRECT("'Control panel'!B" & SMALL(IF('Control panel'!$A$4:$A$23=$X14,'Control panel'!$C$4:$C$23,100),COLUMN(#REF!)),1),"")} -> #REF! | AK14: {=IF(AND(COUNTIF('Control panel'!$A$4:$A$23,$X14)>=COLUMN(#REF!),$X14<>""),INDIRECT("'Control panel'!B" & SMALL(IF('Control panel'!$A$4:$A$23=$X14,'Control panel'!$C$4:$C$23,100),COLUMN(#REF!)),1),"")} -> #REF! | AL14: {=IF(AND(COUNTIF('Control panel'!$A$4:$A$23,$X14)>=COLUMN(#REF!),$X14<>""),INDIRECT("'Control panel'!B" & SMALL(IF('Control panel'!$A$4:$A$23=$X14,'Control panel'!$C$4:$C$23,100),COLUMN(#REF!)),1),"")} -> #REF! | AM14: {=IF(AND(COUNTIF('Control panel'!$A$4:$A$23,$X14)>=COLUMN(#REF!),$X14<>""),INDIRECT("'Control panel'!B" & SMALL(IF('Control panel'!$A$4:$A$23=$X14,'Control panel'!$C$4:$C$23,100),COLUMN(#REF!)),1),"")} -> #REF! | AV14: =IF(A14<>"",A14 & "-" &#REF! & ROW(),"")
K15: =IF(AND(COUNTA(B15:C15)>1,COUNTA(F15:H15)>1,O15="Completed"),(H15-F15)/(C15-B15+1)%,"") | L15: =IF(AND(COUNTA(D15:E15)>1,COUNTA(F15:H15)>1,O15="Completed"),(H15-F15)/(E15-D15+1)%,"") | U15: =IF(AND(A15<>"",P15="Yes"),ROW(),"") | AI15: Knowledge Gathering
K16: =IF(AND(COUNTA(B16:C16)>1,COUNTA(F16:G16)>1,O16="Completed"),(G16-F16)/(C16-B16+1)%,"") | L16: =IF(AND(COUNTA(D16:E16)>1,COUNTA(F16:G16)>1,O16="Completed"),(G16-F16)/(E16-D16+1)%,"") | R16: =IF(H16<>"",SUMIF(H$3:H16,"<>" & "",H$3:H16),"") | S16: {=IF(O16="Completed",SUMIF(W$3:W16,"<>" & "",W$3:W16),"")} | T16: {=IF(AND(J16<>"",O16="Completed"),SUM(IF(O$3:O16="Completed",J$3:J16,0)),"")} | U16: =IF(AND(A16<>"",P16="Yes"),ROW(),"") | V16: =ROW() -> 16 | W16: =IF(O16="Completed",IF(COUNT($I$3:$I$596)>0,IF(I16<>"",I16,H16),""),"") | X16: =IF(ISERROR(SMALL('Control panel'!E$3:E$23,ROW()-2)),"",INDIRECT("'Control panel'!A" & SMALL('Control panel'!E$3:E$23,ROW()-2),1)) | Y16: =IF(ISERROR(SMALL('Control panel'!D$3:D$23,ROW()-2)),"",INDIRECT("'Control panel'!B" & SMALL('Control panel'!D$3:D$23,ROW()-2),2)) | Z16: =IF(A16<>"",'Metrics planning and tracking'!$K$4,"") | AA16: =IF(A16<>"",'Metrics planning and tracking'!$K$5,"") | AB16: =IF(A16<>"",'Metrics planning and tracking'!$K$2,"") | AC16: =IF(A16<>"",'Metrics planning and tracking'!$K$3,"") | AD16: =IF(A16<>"",IF(AND(#REF!<>"",#REF!<>"",#REF!<>0),#REF!/#REF!*100,"NA"),"") | AE16: =IF(A16<>"",IF(AND(#REF!<>"",#REF!<>"",#REF!<>0),#REF!/#REF!*100,"NA"),"") | AF16: =IF($O16="Completed",IF(D16<>"",D16,IF(B16<>"",B16,"")),"") | AG16: =IF($O16="Completed",IF(E16<>"",E16,IF(C16<>"",C16,"")),"") | AH16: =IF(O16="Completed",IF(L16<>"",L16,IF(K16<>"",K16,"")),"") | AI16: Knowledge Transfer and Set-up | AV16: =IF(A16<>"",A16 & "-" &#REF! & ROW(),"")
K17: =IF(AND(COUNTA(B17:C17)>1,COUNTA(F17:G17)>1,O17="Completed"),(G17-F17)/(C17-B17+1)%,"") | L17: =IF(AND(COUNTA(D17:E17)>1,COUNTA(F17:G17)>1,O17="Completed"),(G17-F17)/(E17-D17+1)%,"") | R17: =IF(H17<>"",SUMIF(H$3:H17,"<>" & "",H$3:H17),"") | S17: {=IF(O17="Completed",SUMIF(W$3:W17,"<>" & "",W$3:W17),"")} | T17: {=IF(AND(J17<>"",O17="Completed"),SUM(IF(O$3:O17="Completed",J$3:J17,0)),"")} | U17: =IF(AND(A17<>"",P17="Yes"),ROW(),"") | V17: =ROW() -> 17 | W17: =IF(O17="Completed",IF(COUNT($I$3:$I$596)>0,IF(I17<>"",I17,H17),""),"") | X17: =IF(ISERROR(SMALL('Control panel'!E$3:E$23,ROW()-2)),"",INDIRECT("'Control panel'!A" & SMALL('Control panel'!E$3:E$23,ROW()-2),1)) | Y17: =IF(ISERROR(SMALL('Control panel'!D$3:D$23,ROW()-2)),"",INDIRECT("'Control panel'!B" & SMALL('Control panel'!D$3:D$23,ROW()-2),2)) | Z17: =IF(A17<>"",'Metrics planning and tracking'!$K$4,"") | AA17: =IF(A17<>"",'Metrics planning and tracking'!$K$5,"") | AB17: =IF(A17<>"",'Metrics planning and tracking'!$K$2,"") | AC17: =IF(A17<>"",'Metrics planning and tracking'!$K$3,"") | AD17: =IF(A17<>"",IF(AND(#REF!<>"",#REF!<>"",#REF!<>0),#REF!/#REF!*100,"NA"),"") | AE17: =IF(A17<>"",IF(AND(#REF!<>"",#REF!<>"",#REF!<>0),#REF!/#REF!*100,"NA"),"") | AF17: =IF($O17="Completed",IF(D17<>"",D17,IF(B17<>"",B17,"")),"") | AG17: =IF($O17="Completed",IF(E17<>"",E17,IF(C17<>"",C17,"")),"") | AH17: =IF(O17="Completed",IF(L17<>"",L17,IF(K17<>"",K17,"")),"") | AI17: Pre-UAT Demo | AV17: =IF(A17<>"",A17 & "-" &#REF! & ROW(),"")
K18: =IF(AND(COUNTA(B18:C18)>1,COUNTA(F18:G18)>1,O18="Completed"),(G18-F18)/(C18-B18+1)%,"") | L18: =IF(AND(COUNTA(D18:E18)>1,COUNTA(F18:G18)>1,O18="Completed"),(G18-F18)/(E18-D18+1)%,"") | R18: =IF(H18<>"",SUMIF(H$3:H18,"<>" & "",H$3:H18),"") | S18: {=IF(O18="Completed",SUMIF(W$3:W18,"<>" & "",W$3:W18),"")} | T18: {=IF(AND(J18<>"",O18="Completed"),SUM(IF(O$3:O18="Completed",J$3:J18,0)),"")} | U18: =IF(AND(A18<>"",P18="Yes"),ROW(),"") | V18: =ROW() -> 18 | W18: =IF(O18="Completed",IF(COUNT($I$3:$I$596)>0,IF(I18<>"",I18,H18),""),"") | X18: =IF(ISERROR(SMALL('Control panel'!E$3:E$23,ROW()-2)),"",INDIRECT("'Control panel'!A" & SMALL('Control panel'!E$3:E$23,ROW()-2),1)) | Y18: =IF(ISERROR(SMALL('Control panel'!D$3:D$23,ROW()-2)),"",INDIRECT("'Control panel'!B" & SMALL('Control panel'!D$3:D$23,ROW()-2),2)) | Z18: =IF(A18<>"",'Metrics planning and tracking'!$K$4,"") | AA18: =IF(A18<>"",'Metrics planning and tracking'!$K$5,"") | AB18: =IF(A18<>"",'Metrics planning and tracking'!$K$2,"") | AC18: =IF(A18<>"",'Metrics planning and tracking'!$K$3,"") | AD18: =IF(A18<>"",IF(AND(#REF!<>"",#REF!<>"",#REF!<>0),#REF!/#REF!*100,"NA"),"") | AE18: =IF(A18<>"",IF(AND(#REF!<>"",#REF!<>"",#REF!<>0),#REF!/#REF!*100,"NA"),"") | AF18: =IF($O18="Completed",IF(D18<>"",D18,IF(B18<>"",B18,"")),"") | AG18: =IF($O18="Completed",IF(E18<>"",E18,IF(C18<>"",C18,"")),"") | AH18: =IF(O18="Completed",IF(L18<>"",L18,IF(K18<>"",K18,"")),"") | AI18: Pilot Conversion | AV18: =IF(A18<>"",A18 & "-" &#REF! & ROW(),"")
K19: =IF(AND(COUNTA(B19:C19)>1,COUNTA(F19:G19)>1,O19="Completed"),(G19-F19)/(C19-B19+1)%,"") | L19: =IF(AND(COUNTA(D19:E19)>1,COUNTA(F19:G19)>1,O19="Completed"),(G19-F19)/(E19-D19+1)%,"") | R19: =IF(H19<>"",SUMIF(H$3:H19,"<>" & "",H$3:H19),"") | S19: {=IF(O19="Completed",SUMIF(W$3:W19,"<>" & "",W$3:W19),"")} | T19: {=IF(AND(J19<>"",O19="Completed"),SUM(IF(O$3:O19="Completed",J$3:J19,0)),"")} | U19: =IF(AND(A19<>"",P19="Yes"),ROW(),"") | V19: =ROW() -> 19 | W19: =IF(O19="Completed",IF(COUNT($I$3:$I$596)>0,IF(I19<>"",I19,H19),""),"") | Z19: =IF(A19<>"",'Metrics planning and tracking'!$K$4,"") | AA19: =IF(A19<>"",'Metrics planning and tracking'!$K$5,"") | AB19: =IF(A19<>"",'Metrics planning and tracking'!$K$2,"") | AC19: =IF(A19<>"",'Metrics planning and tracking'!$K$3,"") | AD19: =IF(A19<>"",IF(AND(#REF!<>"",#REF!<>"",#REF!<>0),#REF!/#REF!*100,"NA"),"") | AE19: =IF(A19<>"",IF(AND(#REF!<>"",#REF!<>"",#REF!<>0),#REF!/#REF!*100,"NA"),"") | AF19: =IF($O19="Completed",IF(D19<>"",D19,IF(B19<>"",B19,"")),"") | AG19: =IF($O19="Completed",IF(E19<>"",E19,IF(C19<>"",C19,"")),"") | AH19: =IF(O19="Completed",IF(L19<>"",L19,IF(K19<>"",K19,"")),"") | AI19: Place and Route | AV19: =IF(A19<>"",A19 & "-" &#REF! & ROW(),"")
K20: =IF(AND(COUNTA(B20:C20)>1,COUNTA(F20:G20)>1,O20="Completed"),(G20-F20)/(C20-B20+1)%,"") | L20: =IF(AND(COUNTA(D20:E20)>1,COUNTA(F20:G20)>1,O20="Completed"),(G20-F20)/(E20-D20+1)%,"") | R20: =IF(H20<>"",SUMIF(H$3:H20,"<>" & "",H$3:H20),"") | S20: {=IF(O20="Completed",SUMIF(W$3:W20,"<>" & "",W$3:W20),"")} | T20: {=IF(AND(J20<>"",O20="Completed"),SUM(IF(O$3:O20="Completed",J$3:J20,0)),"")} | U20: =IF(AND(A20<>"",P20="Yes"),ROW(),"") | V20: =ROW() -> 20 | W20: =IF(O20="Completed",IF(COUNT($I$3:$I$596)>0,IF(I20<>"",I20,H20),""),"") | Z20: =IF(A20<>"",'Metrics planning and tracking'!$K$4,"") | AA20: =IF(A20<>"",'Metrics planning and tracking'!$K$5,"") | AB20: =IF(A20<>"",'Metrics planning and tracking'!$K$2,"") | AC20: =IF(A20<>"",'Metrics planning and tracking'!$K$3,"") | AD20: =IF(A20<>"",IF(AND(#REF!<>"",#REF!<>"",#REF!<>0),#REF!/#REF!*100,"NA"),"") | AE20: =IF(A20<>"",IF(AND(#REF!<>"",#REF!<>"",#REF!<>0),#REF!/#REF!*100,"NA"),"") | AF20: =IF($O20="Completed",IF(D20<>"",D20,IF(B20<>"",B20,"")),"") | AG20: =IF($O20="Completed",IF(E20<>"",E20,IF(C20<>"",C20,"")),"") | AH20: =IF(O20="Completed",IF(L20<>"",L20,IF(K20<>"",K20,"")),"") | AI20: Project Planning | AV20: =IF(A20<>"",A20 & "-" &#REF! & ROW(),"")
K21: =IF(AND(COUNTA(B21:C21)>1,COUNTA(F21:G21)>1,O21="Completed"),(G21-F21)/(C21-B21+1)%,"") | L21: =IF(AND(COUNTA(D21:E21)>1,COUNTA(F21:G21)>1,O21="Completed"),(G21-F21)/(E21-D21+1)%,"") | U21: =IF(AND(A21<>"",P21="Yes"),ROW(),"") | AI21: Production Deployment
K22: =IF(AND(COUNTA(B22:C22)>1,COUNTA(F22:G22)>1,O22="Completed"),(G22-F22)/(C22-B22+1)%,"") | L22: =IF(AND(COUNTA(D22:E22)>1,COUNTA(F22:G22)>1,O22="Completed"),(G22-F22)/(E22-D22+1)%,"") | R22: =IF(H22<>"",SUMIF(H$3:H22,"<>" & "",H$3:H22),"") | S22: {=IF(O22="Completed",SUMIF(W$3:W22,"<>" & "",W$3:W22),"")} | T22: {=IF(AND(J22<>"",O22="Completed"),SUM(IF(O$3:O22="Completed",J$3:J22,0)),"")} | U22: =IF(AND(A22<>"",P22="Yes"),ROW(),"") | V22: =ROW() -> 22 | W22: =IF(O22="Completed",IF(COUNT($I$3:$I$596)>0,IF(I22<>"",I22,H22),""),"") | Z22: =IF(A22<>"",'Metrics planning and tracking'!$K$4,"") | AA22: =IF(A22<>"",'Metrics planning and tracking'!$K$5,"") | AB22: =IF(A22<>"",'Metrics planning and tracking'!$K$2,"") | AC22: =IF(A22<>"",'Metrics planning and tracking'!$K$3,"") | AD22: =IF(A22<>"",IF(AND(#REF!<>"",#REF!<>"",#REF!<>0),#REF!/#REF!*100,"NA"),"") | AE22: =IF(A22<>"",IF(AND(#REF!<>"",#REF!<>"",#REF!<>0),#REF!/#REF!*100,"NA"),"") | AF22: =IF($O22="Completed",IF(D22<>"",D22,IF(B22<>"",B22,"")),"") | AG22: =IF($O22="Completed",IF(E22<>"",E22,IF(C22<>"",C22,"")),"") | AH22: =IF(O22="Completed",IF(L22<>"",L22,IF(K22<>"",K22,"")),"") | AI22: Regression Testing | AV22: =IF(A22<>"",A22 & "-" &#REF! & ROW(),"")
K23: =IF(AND(COUNTA(B23:C23)>1,COUNTA(F23:G23)>1,O23="Completed"),(G23-F23)/(C23-B23+1)%,"") | L23: =IF(AND(COUNTA(D23:E23)>1,COUNTA(F23:G23)>1,O23="Completed"),(G23-F23)/(E23-D23+1)%,"") | R23: =IF(H23<>"",SUMIF(H$3:H23,"<>" & "",H$3:H23),"") | S23: {=IF(O23="Completed",SUMIF(W$3:W23,"<>" & "",W$3:W23),"")} | T23: {=IF(AND(J23<>"",O23="Completed"),SUM(IF(O$3:O23="Completed",J$3:J23,0)),"")} | U23: =IF(AND(A23<>"",P23="Yes"),ROW(),"") | V23: =ROW() -> 23 | W23: =IF(O23="Completed",IF(COUNT($I$3:$I$596)>0,IF(I23<>"",I23,H23),""),"") | Z23: =IF(A23<>"",'Metrics planning and tracking'!$K$4,"") | AA23: =IF(A23<>"",'Metrics planning and tracking'!$K$5,"") | AB23: =IF(A23<>"",'Metrics planning and tracking'!$K$2,"") | AC23: =IF(A23<>"",'Metrics planning and tracking'!$K$3,"") | AD23: =IF(A23<>"",IF(AND(#REF!<>"",#REF!<>"",#REF!<>0),#REF!/#REF!*100,"NA"),"") | AE23: =IF(A23<>"",IF(AND(#REF!<>"",#REF!<>"",#REF!<>0),#REF!/#REF!*100,"NA"),"") | AF23: =IF($O23="Completed",IF(D23<>"",D23,IF(B23<>"",B23,"")),"") | AG23: =IF($O23="Completed",IF(E23<>"",E23,IF(C23<>"",C23,"")),"") | AH23: =IF(O23="Completed",IF(L23<>"",L23,IF(K23<>"",K23,"")),"") | AI23: Reqt Collection / Analysis | AV23: =IF(A23<>"",A23 & "-" &#REF! & ROW(),"")
K24: =IF(AND(COUNTA(B24:C24)>1,COUNTA(F24:G24)>1,O24="Completed"),(G24-F24)/(C24-B24+1)%,"") | L24: =IF(AND(COUNTA(D24:E24)>1,COUNTA(F24:G24)>1,O24="Completed"),(G24-F24)/(E24-D24+1)%,"") | R24: =IF(H24<>"",SUMIF(H$3:H24,"<>" & "",H$3:H24),"") | S24: {=IF(O24="Completed",SUMIF(W$3:W24,"<>" & "",W$3:W24),"")} | T24: {=IF(AND(J24<>"",O24="Completed"),SUM(IF(O$3:O24="Completed",J$3:J24,0)),"")} | U24: =IF(AND(A24<>"",P24="Yes"),ROW(),"") | V24: =ROW() -> 24 | W24: =IF(O24="Completed",IF(COUNT($I$3:$I$596)>0,IF(I24<>"",I24,H24),""),"") | Z24: =IF(A24<>"",'Metrics planning and tracking'!$K$4,"") | AA24: =IF(A24<>"",'Metrics planning and tracking'!$K$5,"") | AB24: =IF(A24<>"",'Metrics planning and tracking'!$K$2,"") | AC24: =IF(A24<>"",'Metrics planning and tracking'!$K$3,"") | AD24: =IF(A24<>"",IF(AND(#REF!<>"",#REF!<>"",#REF!<>0),#REF!/#REF!*100,"NA"),"") | AE24: =IF(A24<>"",IF(AND(#REF!<>"",#REF!<>"",#REF!<>0),#REF!/#REF!*100,"NA"),"") | AF24: =IF($O24="Completed",IF(D24<>"",D24,IF(B24<>"",B24,"")),"") | AG24: =IF($O24="Completed",IF(E24<>"",E24,IF(C24<>"",C24,"")),"") | AH24: =IF(O24="Completed",IF(L24<>"",L24,IF(K24<>"",K24,"")),"") | AI24: Requirements specification | AV24: =IF(A24<>"",A24 & "-" &#REF! & ROW(),"")
K25: =IF(AND(COUNTA(B25:C25)>1,COUNTA(F25:G25)>1,O25="Completed"),(G25-F25)/(C25-B25+1)%,"") | L25: =IF(AND(COUNTA(D25:E25)>1,COUNTA(F25:G25)>1,O25="Completed"),(G25-F25)/(E25-D25+1)%,"") | R25: =IF(H25<>"",SUMIF(H$3:H25,"<>" & "",H$3:H25),"") | S25: {=IF(O25="Completed",SUMIF(W$3:W25,"<>" & "",W$3:W25),"")} | T25: {=IF(AND(J25<>"",O25="Completed"),SUM(IF(O$3:O25="Completed",J$3:J25,0)),"")} | U25: =IF(AND(A25<>"",P25="Yes"),ROW(),"") | V25: =ROW() -> 25 | W25: =IF(O25="Completed",IF(COUNT($I$3:$I$596)>0,IF(I25<>"",I25,H25),""),"") | Z25: =IF(A25<>"",'Metrics planning and tracking'!$K$4,"") | AA25: =IF(A25<>"",'Metrics planning and tracking'!$K$5,"") | AB25: =IF(A25<>"",'Metrics planning and tracking'!$K$2,"") | AC25: =IF(A25<>"",'Metrics planning and tracking'!$K$3,"") | AD25: =IF(A25<>"",IF(AND(#REF!<>"",#REF!<>"",#REF!<>0),#REF!/#REF!*100,"NA"),"") | AE25: =IF(A25<>"",IF(AND(#REF!<>"",#REF!<>"",#REF!<>0),#REF!/#REF!*100,"NA"),"") | AF25: =IF($O25="Completed",IF(D25<>"",D25,IF(B25<>"",B25,"")),"") | AG25: =IF($O25="Completed",IF(E25<>"",E25,IF(C25<>"",C25,"")),"") | AH25: =IF(O25="Completed",IF(L25<>"",L25,IF(K25<>"",K25,"")),"") | AI25: Schematics | AV25: =IF(A25<>"",A25 & "-" &#REF! & ROW(),"")
K26: =IF(AND(COUNTA(B26:C26)>1,COUNTA(F26:G26)>1,O26="Completed"),(G26-F26)/(C26-B26+1)%,"") | L26: =IF(AND(COUNTA(D26:E26)>1,COUNTA(F26:G26)>1,O26="Completed"),(G26-F26)/(E26-D26+1)%,"") | R26: =IF(H26<>"",SUMIF(H$3:H26,"<>" & "",H$3:H26),"") | S26: {=IF(O26="Completed",SUMIF(W$3:W26,"<>" & "",W$3:W26),"")} | T26: {=IF(AND(J26<>"",O26="Completed"),SUM(IF(O$3:O26="Completed",J$3:J26,0)),"")} | U26: =IF(AND(A26<>"",P26="Yes"),ROW(),"") | V26: =ROW() -> 26 | W26: =IF(O26="Completed",IF(COUNT($I$3:$I$596)>0,IF(I26<>"",I26,H26),""),"") | Z26: =IF(A26<>"",'Metrics planning and tracking'!$K$4,"") | AA26: =IF(A26<>"",'Metrics planning and tracking'!$K$5,"") | AB26: =IF(A26<>"",'Metrics planning and tracking'!$K$2,"") | AC26: =IF(A26<>"",'Metrics planning and tracking'!$K$3,"") | AD26: =IF(A26<>"",IF(AND(#REF!<>"",#REF!<>"",#REF!<>0),#REF!/#REF!*100,"NA"),"") | AE26: =IF(A26<>"",IF(AND(#REF!<>"",#REF!<>"",#REF!<>0),#REF!/#REF!*100,"NA"),"") | AF26: =IF($O26="Completed",IF(D26<>"",D26,IF(B26<>"",B26,"")),"") | AG26: =IF($O26="Completed",IF(E26<>"",E26,IF(C26<>"",C26,"")),"") | AH26: =IF(O26="Completed",IF(L26<>"",L26,IF(K26<>"",K26,"")),"") | AI26: Simulation | AV26: =IF(A26<>"",A26 & "-" &#REF! & ROW(),"")
K27: =IF(AND(COUNTA(B27:C27)>1,COUNTA(F27:G27)>1,O27="Completed"),(G27-F27)/(C27-B27+1)%,"") | L27: =IF(AND(COUNTA(D27:E27)>1,COUNTA(F27:G27)>1,O27="Completed"),(G27-F27)/(E27-D27+1)%,"") | R27: =IF(H27<>"",SUMIF(H$3:H27,"<>" & "",H$3:H27),"") | S27: {=IF(O27="Completed",SUMIF(W$3:W27,"<>" & "",W$3:W27),"")} | T27: {=IF(AND(J27<>"",O27="Completed"),SUM(IF(O$3:O27="Completed",J$3:J27,0)),"")} | U27: =IF(AND(A27<>"",P27="Yes"),ROW(),"") | V27: =ROW() -> 27 | W27: =IF(O27="Completed",IF(COUNT($I$3:$I$596)>0,IF(I27<>"",I27,H27),""),"") | Z27: =IF(A27<>"",'Metrics planning and tracking'!$K$4,"") | AA27: =IF(A27<>"",'Metrics planning and tracking'!$K$5,"") | AB27: =IF(A27<>"",'Metrics planning and tracking'!$K$2,"") | AC27: =IF(A27<>"",'Metrics planning and tracking'!$K$3,"") | AD27: =IF(A27<>"",IF(AND(#REF!<>"",#REF!<>"",#REF!<>0),#REF!/#REF!*100,"NA"),"") | AE27: =IF(A27<>"",IF(AND(#REF!<>"",#REF!<>"",#REF!<>0),#REF!/#REF!*100,"NA"),"") | AF27: =IF($O27="Completed",IF(D27<>"",D27,IF(B27<>"",B27,"")),"") | AG27: =IF($O27="Completed",IF(E27<>"",E27,IF(C27<>"",C27,"")),"") | AH27: =IF(O27="Completed",IF(L27<>"",L27,IF(K27<>"",K27,"")),"") | AI27: Synthesis | AV27: =IF(A27<>"",A27 & "-" &#REF! & ROW(),"")
K28: =IF(AND(COUNTA(B28:C28)>1,COUNTA(F28:G28)>1,O28="Completed"),(G28-C28)/(C28-#REF!+1)%,"") | L28: =IF(AND(COUNT(D28:E28)>0,COUNTA(F28:G28)>1,O28="Completed"),(G28-AG28)/(AG28-#REF!+1)%,"") | M28: =IF(AND(T28<>"",T28<>0,R28<>"",R28<>0),(T28-R28)/R28%,IF(AND(H28<>"",H28<>0,OR(J28="",J28=0)),"Actual Effort reqd.","")) | N28: =IF(AND(T28<>"",T28<>0,S28<>"",S28<>0),(T28-S28)/S28%,IF(AND(I28<>"",I28<>0,OR(J28="",J28=0)),"Actual Effort reqd.","")) | R28: =IF(H28<>"",SUMIF(H$3:H28,"<>" & "",H$3:H28),"") | S28: {=IF(O28="Completed",SUMIF(W$3:W28,"<>" & "",W$3:W28),"")} | T28: {=IF(AND(J28<>"",O28="Completed"),SUM(IF(O$3:O28="Completed",J$3:J28,0)),"")} | U28: =IF(AND(A28<>"",P28="Yes"),ROW(),"") | V28: =ROW() -> 28 | W28: =IF(O28="Completed",IF(COUNT($I$3:$I$596)>0,IF(I28<>"",I28,H28),""),"") | Z28: =IF(A28<>"",'Metrics planning and tracking'!$K$4,"") | AA28: =IF(A28<>"",'Metrics planning and tracking'!$K$5,"") | AB28: =IF(A28<>"",'Metrics planning and tracking'!$K$2,"") | AC28: =IF(A28<>"",'Metrics planning and tracking'!$K$3,"") | AD28: =IF(A28<>"",IF(AND(#REF!<>"",#REF!<>"",#REF!<>0),#REF!/#REF!*100,"NA"),"") | AE28: =IF(A28<>"",IF(AND(#REF!<>"",#REF!<>"",#REF!<>0),#REF!/#REF!*100,"NA"),"") | AF28: =IF($O28="Completed",IF(D28<>"",D28,IF(B28<>"",B28,"")),"") | AG28: =IF($O28="Completed",IF(E28<>"",E28,IF(C28<>"",C28,"")),"") | AH28: =IF(O28="Completed",IF(L28<>"",L28,IF(K28<>"",K28,"")),"") | AI28: Symbol Creation | AV28: =IF(A28<>"",A28 & "-" &#REF! & ROW(),"")
K29: =IF(AND(COUNTA(B29:C29)>1,COUNTA(F29:G29)>1,O29="Completed"),(G29-C29)/(C29-#REF!+1)%,"") | L29: =IF(AND(COUNT(D29:E29)>0,COUNTA(F29:G29)>1,O29="Completed"),(G29-AG29)/(AG29-#REF!+1)%,"") | M29: =IF(AND(T29<>"",T29<>0,R29<>"",R29<>0),(T29-R29)/R29%,IF(AND(H29<>"",H29<>0,OR(J29="",J29=0)),"Actual Effort reqd.","")) | N29: =IF(AND(T29<>"",T29<>0,S29<>"",S29<>0),(T29-S29)/S29%,IF(AND(I29<>"",I29<>0,OR(J29="",J29=0)),"Actual Effort reqd.","")) | R29: =IF(H29<>"",SUMIF(H$3:H29,"<>" & "",H$3:H29),"") | S29: {=IF(O29="Completed",SUMIF(W$3:W29,"<>" & "",W$3:W29),"")} | T29: {=IF(AND(J29<>"",O29="Completed"),SUM(IF(O$3:O29="Completed",J$3:J29,0)),"")} | U29: =IF(AND(A29<>"",P29="Yes"),ROW(),"") | V29: =ROW() -> 29 | W29: =IF(O29="Completed",IF(COUNT($I$3:$I$596)>0,IF(I29<>"",I29,H29),""),"") | Z29: =IF(A29<>"",'Metrics planning and tracking'!$K$4,"") | AA29: =IF(A29<>"",'Metrics planning and tracking'!$K$5,"") | AB29: =IF(A29<>"",'Metrics planning and tracking'!$K$2,"") | AC29: =IF(A29<>"",'Metrics planning and tracking'!$K$3,"") | AD29: =IF(A29<>"",IF(AND(#REF!<>"",#REF!<>"",#REF!<>0),#REF!/#REF!*100,"NA"),"") | AE29: =IF(A29<>"",IF(AND(#REF!<>"",#REF!<>"",#REF!<>0),#REF!/#REF!*100,"NA"),"") | AF29: =IF($O29="Completed",IF(D29<>"",D29,IF(B29<>"",B29,"")),"") | AG29: =IF($O29="Completed",IF(E29<>"",E29,IF(C29<>"",C29,"")),"") | AH29: =IF(O29="Completed",IF(L29<>"",L29,IF(K29<>"",K29,"")),"") | AI29: System and Requirements Study | AV29: =IF(A29<>"",A29 & "-" &#REF! & ROW(),"")
K30: =IF(AND(COUNTA(B30:C30)>1,COUNTA(F30:G30)>1,O30="Completed"),(G30-C30)/(C30-#REF!+1)%,"") | L30: =IF(AND(COUNT(D30:E30)>0,COUNTA(F30:G30)>1,O30="Completed"),(G30-AG30)/(AG30-#REF!+1)%,"") | M30: =IF(AND(T30<>"",T30<>0,R30<>"",R30<>0),(T30-R30)/R30%,IF(AND(H30<>"",H30<>0,OR(J30="",J30=0)),"Actual Effort reqd.","")) | N30: =IF(AND(T30<>"",T30<>0,S30<>"",S30<>0),(T30-S30)/S30%,IF(AND(I30<>"",I30<>0,OR(J30="",J30=0)),"Actual Effort reqd.","")) | R30: =IF(H30<>"",SUMIF(H$3:H30,"<>" & "",H$3:H30),"") | S30: {=IF(O30="Completed",SUMIF(W$3:W30,"<>" & "",W$3:W30),"")} | T30: {=IF(AND(J30<>"",O30="Completed"),SUM(IF(O$3:O30="Completed",J$3:J30,0)),"")} | U30: =IF(AND(A30<>"",P30="Yes"),ROW(),"") | V30: =ROW() -> 30 | W30: =IF(O30="Completed",IF(COUNT($I$3:$I$596)>0,IF(I30<>"",I30,H30),""),"") | Z30: =IF(A30<>"",'Metrics planning and tracking'!$K$4,"") | AA30: =IF(A30<>"",'Metrics planning and tracking'!$K$5,"") | AB30: =IF(A30<>"",'Metrics planning and tracking'!$K$2,"") | AC30: =IF(A30<>"",'Metrics planning and tracking'!$K$3,"") | AD30: =IF(A30<>"",IF(AND(#REF!<>"",#REF!<>"",#REF!<>0),#REF!/#REF!*100,"NA"),"") | AE30: =IF(A30<>"",IF(AND(#REF!<>"",#REF!<>"",#REF!<>0),#REF!/#REF!*100,"NA"),"") | AF30: =IF($O30="Completed",IF(D30<>"",D30,IF(B30<>"",B30,"")),"") | AG30: =IF($O30="Completed",IF(E30<>"",E30,IF(C30<>"",C30,"")),"") | AH30: =IF(O30="Completed",IF(L30<>"",L30,IF(K30<>"",K30,"")),"") | AI30: System testing | AV30: =IF(A30<>"",A30 & "-" &#REF! & ROW(),"")
K31: =IF(AND(COUNTA(B31:C31)>1,COUNTA(F31:G31)>1,O31="Completed"),(G31-C31)/(C31-#REF!+1)%,"") | L31: =IF(AND(COUNT(D31:E31)>0,COUNTA(F31:G31)>1,O31="Completed"),(G31-AG31)/(AG31-#REF!+1)%,"") | M31: =IF(AND(T31<>"",T31<>0,R31<>"",R31<>0),(T31-R31)/R31%,IF(AND(H31<>"",H31<>0,OR(J31="",J31=0)),"Actual Effort reqd.","")) | N31: =IF(AND(T31<>"",T31<>0,S31<>"",S31<>0),(T31-S31)/S31%,IF(AND(I31<>"",I31<>0,OR(J31="",J31=0)),"Actual Effort reqd.","")) | R31: =IF(H31<>"",SUMIF(H$3:H31,"<>" & "",H$3:H31),"") | S31: {=IF(O31="Completed",SUMIF(W$3:W31,"<>" & "",W$3:W31),"")} | T31: {=IF(AND(J31<>"",O31="Completed"),SUM(IF(O$3:O31="Completed",J$3:J31,0)),"")} | U31: =IF(AND(A31<>"",P31="Yes"),ROW(),"") | V31: =ROW() -> 31 | W31: =IF(O31="Completed",IF(COUNT($I$3:$I$596)>0,IF(I31<>"",I31,H31),""),"") | Z31: =IF(A31<>"",'Metrics planning and tracking'!$K$4,"") | AA31: =IF(A31<>"",'Metrics planning and tracking'!$K$5,"") | AB31: =IF(A31<>"",'Metrics planning and tracking'!$K$2,"") | AC31: =IF(A31<>"",'Metrics planning and tracking'!$K$3,"") | AD31: =IF(A31<>"",IF(AND(#REF!<>"",#REF!<>"",#REF!<>0),#REF!/#REF!*100,"NA"),"") | AE31: =IF(A31<>"",IF(AND(#REF!<>"",#REF!<>"",#REF!<>0),#REF!/#REF!*100,"NA"),"") | AF31: =IF($O31="Completed",IF(D31<>"",D31,IF(B31<>"",B31,"")),"") | AG31: =IF($O31="Completed",IF(E31<>"",E31,IF(C31<>"",C31,"")),"") | AH31: =IF(O31="Completed",IF(L31<>"",L31,IF(K31<>"",K31,"")),"") | AI31: Tech Spec | AV31: =IF(A31<>"",A31 & "-" &#REF! & ROW(),"")
K32: =IF(AND(COUNTA(B32:C32)>1,COUNTA(F32:G32)>1,O32="Completed"),(G32-C32)/(C32-#REF!+1)%,"") | L32: =IF(AND(COUNT(D32:E32)>0,COUNTA(F32:G32)>1,O32="Completed"),(G32-AG32)/(AG32-#REF!+1)%,"") | M32: =IF(AND(T32<>"",T32<>0,R32<>"",R32<>0),(T32-R32)/R32%,IF(AND(H32<>"",H32<>0,OR(J32="",J32=0)),"Actual Effort reqd.","")) | N32: =IF(AND(T32<>"",T32<>0,S32<>"",S32<>0),(T32-S32)/S32%,IF(AND(I32<>"",I32<>0,OR(J32="",J32=0)),"Actual Effort reqd.","")) | R32: =IF(H32<>"",SUMIF(H$3:H32,"<>" & "",H$3:H32),"") | S32: {=IF(O32="Completed",SUMIF(W$3:W32,"<>" & "",W$3:W32),"")} | T32: {=IF(AND(J32<>"",O32="Completed"),SUM(IF(O$3:O32="Completed",J$3:J32,0)),"")} | U32: =IF(AND(A32<>"",P32="Yes"),ROW(),"") | V32: =ROW() -> 32 | W32: =IF(O32="Completed",IF(COUNT($I$3:$I$596)>0,IF(I32<>"",I32,H32),""),"") | Z32: =IF(A32<>"",'Metrics planning and tracking'!$K$4,"") | AA32: =IF(A32<>"",'Metrics planning and tracking'!$K$5,"") | AB32: =IF(A32<>"",'Metrics planning and tracking'!$K$2,"") | AC32: =IF(A32<>"",'Metrics planning and tracking'!$K$3,"") | AD32: =IF(A32<>"",IF(AND(#REF!<>"",#REF!<>"",#REF!<>0),#REF!/#REF!*100,"NA"),"") | AE32: =IF(A32<>"",IF(AND(#REF!<>"",#REF!<>"",#REF!<>0),#REF!/#REF!*100,"NA"),"") | AF32: =IF($O32="Completed",IF(D32<>"",D32,IF(B32<>"",B32,"")),"") | AG32: =IF($O32="Completed",IF(E32<>"",E32,IF(C32<>"",C32,"")),"") | AH32: =IF(O32="Completed",IF(L32<>"",L32,IF(K32<>"",K32,"")),"") | AI32: Test Execution and Defect Management | AV32: =IF(A32<>"",A32 & "-" &#REF! & ROW(),"")
K33: =IF(AND(COUNTA(B33:C33)>1,COUNTA(F33:G33)>1,O33="Completed"),(G33-C33)/(C33-#REF!+1)%,"") | L33: =IF(AND(COUNT(D33:E33)>0,COUNTA(F33:G33)>1,O33="Completed"),(G33-AG33)/(AG33-#REF!+1)%,"") | M33: =IF(AND(T33<>"",T33<>0,R33<>"",R33<>0),(T33-R33)/R33%,IF(AND(H33<>"",H33<>0,OR(J33="",J33=0)),"Actual Effort reqd.","")) | N33: =IF(AND(T33<>"",T33<>0,S33<>"",S33<>0),(T33-S33)/S33%,IF(AND(I33<>"",I33<>0,OR(J33="",J33=0)),"Actual Effort reqd.","")) | R33: =IF(H33<>"",SUMIF(H$3:H33,"<>" & "",H$3:H33),"") | S33: {=IF(O33="Completed",SUMIF(W$3:W33,"<>" & "",W$3:W33),"")} | T33: {=IF(AND(J33<>"",O33="Completed"),SUM(IF(O$3:O33="Completed",J$3:J33,0)),"")} | U33: =IF(AND(A33<>"",P33="Yes"),ROW(),"") | V33: =ROW() -> 33 | W33: =IF(O33="Completed",IF(COUNT($I$3:$I$596)>0,IF(I33<>"",I33,H33),""),"") | Z33: =IF(A33<>"",'Metrics planning and tracking'!$K$4,"") | AA33: =IF(A33<>"",'Metrics planning and tracking'!$K$5,"") | AB33: =IF(A33<>"",'Metrics planning and tracking'!$K$2,"") | AC33: =IF(A33<>"",'Metrics planning and tracking'!$K$3,"") | AD33: =IF(A33<>"",IF(AND(#REF!<>"",#REF!<>"",#REF!<>0),#REF!/#REF!*100,"NA"),"") | AE33: =IF(A33<>"",IF(AND(#REF!<>"",#REF!<>"",#REF!<>0),#REF!/#REF!*100,"NA"),"") | AF33: =IF($O33="Completed",IF(D33<>"",D33,IF(B33<>"",B33,"")),"") | AG33: =IF($O33="Completed",IF(E33<>"",E33,IF(C33<>"",C33,"")),"") | AH33: =IF(O33="Completed",IF(L33<>"",L33,IF(K33<>"",K33,"")),"") | AI33: Test Planning | AV33: =IF(A33<>"",A33 & "-" &#REF! & ROW(),"")
K34: =IF(AND(COUNTA(B34:C34)>1,COUNTA(F34:G34)>1,O34="Completed"),(G34-C34)/(C34-#REF!+1)%,"") | L34: =IF(AND(COUNT(D34:E34)>0,COUNTA(F34:G34)>1,O34="Completed"),(G34-AG34)/(AG34-#REF!+1)%,"") | M34: =IF(AND(T34<>"",T34<>0,R34<>"",R34<>0),(T34-R34)/R34%,IF(AND(H34<>"",H34<>0,OR(J34="",J34=0)),"Actual Effort reqd.","")) | N34: =IF(AND(T34<>"",T34<>0,S34<>"",S34<>0),(T34-S34)/S34%,IF(AND(I34<>"",I34<>0,OR(J34="",J34=0)),"Actual Effort reqd.","")) | R34: =IF(H34<>"",SUMIF(H$3:H34,"<>" & "",H$3:H34),"") | S34: {=IF(O34="Completed",SUMIF(W$3:W34,"<>" & "",W$3:W34),"")} | T34: {=IF(AND(J34<>"",O34="Completed"),SUM(IF(O$3:O34="Completed",J$3:J34,0)),"")} | U34: =IF(AND(A34<>"",P34="Yes"),ROW(),"") | V34: =ROW() -> 34 | W34: =IF(O34="Completed",IF(COUNT($I$3:$I$596)>0,IF(I34<>"",I34,H34),""),"") | Z34: =IF(A34<>"",'Metrics planning and tracking'!$K$4,"") | AA34: =IF(A34<>"",'Metrics planning and tracking'!$K$5,"") | AB34: =IF(A34<>"",'Metrics planning and tracking'!$K$2,"") | AC34: =IF(A34<>"",'Metrics planning and tracking'!$K$3,"") | AD34: =IF(A34<>"",IF(AND(#REF!<>"",#REF!<>"",#REF!<>0),#REF!/#REF!*100,"NA"),"") | AE34: =IF(A34<>"",IF(AND(#REF!<>"",#REF!<>"",#REF!<>0),#REF!/#REF!*100,"NA"),"") | AF34: =IF($O34="Completed",IF(D34<>"",D34,IF(B34<>"",B34,"")),"") | AG34: =IF($O34="Completed",IF(E34<>"",E34,IF(C34<>"",C34,"")),"") | AH34: =IF(O34="Completed",IF(L34<>"",L34,IF(K34<>"",K34,"")),"") | AI34: Test Planning | AV34: =IF(A34<>"",A34 & "-" &#REF! & ROW(),"")
K35: =IF(AND(COUNTA(B35:C35)>1,COUNTA(F35:G35)>1,O35="Completed"),(G35-C35)/(C35-#REF!+1)%,"") | L35: =IF(AND(COUNT(D35:E35)>0,COUNTA(F35:G35)>1,O35="Completed"),(G35-AG35)/(AG35-#REF!+1)%,"") | M35: =IF(AND(T35<>"",T35<>0,R35<>"",R35<>0),(T35-R35)/R35%,IF(AND(H35<>"",H35<>0,OR(J35="",J35=0)),"Actual Effort reqd.","")) | N35: =IF(AND(T35<>"",T35<>0,S35<>"",S35<>0),(T35-S35)/S35%,IF(AND(I35<>"",I35<>0,OR(J35="",J35=0)),"Actual Effort reqd.","")) | R35: =IF(H35<>"",SUMIF(H$3:H35,"<>" & "",H$3:H35),"") | S35: {=IF(O35="Completed",SUMIF(W$3:W35,"<>" & "",W$3:W35),"")} | T35: {=IF(AND(J35<>"",O35="Completed"),SUM(IF(O$3:O35="Completed",J$3:J35,0)),"")} | U35: =IF(AND(A35<>"",P35="Yes"),ROW(),"") | V35: =ROW() -> 35 | W35: =IF(O35="Completed",IF(COUNT($I$3:$I$596)>0,IF(I35<>"",I35,H35),""),"") | Z35: =IF(A35<>"",'Metrics planning and tracking'!$K$4,"") | AA35: =IF(A35<>"",'Metrics planning and tracking'!$K$5,"") | AB35: =IF(A35<>"",'Metrics planning and tracking'!$K$2,"") | AC35: =IF(A35<>"",'Metrics planning and tracking'!$K$3,"") | AD35: =IF(A35<>"",IF(AND(#REF!<>"",#REF!<>"",#REF!<>0),#REF!/#REF!*100,"NA"),"") | AE35: =IF(A35<>"",IF(AND(#REF!<>"",#REF!<>"",#REF!<>0),#REF!/#REF!*100,"NA"),"") | AF35: =IF($O35="Completed",IF(D35<>"",D35,IF(B35<>"",B35,"")),"") | AG35: =IF($O35="Completed",IF(E35<>"",E35,IF(C35<>"",C35,"")),"") | AH35: =IF(O35="Completed",IF(L35<>"",L35,IF(K35<>"",K35,"")),"") | AI35: UAT | AV35: =IF(A35<>"",A35 & "-" &#REF! & ROW(),"")
K36: =IF(AND(COUNTA(B36:C36)>1,COUNTA(F36:G36)>1,O36="Completed"),(G36-C36)/(C36-#REF!+1)%,"") | L36: =IF(AND(COUNT(D36:E36)>0,COUNTA(F36:G36)>1,O36="Completed"),(G36-AG36)/(AG36-#REF!+1)%,"") | M36: =IF(AND(T36<>"",T36<>0,R36<>"",R36<>0),(T36-R36)/R36%,IF(AND(H36<>"",H36<>0,OR(J36="",J36=0)),"Actual Effort reqd.","")) | N36: =IF(AND(T36<>"",T36<>0,S36<>"",S36<>0),(T36-S36)/S36%,IF(AND(I36<>"",I36<>0,OR(J36="",J36=0)),"Actual Effort reqd.","")) | R36: =IF(H36<>"",SUMIF(H$3:H36,"<>" & "",H$3:H36),"") | S36: {=IF(O36="Completed",SUMIF(W$3:W36,"<>" & "",W$3:W36),"")} | T36: {=IF(AND(J36<>"",O36="Completed"),SUM(IF(O$3:O36="Completed",J$3:J36,0)),"")} | U36: =IF(AND(A36<>"",P36="Yes"),ROW(),"") | V36: =ROW() -> 36 | W36: =IF(O36="Completed",IF(COUNT($I$3:$I$596)>0,IF(I36<>"",I36,H36),""),"") | Z36: =IF(A36<>"",'Metrics planning and tracking'!$K$4,"") | AA36: =IF(A36<>"",'Metrics planning and tracking'!$K$5,"") | AB36: =IF(A36<>"",'Metrics planning and tracking'!$K$2,"") | AC36: =IF(A36<>"",'Metrics planning and tracking'!$K$3,"") | AD36: =IF(A36<>"",IF(AND(#REF!<>"",#REF!<>"",#REF!<>0),#REF!/#REF!*100,"NA"),"") | AE36: =IF(A36<>"",IF(AND(#REF!<>"",#REF!<>"",#REF!<>0),#REF!/#REF!*100,"NA"),"") | AF36: =IF($O36="Completed",IF(D36<>"",D36,IF(B36<>"",B36,"")),"") | AG36: =IF($O36="Completed",IF(E36<>"",E36,IF(C36<>"",C36,"")),"") | AH36: =IF(O36="Completed",IF(L36<>"",L36,IF(K36<>"",K36,"")),"") | AI36: Unit testing | AV36: =IF(A36<>"",A36 & "-" &#REF! & ROW(),"")
K37: =IF(AND(COUNTA(B37:C37)>1,COUNTA(F37:G37)>1,O37="Completed"),(G37-C37)/(C37-#REF!+1)%,"") | L37: =IF(AND(COUNT(D37:E37)>0,COUNTA(F37:G37)>1,O37="Completed"),(G37-AG37)/(AG37-#REF!+1)%,"") | M37: =IF(AND(T37<>"",T37<>0,R37<>"",R37<>0),(T37-R37)/R37%,IF(AND(H37<>"",H37<>0,OR(J37="",J37=0)),"Actual Effort reqd.","")) | N37: =IF(AND(T37<>"",T37<>0,S37<>"",S37<>0),(T37-S37)/S37%,IF(AND(I37<>"",I37<>0,OR(J37="",J37=0)),"Actual Effort reqd.","")) | R37: =IF(H37<>"",SUMIF(H$3:H37,"<>" & "",H$3:H37),"") | S37: {=IF(O37="Completed",SUMIF(W$3:W37,"<>" & "",W$3:W37),"")} | T37: {=IF(AND(J37<>"",O37="Completed"),SUM(IF(O$3:O37="Completed",J$3:J37,0)),"")} | U37: =IF(AND(A37<>"",P37="Yes"),ROW(),"") | V37: =ROW() -> 37 | W37: =IF(O37="Completed",IF(COUNT($I$3:$I$596)>0,IF(I37<>"",I37,H37),""),"") | Z37: =IF(A37<>"",'Metrics planning and tracking'!$K$4,"") | AA37: =IF(A37<>"",'Metrics planning and tracking'!$K$5,"") | AB37: =IF(A37<>"",'Metrics planning and tracking'!$K$2,"") | AC37: =IF(A37<>"",'Metrics planning and tracking'!$K$3,"") | AD37: =IF(A37<>"",IF(AND(#REF!<>"",#REF!<>"",#REF!<>0),#REF!/#REF!*100,"NA"),"") | AE37: =IF(A37<>"",IF(AND(#REF!<>"",#REF!<>"",#REF!<>0),#REF!/#REF!*100,"NA"),"") | AF37: =IF($O37="Completed",IF(D37<>"",D37,IF(B37<>"",B37,"")),"") | AG37: =IF($O37="Completed",IF(E37<>"",E37,IF(C37<>"",C37,"")),"") | AH37: =IF(O37="Completed",IF(L37<>"",L37,IF(K37<>"",K37,"")),"") | AI37: UAT | AV37: =IF(A37<>"",A37 & "-" &#REF! & ROW(),"")
K38: =IF(AND(COUNTA(B38:C38)>1,COUNTA(F38:G38)>1,O38="Completed"),(G38-C38)/(C38-#REF!+1)%,"") | L38: =IF(AND(COUNT(D38:E38)>0,COUNTA(F38:G38)>1,O38="Completed"),(G38-AG38)/(AG38-#REF!+1)%,"") | M38: =IF(AND(T38<>"",T38<>0,R38<>"",R38<>0),(T38-R38)/R38%,IF(AND(H38<>"",H38<>0,OR(J38="",J38=0)),"Actual Effort reqd.","")) | N38: =IF(AND(T38<>"",T38<>0,S38<>"",S38<>0),(T38-S38)/S38%,IF(AND(I38<>"",I38<>0,OR(J38="",J38=0)),"Actual Effort reqd.","")) | R38: =IF(H38<>"",SUMIF(H$3:H38,"<>" & "",H$3:H38),"") | S38: {=IF(O38="Completed",SUMIF(W$3:W38,"<>" & "",W$3:W38),"")} | T38: {=IF(AND(J38<>"",O38="Completed"),SUM(IF(O$3:O38="Completed",J$3:J38,0)),"")} | U38: =IF(AND(A38<>"",P38="Yes"),ROW(),"") | V38: =ROW() -> 38 | W38: =IF(O38="Completed",IF(COUNT($I$3:$I$596)>0,IF(I38<>"",I38,H38),""),"") | Z38: =IF(A38<>"",'Metrics planning and tracking'!$K$4,"") | AA38: =IF(A38<>"",'Metrics planning and tracking'!$K$5,"") | AB38: =IF(A38<>"",'Metrics planning and tracking'!$K$2,"") | AC38: =IF(A38<>"",'Metrics planning and tracking'!$K$3,"") | AD38: =IF(A38<>"",IF(AND(#REF!<>"",#REF!<>"",#REF!<>0),#REF!/#REF!*100,"NA"),"") | AE38: =IF(A38<>"",IF(AND(#REF!<>"",#REF!<>"",#REF!<>0),#REF!/#REF!*100,"NA"),"") | AF38: =IF($O38="Completed",IF(D38<>"",D38,IF(B38<>"",B38,"")),"") | AG38: =IF($O38="Completed",IF(E38<>"",E38,IF(C38<>"",C38,"")),"") | AH38: =IF(O38="Completed",IF(L38<>"",L38,IF(K38<>"",K38,"")),"") | AV38: =IF(A38<>"",A38 & "-" &#REF! & ROW(),"")
K39: =IF(AND(COUNTA(B39:C39)>1,COUNTA(F39:G39)>1,O39="Completed"),(G39-C39)/(C39-#REF!+1)%,"") | L39: =IF(AND(COUNT(D39:E39)>0,COUNTA(F39:G39)>1,O39="Completed"),(G39-AG39)/(AG39-#REF!+1)%,"") | M39: =IF(AND(T39<>"",T39<>0,R39<>"",R39<>0),(T39-R39)/R39%,IF(AND(H39<>"",H39<>0,OR(J39="",J39=0)),"Actual Effort reqd.","")) | N39: =IF(AND(T39<>"",T39<>0,S39<>"",S39<>0),(T39-S39)/S39%,IF(AND(I39<>"",I39<>0,OR(J39="",J39=0)),"Actual Effort reqd.","")) | R39: =IF(H39<>"",SUMIF(H$3:H39,"<>" & "",H$3:H39),"") | S39: {=IF(O39="Completed",SUMIF(W$3:W39,"<>" & "",W$3:W39),"")} | T39: {=IF(AND(J39<>"",O39="Completed"),SUM(IF(O$3:O39="Completed",J$3:J39,0)),"")} | U39: =IF(AND(A39<>"",P39="Yes"),ROW(),"") | V39: =ROW() -> 39 | W39: =IF(O39="Completed",IF(COUNT($I$3:$I$596)>0,IF(I39<>"",I39,H39),""),"") | Z39: =IF(A39<>"",'Metrics planning and tracking'!$K$4,"") | AA39: =IF(A39<>"",'Metrics planning and tracking'!$K$5,"") | AB39: =IF(A39<>"",'Metrics planning and tracking'!$K$2,"") | AC39: =IF(A39<>"",'Metrics planning and tracking'!$K$3,"") | AD39: =IF(A39<>"",IF(AND(#REF!<>"",#REF!<>"",#REF!<>0),#REF!/#REF!*100,"NA"),"") | AE39: =IF(A39<>"",IF(AND(#REF!<>"",#REF!<>"",#REF!<>0),#REF!/#REF!*100,"NA"),"") | AF39: =IF($O39="Completed",IF(D39<>"",D39,IF(B39<>"",B39,"")),"") | AG39: =IF($O39="Completed",IF(E39<>"",E39,IF(C39<>"",C39,"")),"") | AH39: =IF(O39="Completed",IF(L39<>"",L39,IF(K39<>"",K39,"")),"") | AV39: =IF(A39<>"",A39 & "-" &#REF! & ROW(),"")
K40: =IF(AND(COUNTA(B40:C40)>1,COUNTA(F40:G40)>1,O40="Completed"),(G40-C40)/(C40-#REF!+1)%,"") | L40: =IF(AND(COUNT(D40:E40)>0,COUNTA(F40:G40)>1,O40="Completed"),(G40-AG40)/(AG40-#REF!+1)%,"") | M40: =IF(AND(T40<>"",T40<>0,R40<>"",R40<>0),(T40-R40)/R40%,IF(AND(H40<>"",H40<>0,OR(J40="",J40=0)),"Actual Effort reqd.","")) | N40: =IF(AND(T40<>"",T40<>0,S40<>"",S40<>0),(T40-S40)/S40%,IF(AND(I40<>"",I40<>0,OR(J40="",J40=0)),"Actual Effort reqd.","")) | R40: =IF(H40<>"",SUMIF(H$3:H40,"<>" & "",H$3:H40),"") | S40: {=IF(O40="Completed",SUMIF(W$3:W40,"<>" & "",W$3:W40),"")} | T40: {=IF(AND(J40<>"",O40="Completed"),SUM(IF(O$3:O40="Completed",J$3:J40,0)),"")} | U40: =IF(AND(A40<>"",P40="Yes"),ROW(),"") | V40: =ROW() -> 40 | W40: =IF(O40="Completed",IF(COUNT($I$3:$I$596)>0,IF(I40<>"",I40,H40),""),"") | Z40: =IF(A40<>"",'Metrics planning and tracking'!$K$4,"") | AA40: =IF(A40<>"",'Metrics planning and tracking'!$K$5,"") | AB40: =IF(A40<>"",'Metrics planning and tracking'!$K$2,"") | AC40: =IF(A40<>"",'Metrics planning and tracking'!$K$3,"") | AD40: =IF(A40<>"",IF(AND(#REF!<>"",#REF!<>"",#REF!<>0),#REF!/#REF!*100,"NA"),"") | AE40: =IF(A40<>"",IF(AND(#REF!<>"",#REF!<>"",#REF!<>0),#REF!/#REF!*100,"NA"),"") | AF40: =IF($O40="Completed",IF(D40<>"",D40,IF(B40<>"",B40,"")),"") | AG40: =IF($O40="Completed",IF(E40<>"",E40,IF(C40<>"",C40,"")),"") | AH40: =IF(O40="Completed",IF(L40<>"",L40,IF(K40<>"",K40,"")),"") | AV40: =IF(A40<>"",A40 & "-" &#REF! & ROW(),"")
K41: =IF(AND(COUNTA(B41:C41)>1,COUNTA(F41:G41)>1,O41="Completed"),(G41-C41)/(C41-#REF!+1)%,"") | L41: =IF(AND(COUNT(D41:E41)>0,COUNTA(F41:G41)>1,O41="Completed"),(G41-AG41)/(AG41-#REF!+1)%,"") | M41: =IF(AND(T41<>"",T41<>0,R41<>"",R41<>0),(T41-R41)/R41%,IF(AND(H41<>"",H41<>0,OR(J41="",J41=0)),"Actual Effort reqd.","")) | N41: =IF(AND(T41<>"",T41<>0,S41<>"",S41<>0),(T41-S41)/S41%,IF(AND(I41<>"",I41<>0,OR(J41="",J41=0)),"Actual Effort reqd.","")) | R41: =IF(H41<>"",SUMIF(H$3:H41,"<>" & "",H$3:H41),"") | S41: {=IF(O41="Completed",SUMIF(W$3:W41,"<>" & "",W$3:W41),"")} | T41: {=IF(AND(J41<>"",O41="Completed"),SUM(IF(O$3:O41="Completed",J$3:J41,0)),"")} | U41: =IF(AND(A41<>"",P41="Yes"),ROW(),"") | V41: =ROW() -> 41 | W41: =IF(O41="Completed",IF(COUNT($I$3:$I$596)>0,IF(I41<>"",I41,H41),""),"") | Z41: =IF(A41<>"",'Metrics planning and tracking'!$K$4,"") | AA41: =IF(A41<>"",'Metrics planning and tracking'!$K$5,"") | AB41: =IF(A41<>"",'Metrics planning and tracking'!$K$2,"") | AC41: =IF(A41<>"",'Metrics planning and tracking'!$K$3,"") | AD41: =IF(A41<>"",IF(AND(#REF!<>"",#REF!<>"",#REF!<>0),#REF!/#REF!*100,"NA"),"") | AE41: =IF(A41<>"",IF(AND(#REF!<>"",#REF!<>"",#REF!<>0),#REF!/#REF!*100,"NA"),"") | AF41: =IF($O41="Completed",IF(D41<>"",D41,IF(B41<>"",B41,"")),"") | AG41: =IF($O41="Completed",IF(E41<>"",E41,IF(C41<>"",C41,"")),"") | AH41: =IF(O41="Completed",IF(L41<>"",L41,IF(K41<>"",K41,"")),"") | AV41: =IF(A41<>"",A41 & "-" &#REF! & ROW(),"")
K42: =IF(AND(COUNTA(B42:C42)>1,COUNTA(F42:G42)>1,O42="Completed"),(G42-C42)/(C42-#REF!+1)%,"") | L42: =IF(AND(COUNT(D42:E42)>0,COUNTA(F42:G42)>1,O42="Completed"),(G42-AG42)/(AG42-#REF!+1)%,"") | M42: =IF(AND(T42<>"",T42<>0,R42<>"",R42<>0),(T42-R42)/R42%,IF(AND(H42<>"",H42<>0,OR(J42="",J42=0)),"Actual Effort reqd.","")) | N42: =IF(AND(T42<>"",T42<>0,S42<>"",S42<>0),(T42-S42)/S42%,IF(AND(I42<>"",I42<>0,OR(J42="",J42=0)),"Actual Effort reqd.","")) | R42: =IF(H42<>"",SUMIF(H$3:H42,"<>" & "",H$3:H42),"") | S42: {=IF(O42="Completed",SUMIF(W$3:W42,"<>" & "",W$3:W42),"")} | T42: {=IF(AND(J42<>"",O42="Completed"),SUM(IF(O$3:O42="Completed",J$3:J42,0)),"")} | U42: =IF(AND(A42<>"",P42="Yes"),ROW(),"") | V42: =ROW() -> 42 | W42: =IF(O42="Completed",IF(COUNT($I$3:$I$596)>0,IF(I42<>"",I42,H42),""),"") | Z42: =IF(A42<>"",'Metrics planning and tracking'!$K$4,"") | AA42: =IF(A42<>"",'Metrics planning and tracking'!$K$5,"") | AB42: =IF(A42<>"",'Metrics planning and tracking'!$K$2,"") | AC42: =IF(A42<>"",'Metrics planning and tracking'!$K$3,"") | AD42: =IF(A42<>"",IF(AND(#REF!<>"",#REF!<>"",#REF!<>0),#REF!/#REF!*100,"NA"),"") | AE42: =IF(A42<>"",IF(AND(#REF!<>"",#REF!<>"",#REF!<>0),#REF!/#REF!*100,"NA"),"") | AF42: =IF($O42="Completed",IF(D42<>"",D42,IF(B42<>"",B42,"")),"") | AG42: =IF($O42="Completed",IF(E42<>"",E42,IF(C42<>"",C42,"")),"") | AH42: =IF(O42="Completed",IF(L42<>"",L42,IF(K42<>"",K42,"")),"") | AV42: =IF(A42<>"",A42 & "-" &#REF! & ROW(),"")
K43: =IF(AND(COUNTA(B43:C43)>1,COUNTA(F43:G43)>1,O43="Completed"),(G43-C43)/(C43-#REF!+1)%,"") | L43: =IF(AND(COUNT(D43:E43)>0,COUNTA(F43:G43)>1,O43="Completed"),(G43-AG43)/(AG43-#REF!+1)%,"") | M43: =IF(AND(T43<>"",T43<>0,R43<>"",R43<>0),(T43-R43)/R43%,IF(AND(H43<>"",H43<>0,OR(J43="",J43=0)),"Actual Effort reqd.","")) | N43: =IF(AND(T43<>"",T43<>0,S43<>"",S43<>0),(T43-S43)/S43%,IF(AND(I43<>"",I43<>0,OR(J43="",J43=0)),"Actual Effort reqd.","")) | R43: =IF(H43<>"",SUMIF(H$3:H43,"<>" & "",H$3:H43),"") | S43: {=IF(O43="Completed",SUMIF(W$3:W43,"<>" & "",W$3:W43),"")} | T43: {=IF(AND(J43<>"",O43="Completed"),SUM(IF(O$3:O43="Completed",J$3:J43,0)),"")} | U43: =IF(AND(A43<>"",P43="Yes"),ROW(),"") | V43: =ROW() -> 43 | W43: =IF(O43="Completed",IF(COUNT($I$3:$I$596)>0,IF(I43<>"",I43,H43),""),"") | Z43: =IF(A43<>"",'Metrics planning and tracking'!$K$4,"") | AA43: =IF(A43<>"",'Metrics planning and tracking'!$K$5,"") | AB43: =IF(A43<>"",'Metrics planning and tracking'!$K$2,"") | AC43: =IF(A43<>"",'Metrics planning and tracking'!$K$3,"") | AD43: =IF(A43<>"",IF(AND(#REF!<>"",#REF!<>"",#REF!<>0),#REF!/#REF!*100,"NA"),"") | AE43: =IF(A43<>"",IF(AND(#REF!<>"",#REF!<>"",#REF!<>0),#REF!/#REF!*100,"NA"),"") | AF43: =IF($O43="Completed",IF(D43<>"",D43,IF(B43<>"",B43,"")),"") | AG43: =IF($O43="Completed",IF(E43<>"",E43,IF(C43<>"",C43,"")),"") | AH43: =IF(O43="Completed",IF(L43<>"",L43,IF(K43<>"",K43,"")),"") | AV43: =IF(A43<>"",A43 & "-" &#REF! & ROW(),"")
K44: =IF(AND(COUNTA(B44:C44)>1,COUNTA(F44:G44)>1,O44="Completed"),(G44-C44)/(C44-#REF!+1)%,"") | L44: =IF(AND(COUNT(D44:E44)>0,COUNTA(F44:G44)>1,O44="Completed"),(G44-AG44)/(AG44-#REF!+1)%,"") | M44: =IF(AND(T44<>"",T44<>0,R44<>"",R44<>0),(T44-R44)/R44%,IF(AND(H44<>"",H44<>0,OR(J44="",J44=0)),"Actual Effort reqd.","")) | N44: =IF(AND(T44<>"",T44<>0,S44<>"",S44<>0),(T44-S44)/S44%,IF(AND(I44<>"",I44<>0,OR(J44="",J44=0)),"Actual Effort reqd.","")) | R44: =IF(H44<>"",SUMIF(H$3:H44,"<>" & "",H$3:H44),"") | S44: {=IF(O44="Completed",SUMIF(W$3:W44,"<>" & "",W$3:W44),"")} | T44: {=IF(AND(J44<>"",O44="Completed"),SUM(IF(O$3:O44="Completed",J$3:J44,0)),"")} | U44: =IF(AND(A44<>"",P44="Yes"),ROW(),"") | V44: =ROW() -> 44 | W44: =IF(O44="Completed",IF(COUNT($I$3:$I$596)>0,IF(I44<>"",I44,H44),""),"") | Z44: =IF(A44<>"",'Metrics planning and tracking'!$K$4,"") | AA44: =IF(A44<>"",'Metrics planning and tracking'!$K$5,"") | AB44: =IF(A44<>"",'Metrics planning and tracking'!$K$2,"") | AC44: =IF(A44<>"",'Metrics planning and tracking'!$K$3,"") | AD44: =IF(A44<>"",IF(AND(#REF!<>"",#REF!<>"",#REF!<>0),#REF!/#REF!*100,"NA"),"") | AE44: =IF(A44<>"",IF(AND(#REF!<>"",#REF!<>"",#REF!<>0),#REF!/#REF!*100,"NA"),"") | AF44: =IF($O44="Completed",IF(D44<>"",D44,IF(B44<>"",B44,"")),"") | AG44: =IF($O44="Completed",IF(E44<>"",E44,IF(C44<>"",C44,"")),"") | AH44: =IF(O44="Completed",IF(L44<>"",L44,IF(K44<>"",K44,"")),"") | AV44: =IF(A44<>"",A44 & "-" &#REF! & ROW(),"")
K45: =IF(AND(COUNTA(B45:C45)>1,COUNTA(F45:G45)>1,O45="Completed"),(G45-C45)/(C45-#REF!+1)%,"") | L45: =IF(AND(COUNT(D45:E45)>0,COUNTA(F45:G45)>1,O45="Completed"),(G45-AG45)/(AG45-#REF!+1)%,"") | M45: =IF(AND(T45<>"",T45<>0,R45<>"",R45<>0),(T45-R45)/R45%,IF(AND(H45<>"",H45<>0,OR(J45="",J45=0)),"Actual Effort reqd.","")) | N45: =IF(AND(T45<>"",T45<>0,S45<>"",S45<>0),(T45-S45)/S45%,IF(AND(I45<>"",I45<>0,OR(J45="",J45=0)),"Actual Effort reqd.","")) | R45: =IF(H45<>"",SUMIF(H$3:H45,"<>" & "",H$3:H45),"") | S45: {=IF(O45="Completed",SUMIF(W$3:W45,"<>" & "",W$3:W45),"")} | T45: {=IF(AND(J45<>"",O45="Completed"),SUM(IF(O$3:O45="Completed",J$3:J45,0)),"")} | U45: =IF(AND(A45<>"",P45="Yes"),ROW(),"") | V45: =ROW() -> 45 | W45: =IF(O45="Completed",IF(COUNT($I$3:$I$596)>0,IF(I45<>"",I45,H45),""),"") | Z45: =IF(A45<>"",'Metrics planning and tracking'!$K$4,"") | AA45: =IF(A45<>"",'Metrics planning and tracking'!$K$5,"") | AB45: =IF(A45<>"",'Metrics planning and tracking'!$K$2,"") | AC45: =IF(A45<>"",'Metrics planning and tracking'!$K$3,"") | AD45: =IF(A45<>"",IF(AND(#REF!<>"",#REF!<>"",#REF!<>0),#REF!/#REF!*100,"NA"),"") | AE45: =IF(A45<>"",IF(AND(#REF!<>"",#REF!<>"",#REF!<>0),#REF!/#REF!*100,"NA"),"") | AF45: =IF($O45="Completed",IF(D45<>"",D45,IF(B45<>"",B45,"")),"") | AG45: =IF($O45="Completed",IF(E45<>"",E45,IF(C45<>"",C45,"")),"") | AH45: =IF(O45="Completed",IF(L45<>"",L45,IF(K45<>"",K45,"")),"") | AV45: =IF(A45<>"",A45 & "-" &#REF! & ROW(),"")
K46: =IF(AND(COUNTA(B46:C46)>1,COUNTA(F46:G46)>1,O46="Completed"),(G46-C46)/(C46-#REF!+1)%,"") | L46: =IF(AND(COUNT(D46:E46)>0,COUNTA(F46:G46)>1,O46="Completed"),(G46-AG46)/(AG46-#REF!+1)%,"") | M46: =IF(AND(T46<>"",T46<>0,R46<>"",R46<>0),(T46-R46)/R46%,IF(AND(H46<>"",H46<>0,OR(J46="",J46=0)),"Actual Effort reqd.","")) | N46: =IF(AND(T46<>"",T46<>0,S46<>"",S46<>0),(T46-S46)/S46%,IF(AND(I46<>"",I46<>0,OR(J46="",J46=0)),"Actual Effort reqd.","")) | R46: =IF(H46<>"",SUMIF(H$3:H46,"<>" & "",H$3:H46),"") | S46: {=IF(O46="Completed",SUMIF(W$3:W46,"<>" & "",W$3:W46),"")} | T46: {=IF(AND(J46<>"",O46="Completed"),SUM(IF(O$3:O46="Completed",J$3:J46,0)),"")} | U46: =IF(AND(A46<>"",P46="Yes"),ROW(),"") | V46: =ROW() -> 46 | W46: =IF(O46="Completed",IF(COUNT($I$3:$I$596)>0,IF(I46<>"",I46,H46),""),"") | Z46: =IF(A46<>"",'Metrics planning and tracking'!$K$4,"") | AA46: =IF(A46<>"",'Metrics planning and tracking'!$K$5,"") | AB46: =IF(A46<>"",'Metrics planning and tracking'!$K$2,"") | AC46: =IF(A46<>"",'Metrics planning and tracking'!$K$3,"") | AD46: =IF(A46<>"",IF(AND(#REF!<>"",#REF!<>"",#REF!<>0),#REF!/#REF!*100,"NA"),"") | AE46: =IF(A46<>"",IF(AND(#REF!<>"",#REF!<>"",#REF!<>0),#REF!/#REF!*100,"NA"),"") | AF46: =IF($O46="Completed",IF(D46<>"",D46,IF(B46<>"",B46,"")),"") | AG46: =IF($O46="Completed",IF(E46<>"",E46,IF(C46<>"",C46,"")),"") | AH46: =IF(O46="Completed",IF(L46<>"",L46,IF(K46<>"",K46,"")),"") | AV46: =IF(A46<>"",A46 & "-" &#REF! & ROW(),"")
K47: =IF(AND(COUNTA(B47:C47)>1,COUNTA(F47:G47)>1,O47="Completed"),(G47-C47)/(C47-#REF!+1)%,"") | L47: =IF(AND(COUNT(D47:E47)>0,COUNTA(F47:G47)>1,O47="Completed"),(G47-AG47)/(AG47-#REF!+1)%,"") | M47: =IF(AND(T47<>"",T47<>0,R47<>"",R47<>0),(T47-R47)/R47%,IF(AND(H47<>"",H47<>0,OR(J47="",J47=0)),"Actual Effort reqd.","")) | N47: =IF(AND(T47<>"",T47<>0,S47<>"",S47<>0),(T47-S47)/S47%,IF(AND(I47<>"",I47<>0,OR(J47="",J47=0)),"Actual Effort reqd.","")) | R47: =IF(H47<>"",SUMIF(H$3:H47,"<>" & "",H$3:H47),"") | S47: {=IF(O47="Completed",SUMIF(W$3:W47,"<>" & "",W$3:W47),"")} | T47: {=IF(AND(J47<>"",O47="Completed"),SUM(IF(O$3:O47="Completed",J$3:J47,0)),"")} | U47: =IF(AND(A47<>"",P47="Yes"),ROW(),"") | V47: =ROW() -> 47 | W47: =IF(O47="Completed",IF(COUNT($I$3:$I$596)>0,IF(I47<>"",I47,H47),""),"") | Z47: =IF(A47<>"",'Metrics planning and tracking'!$K$4,"") | AA47: =IF(A47<>"",'Metrics planning and tracking'!$K$5,"") | AB47: =IF(A47<>"",'Metrics planning and tracking'!$K$2,"") | AC47: =IF(A47<>"",'Metrics planning and tracking'!$K$3,"") | AD47: =IF(A47<>"",IF(AND(#REF!<>"",#REF!<>"",#REF!<>0),#REF!/#REF!*100,"NA"),"") | AE47: =IF(A47<>"",IF(AND(#REF!<>"",#REF!<>"",#REF!<>0),#REF!/#REF!*100,"NA"),"") | AF47: =IF($O47="Completed",IF(D47<>"",D47,IF(B47<>"",B47,"")),"") | AG47: =IF($O47="Completed",IF(E47<>"",E47,IF(C47<>"",C47,"")),"") | AH47: =IF(O47="Completed",IF(L47<>"",L47,IF(K47<>"",K47,"")),"") | AV47: =IF(A47<>"",A47 & "-" &#REF! & ROW(),"")
K48: =IF(AND(COUNTA(B48:C48)>1,COUNTA(F48:G48)>1,O48="Completed"),(G48-C48)/(C48-#REF!+1)%,"") | L48: =IF(AND(COUNT(D48:E48)>0,COUNTA(F48:G48)>1,O48="Completed"),(G48-AG48)/(AG48-#REF!+1)%,"") | M48: =IF(AND(T48<>"",T48<>0,R48<>"",R48<>0),(T48-R48)/R48%,IF(AND(H48<>"",H48<>0,OR(J48="",J48=0)),"Actual Effort reqd.","")) | N48: =IF(AND(T48<>"",T48<>0,S48<>"",S48<>0),(T48-S48)/S48%,IF(AND(I48<>"",I48<>0,OR(J48="",J48=0)),"Actual Effort reqd.","")) | R48: =IF(H48<>"",SUMIF(H$3:H48,"<>" & "",H$3:H48),"") | S48: {=IF(O48="Completed",SUMIF(W$3:W48,"<>" & "",W$3:W48),"")} | T48: {=IF(AND(J48<>"",O48="Completed"),SUM(IF(O$3:O48="Completed",J$3:J48,0)),"")} | U48: =IF(AND(A48<>"",P48="Yes"),ROW(),"") | V48: =ROW() -> 48 | W48: =IF(O48="Completed",IF(COUNT($I$3:$I$596)>0,IF(I48<>"",I48,H48),""),"") | Z48: =IF(A48<>"",'Metrics planning and tracking'!$K$4,"") | AA48: =IF(A48<>"",'Metrics planning and tracking'!$K$5,"") | AB48: =IF(A48<>"",'Metrics planning and tracking'!$K$2,"") | AC48: =IF(A48<>"",'Metrics planning and tracking'!$K$3,"") | AD48: =IF(A48<>"",IF(AND(#REF!<>"",#REF!<>"",#REF!<>0),#REF!/#REF!*100,"NA"),"") | AE48: =IF(A48<>"",IF(AND(#REF!<>"",#REF!<>"",#REF!<>0),#REF!/#REF!*100,"NA"),"") | AF48: =IF($O48="Completed",IF(D48<>"",D48,IF(B48<>"",B48,"")),"") | AG48: =IF($O48="Completed",IF(E48<>"",E48,IF(C48<>"",C48,"")),"") | AH48: =IF(O48="Completed",IF(L48<>"",L48,IF(K48<>"",K48,"")),"") | AV48: =IF(A48<>"",A48 & "-" &#REF! & ROW(),"")
K49: =IF(AND(COUNTA(B49:C49)>1,COUNTA(F49:G49)>1,O49="Completed"),(G49-C49)/(C49-#REF!+1)%,"") | L49: =IF(AND(COUNT(D49:E49)>0,COUNTA(F49:G49)>1,O49="Completed"),(G49-AG49)/(AG49-#REF!+1)%,"") | M49: =IF(AND(T49<>"",T49<>0,R49<>"",R49<>0),(T49-R49)/R49%,IF(AND(H49<>"",H49<>0,OR(J49="",J49=0)),"Actual Effort reqd.","")) | N49: =IF(AND(T49<>"",T49<>0,S49<>"",S49<>0),(T49-S49)/S49%,IF(AND(I49<>"",I49<>0,OR(J49="",J49=0)),"Actual Effort reqd.","")) | R49: =IF(H49<>"",SUMIF(H$3:H49,"<>" & "",H$3:H49),"") | S49: {=IF(O49="Completed",SUMIF(W$3:W49,"<>" & "",W$3:W49),"")} | T49: {=IF(AND(J49<>"",O49="Completed"),SUM(IF(O$3:O49="Completed",J$3:J49,0)),"")} | U49: =IF(AND(A49<>"",P49="Yes"),ROW(),"") | V49: =ROW() -> 49 | W49: =IF(O49="Completed",IF(COUNT($I$3:$I$596)>0,IF(I49<>"",I49,H49),""),"") | Z49: =IF(A49<>"",'Metrics planning and tracking'!$K$4,"") | AA49: =IF(A49<>"",'Metrics planning and tracking'!$K$5,"") | AB49: =IF(A49<>"",'Metrics planning and tracking'!$K$2,"") | AC49: =IF(A49<>"",'Metrics planning and tracking'!$K$3,"") | AD49: =IF(A49<>"",IF(AND(#REF!<>"",#REF!<>"",#REF!<>0),#REF!/#REF!*100,"NA"),"") | AE49: =IF(A49<>"",IF(AND(#REF!<>"",#REF!<>"",#REF!<>0),#REF!/#REF!*100,"NA"),"") | AF49: =IF($O49="Completed",IF(D49<>"",D49,IF(B49<>"",B49,"")),"") | AG49: =IF($O49="Completed",IF(E49<>"",E49,IF(C49<>"",C49,"")),"") | AH49: =IF(O49="Completed",IF(L49<>"",L49,IF(K49<>"",K49,"")),"") | AV49: =IF(A49<>"",A49 & "-" &#REF! & ROW(),"")
... K496: =IF(AND(COUNTA(B496:C496)>1,COUNTA(F496:G496)>1,O496="Completed"),(G496-C496)/(C496-#REF!+1)%,"") | L496: =IF(AND(COUNT(D496:E496)>0,COUNTA(F496:G496)>1,O496="Completed"),(G496-AG496)/(AG496-#REF!+1)%,"") | M496: =IF(AND(T496<>"",T496<>0,R496<>"",R496<>0),(T496-R496)/R496%,IF(AND(H496<>"",H496<>0,OR(J496="",J496=0)),"Actual Effort reqd.","")) | N496: =IF(AND(T496<>"",T496<>0,S496<>"",S496<>0),(T496-S496)/S496%,IF(AND(I496<>"",I496<>0,OR(J496="",J496=0)),"Actual Effort reqd.","")) | R496: =IF(H496<>"",SUMIF(H$3:H496,"<>" & "",H$3:H496),"") | S496: {=IF(O496="Completed",SUMIF(W$3:W496,"<>" & "",W$3:W496),"")} | T496: {=IF(AND(J496<>"",O496="Completed"),SUM(IF(O$3:O496="Completed",J$3:J496,0)),"")} | U496: =IF(AND(A496<>"",P496="Yes"),ROW(),"") | V496: =ROW() -> 496 | W496: =IF(O496="Completed",IF(COUNT($I$3:$I$596)>0,IF(I496<>"",I496,H496),""),"") | Z496: =IF(A496<>"",'Metrics planning and tracking'!$K$4,"") | AA496: =IF(A496<>"",'Metrics planning and tracking'!$K$5,"") | AB496: =IF(A496<>"",'Metrics planning and tracking'!$K$2,"") | AC496: =IF(A496<>"",'Metrics planning and tracking'!$K$3,"") | AD496: =IF(A496<>"",IF(AND(#REF!<>"",#REF!<>"",#REF!<>0),#REF!/#REF!*100,"NA"),"") | AE496: =IF(A496<>"",IF(AND(#REF!<>"",#REF!<>"",#REF!<>0),#REF!/#REF!*100,"NA"),"") | AF496: =IF($O496="Completed",IF(D496<>"",D496,IF(B496<>"",B496,"")),"") | AG496: =IF($O496="Completed",IF(E496<>"",E496,IF(C496<>"",C496,"")),"") | AH496: =IF(O496="Completed",IF(L496<>"",L496,IF(K496<>"",K496,"")),"") | AV496: =IF(A496<>"",A496 & "-" &#REF! & ROW(),"")

Sheet Control panel
A3: Applicable project phases | B3: Size measurement unit for phases | G3: Phase List | H3: Size Measure | I3: Equivalent Standard SDLC Phase
A4: Analysis and design | B4: Hours | C4: =ROW() -> 4 | D4: =IF(COUNTIF(B$4:B4,B4)=1,ROW(),"") -> 4 | E4: =IF(COUNTIF(A$4:A4,A4)=1,ROW(),"") -> 4 | G4: Analysis and design | H4: Components | I4: Planning | K4: Planning
A5: Coding and unit testing | B5: Hours | C5: =ROW() -> 5 | D5: =IF(COUNTIF(B$4:B5,B5)=1,ROW(),"") | E5: =IF(COUNTIF(A$4:A5,A5)=1,ROW(),"") -> 5 | G5: Coding and unit testing | H5: Feature points | I5: Package & release | K5: Requirement Specification
A6: System integration testing | B6: Hours | C6: =ROW() -> 6 | D6: =IF(COUNTIF(B$4:B6,B6)=1,ROW(),"") | E6: =IF(COUNTIF(A$4:A6,A6)=1,ROW(),"") -> 6 | G6: System integration testing | H6: Func. Modules | I6: Construction | K6: High Level design
A7: User acceptance testing | B7: Hours | C7: =ROW() -> 7 | D7: =IF(COUNTIF(B$4:B7,B7)=1,ROW(),"") | E7: =IF(COUNTIF(A$4:A7,A7)=1,ROW(),"") -> 7 | G7: User acceptance testing | H7: Function points | I7: Construction | K7: Low Level design
A8: Production Deployment | B8: Hours | C8: =ROW() -> 8 | D8: =IF(COUNTIF(B$4:B8,B8)=1,ROW(),"") | E8: =IF(COUNTIF(A$4:A8,A8)=1,ROW(),"") -> 8 | G8: Production Deployment | H8: Icons | I8: High Level design | K8: Construction
A9: Post production support | B9: Hours | C9: =ROW() -> 9 | D9: =IF(COUNTIF(B$4:B9,B9)=1,ROW(),"") | E9: =IF(COUNTIF(A$4:A9,A9)=1,ROW(),"") -> 9 | G9: Post production support | H9: NCSLOC | I9: Planning | K9: Testing
C10: =ROW() -> 10 | D10: =IF(COUNTIF(B$4:B10,B10)=1,ROW(),"") | E10: =IF(COUNTIF(A$4:A10,A10)=1,ROW(),"") | H10: Hours | I10: Testing | K10: Package & release
C11: =ROW() -> 11 | D11: =IF(COUNTIF(B$4:B11,B11)=1,ROW(),"") | E11: =IF(COUNTIF(A$4:A11,A11)=1,ROW(),"") | H11: Paths | I11: Package & release | K11: Acceptance
C12: =ROW() -> 12 | D12: =IF(COUNTIF(B$4:B12,B12)=1,ROW(),"") | E12: =IF(COUNTIF(A$4:A12,A12)=1,ROW(),"") | H12: Screens | I12: Testing
C13: =ROW() -> 13 | D13: =IF(COUNTIF(B$4:B13,B13)=1,ROW(),"") | E13: =IF(COUNTIF(A$4:A13,A13)=1,ROW(),"") | H13: System function points | I13: Testing
C14: =ROW() -> 14 | D14: =IF(COUNTIF(B$4:B14,B14)=1,ROW(),"") | E14: =IF(COUNTIF(A$4:A14,A14)=1,ROW(),"") | H14: Test cases
C15: =ROW() -> 15 | D15: =IF(COUNTIF(B$4:B15,B15)=1,ROW(),"") | E15: =IF(COUNTIF(A$4:A15,A15)=1,ROW(),"") | H15: Use cases
C16: =ROW() -> 16 | D16: =IF(COUNTIF(B$4:B16,B16)=1,ROW(),"") | E16: =IF(COUNTIF(A$4:A16,A16)=1,ROW(),"") | H16: Others
C17: =ROW() -> 17 | D17: =IF(COUNTIF(B$4:B17,B17)=1,ROW(),"") | E17: =IF(COUNTIF(A$4:A17,A17)=1,ROW(),"")
C18: =ROW() -> 18 | D18: =IF(COUNTIF(B$4:B18,B18)=1,ROW(),"") | E18: =IF(COUNTIF(A$4:A18,A18)=1,ROW(),"")
C19: =ROW() -> 19 | D19: =IF(COUNTIF(B$4:B19,B19)=1,ROW(),"") | E19: =IF(COUNTIF(A$4:A19,A19)=1,ROW(),"")
C20: =ROW() -> 20 | D20: =IF(COUNTIF(B$4:B20,B20)=1,ROW(),"") | E20: =IF(COUNTIF(A$4:A20,A20)=1,ROW(),"")
C21: =ROW() -> 21 | D21: =IF(COUNTIF(B$4:B21,B21)=1,ROW(),"") | E21: =IF(COUNTIF(A$4:A21,A21)=1,ROW(),"")
C22: =ROW() -> 22 | D22: =IF(COUNTIF(B$4:B22,B22)=1,ROW(),"") | E22: =IF(COUNTIF(A$4:A22,A22)=1,ROW(),"")
C23: =ROW() -> 23 | D23: =IF(COUNTIF(B$4:B23,B23)=1,ROW(),"") | E23: =IF(COUNTIF(A$4:A23,A23)=1,ROW(),"")
C24: =ROW() -> 24 | D24: =IF(COUNTIF(B$4:B24,B24)=1,ROW(),"") | E24: =IF(COUNTIF(A$4:A24,A24)=1,ROW(),"")
C25: =ROW() -> 25 | D25: =IF(COUNTIF(B$4:B25,B25)=1,ROW(),"") | E25: =IF(COUNTIF(A$4:A25,A25)=1,ROW(),"")
C26: =ROW() -> 26 | D26: =IF(COUNTIF(B$4:B26,B26)=1,ROW(),"") | E26: =IF(COUNTIF(A$4:A26,A26)=1,ROW(),"")
C27: =ROW() -> 27 | D27: =IF(COUNTIF(B$4:B27,B27)=1,ROW(),"") | E27: =IF(COUNTIF(A$4:A27,A27)=1,ROW(),"")
C28: =ROW() -> 28 | D28: =IF(COUNTIF(B$4:B28,B28)=1,ROW(),"") | E28: =IF(COUNTIF(A$4:A28,A28)=1,ROW(),"")
... C37: =ROW() -> 37 | D37: =IF(COUNTIF(B$4:B37,B37)=1,ROW(),"") | E37: =IF(COUNTIF(A$4:A37,A37)=1,ROW(),"")

Sheet Sheet2

Sheet Quality of Work
A1: DFC | D1: SV
A2: Delivery accepted without any comments | B2: 35 | D2: SV >=25% | E2: 0
A3: Delivery accepted with minor comments | B3: 30 | D3: SV >=20% | E3: 5
A4: Delivery accepted with 1-2 major comments | B4: 25 | D4: SV >=15% | E4: 10
A5: Delivery accepted with many major comments | B5: 15 | D5: SV >=10% | E5: 15
A6: Delivery not accepted | B6: 0 | D6: SV>=5% | E6: 20
A7: Not applicable | B7: NA | D7: SV<5% | E7: 25
D8: Not Applicable | E8: NA
A17: Delivery Quality | N17: 35 | O17: 25
A18: Batch / Activity / Work Product | B18: Delivery details | C18: Plan Delivery date | D18: Actual Delivery date | E18: Feedback from customer | F18: Delivery Schedule Variation | G18: Delivery quality index | H18: Customer feedback communication reference | N18: DFC | O18: SV | P18: Delivery Feedback | Q18: SV-Range | R18: SV - Bin
A19: =IF(COUNT('Size, Schedule and Effort'!U:U)>=ROW()-18,INDIRECT("'Size, Schedule and Effort'!$C$" & SMALL('Size, Schedule and Effort'!U:U,ROW()-18)),"") -> 0 | C19: =IF(M19<>"",IF(SUMIF('Size, Schedule and Effort'!$AV$3:$AV$496,M19,'Size, Schedule and Effort'!$AG$3:$AG$496)<>0,SUMIF('Size, Schedule and Effort'!$AV$3:$AV$496,M19,'Size, Schedule and Effort'!$AG$3:$AG$496),"NA"),"") -> NA | D19: =IF(M19<>"",IF(SUMIF('Size, Schedule and Effort'!$AV$3:$AV$496,M19,'Size, Schedule and Effort'!$G$3:$G$496)<>0,SUMIF('Size, Schedule and Effort'!$AV$3:$AV$496,M19,'Size, Schedule and Effort'!$G$3:$G$496),"NA"),"") -> NA | E19: Delivery accepted with many major comments | F19: =IF(R19<>"",CHOOSE(R19,D$7,D$6,D$5,D$4,D$3,D$2),"") | G19: =IF(A19<>"",IF(P19<>"",P19,""),"") | M19: =IF(COUNT('Size, Schedule and Effort'!U:U)>=ROW()-18,INDIRECT("'Size, Schedule and Effort'!$BH$" & SMALL('Size, Schedule and Effort'!U:U,ROW()-18)),"") -> 0 | N19: =IF($E19<>"",VLOOKUP($E19,$A$1:$B$7,2,0),"") -> 15 | O19: =IF($F19<>"",VLOOKUP($F19,$D$1:$E$8,2,0),"") | P19: =IF(COUNTA(B19,E19)+COUNT(D19)>=3,IF(COUNT($N19:$O19)<>0,SUM($N19:$O19)/(SUM($N$17:$O$17)-IF($N19="NA",$N$17,0)-IF($O19="NA",$O$17,0))*100,"NA"),"") | Q19: =IF(AND(A19<>"",D19<>"",D19<>"NA"),VLOOKUP(A19,'Size, Schedule and Effort'!$B$3:$AH$496,44,0),"") | R19: =IF(Q19<>"",IF(Q19<5,1,IF(Q19<10,2,IF(Q19<15,3,IF(Q19<20,4,IF(Q19<25,5,IF(Q19>=25,6,7)))))),"")
A20: =IF(COUNT('Size, Schedule and Effort'!U:U)>=ROW()-18,INDIRECT("'Size, Schedule and Effort'!$C$" & SMALL('Size, Schedule and Effort'!U:U,ROW()-18)),"") -> 0 | C20: =IF(M20<>"",IF(SUMIF('Size, Schedule and Effort'!$AV$3:$AV$496,M20,'Size, Schedule and Effort'!$AG$3:$AG$496)<>0,SUMIF('Size, Schedule and Effort'!$AV$3:$AV$496,M20,'Size, Schedule and Effort'!$AG$3:$AG$496),"NA"),"") -> NA | D20: =IF(M20<>"",IF(SUMIF('Size, Schedule and Effort'!$AV$3:$AV$496,M20,'Size, Schedule and Effort'!$G$3:$G$496)<>0,SUMIF('Size, Schedule and Effort'!$AV$3:$AV$496,M20,'Size, Schedule and Effort'!$G$3:$G$496),"NA"),"") -> NA | E20: Delivery accepted without any comments | F20: =IF(R20<>"",CHOOSE(R20,D$7,D$6,D$5,D$4,D$3,D$2),"") | G20: =IF(A20<>"",IF(P20<>"",P20,""),"") | M20: =IF(COUNT('Size, Schedule and Effort'!U:U)>=ROW()-18,INDIRECT("'Size, Schedule and Effort'!$BH$" & SMALL('Size, Schedule and Effort'!U:U,ROW()-18)),"") -> 0 | N20: =IF($E20<>"",VLOOKUP($E20,$A$1:$B$7,2,0),"") -> 35 | O20: =IF($F20<>"",VLOOKUP($F20,$D$1:$E$8,2,0),"") | P20: =IF(COUNTA(B20,E20)+COUNT(D20)>=3,IF(COUNT($N20:$O20)<>0,SUM($N20:$O20)/(SUM($N$17:$O$17)-IF($N20="NA",$N$17,0)-IF($O20="NA",$O$17,0))*100,"NA"),"") | Q20: =IF(AND(A20<>"",D20<>"",D20<>"NA"),VLOOKUP(A20,'Size, Schedule and Effort'!$B$3:$AH$496,44,0),"") | R20: =IF(Q20<>"",IF(Q20<5,1,IF(Q20<10,2,IF(Q20<15,3,IF(Q20<20,4,IF(Q20<25,5,IF(Q20>=25,6,7)))))),"")
A21: =IF(COUNT('Size, Schedule and Effort'!U:U)>=ROW()-18,INDIRECT("'Size, Schedule and Effort'!$C$" & SMALL('Size, Schedule and Effort'!U:U,ROW()-18)),"") -> 0 | C21: =IF(M21<>"",IF(SUMIF('Size, Schedule and Effort'!$AV$3:$AV$496,M21,'Size, Schedule and Effort'!$AG$3:$AG$496)<>0,SUMIF('Size, Schedule and Effort'!$AV$3:$AV$496,M21,'Size, Schedule and Effort'!$AG$3:$AG$496),"NA"),"") -> NA | D21: =IF(M21<>"",IF(SUMIF('Size, Schedule and Effort'!$AV$3:$AV$496,M21,'Size, Schedule and Effort'!$G$3:$G$496)<>0,SUMIF('Size, Schedule and Effort'!$AV$3:$AV$496,M21,'Size, Schedule and Effort'!$G$3:$G$496),"NA"),"") -> NA | E21: Delivery accepted without any comments | F21: =IF(R21<>"",CHOOSE(R21,D$7,D$6,D$5,D$4,D$3,D$2),"") | G21: =IF(A21<>"",IF(P21<>"",P21,""),"") | M21: =IF(COUNT('Size, Schedule and Effort'!U:U)>=ROW()-18,INDIRECT("'Size, Schedule and Effort'!$BH$" & SMALL('Size, Schedule and Effort'!U:U,ROW()-18)),"") -> 0 | N21: =IF($E21<>"",VLOOKUP($E21,$A$1:$B$7,2,0),"") -> 35 | O21: =IF($F21<>"",VLOOKUP($F21,$D$1:$E$8,2,0),"") | P21: =IF(COUNTA(B21,E21)+COUNT(D21)>=3,IF(COUNT($N21:$O21)<>0,SUM($N21:$O21)/(SUM($N$17:$O$17)-IF($N21="NA",$N$17,0)-IF($O21="NA",$O$17,0))*100,"NA"),"") | Q21: =IF(AND(A21<>"",D21<>"",D21<>"NA"),VLOOKUP(A21,'Size, Schedule and Effort'!$B$3:$AH$496,44,0),"") | R21: =IF(Q21<>"",IF(Q21<5,1,IF(Q21<10,2,IF(Q21<15,3,IF(Q21<20,4,IF(Q21<25,5,IF(Q21>=25,6,7)))))),"")
A22: =IF(COUNT('Size, Schedule and Effort'!U:U)>=ROW()-18,INDIRECT("'Size, Schedule and Effort'!$C$" & SMALL('Size, Schedule and Effort'!U:U,ROW()-18)),"") -> 0 | C22: =IF(M22<>"",IF(SUMIF('Size, Schedule and Effort'!$AV$3:$AV$496,M22,'Size, Schedule and Effort'!$AG$3:$AG$496)<>0,SUMIF('Size, Schedule and Effort'!$AV$3:$AV$496,M22,'Size, Schedule and Effort'!$AG$3:$AG$496),"NA"),"") -> NA | D22: =IF(M22<>"",IF(SUMIF('Size, Schedule and Effort'!$AV$3:$AV$496,M22,'Size, Schedule and Effort'!$G$3:$G$496)<>0,SUMIF('Size, Schedule and Effort'!$AV$3:$AV$496,M22,'Size, Schedule and Effort'!$G$3:$G$496),"NA"),"") -> NA | F22: =IF(R22<>"",CHOOSE(R22,D$7,D$6,D$5,D$4,D$3,D$2),"") | G22: =IF(A22<>"",IF(P22<>"",P22,""),"") | M22: =IF(COUNT('Size, Schedule and Effort'!U:U)>=ROW()-18,INDIRECT("'Size, Schedule and Effort'!$BH$" & SMALL('Size, Schedule and Effort'!U:U,ROW()-18)),"") -> 0 | N22: =IF($E22<>"",VLOOKUP($E22,$A$1:$B$7,2,0),"") | O22: =IF($F22<>"",VLOOKUP($F22,$D$1:$E$8,2,0),"") | P22: =IF(COUNTA(B22,E22)+COUNT(D22)>=3,IF(COUNT($N22:$O22)<>0,SUM($N22:$O22)/(SUM($N$17:$O$17)-IF($N22="NA",$N$17,0)-IF($O22="NA",$O$17,0))*100,"NA"),"") | Q22: =IF(AND(A22<>"",D22<>"",D22<>"NA"),VLOOKUP(A22,'Size, Schedule and Effort'!$B$3:$AH$496,44,0),"") | R22: =IF(Q22<>"",IF(Q22<5,1,IF(Q22<10,2,IF(Q22<15,3,IF(Q22<20,4,IF(Q22<25,5,IF(Q22>=25,6,7)))))),"")
A23: =IF(COUNT('Size, Schedule and Effort'!U:U)>=ROW()-18,INDIRECT("'Size, Schedule and Effort'!$C$" & SMALL('Size, Schedule and Effort'!U:U,ROW()-18)),"") | C23: =IF(M23<>"",IF(SUMIF('Size, Schedule and Effort'!$AV$3:$AV$496,M23,'Size, Schedule and Effort'!$AG$3:$AG$496)<>0,SUMIF('Size, Schedule and Effort'!$AV$3:$AV$496,M23,'Size, Schedule and Effort'!$AG$3:$AG$496),"NA"),"") | D23: =IF(M23<>"",IF(SUMIF('Size, Schedule and Effort'!$AV$3:$AV$496,M23,'Size, Schedule and Effort'!$G$3:$G$496)<>0,SUMIF('Size, Schedule and Effort'!$AV$3:$AV$496,M23,'Size, Schedule and Effort'!$G$3:$G$496),"NA"),"") | E23: Not applicable | F23: =IF(R23<>"",CHOOSE(R23,D$7,D$6,D$5,D$4,D$3,D$2),"") | G23: =IF(A23<>"",IF(P23<>"",P23,""),"") | M23: =IF(COUNT('Size, Schedule and Effort'!U:U)>=ROW()-18,INDIRECT("'Size, Schedule and Effort'!$BH$" & SMALL('Size, Schedule and Effort'!U:U,ROW()-18)),"") | N23: =IF($E23<>"",VLOOKUP($E23,$A$1:$B$7,2,0),"") -> NA | O23: =IF($F23<>"",VLOOKUP($F23,$D$1:$E$8,2,0),"") | P23: =IF(COUNTA(B23,E23)+COUNT(D23)>=3,IF(COUNT($N23:$O23)<>0,SUM($N23:$O23)/(SUM($N$17:$O$17)-IF($N23="NA",$N$17,0)-IF($O23="NA",$O$17,0))*100,"NA"),"") | Q23: =IF(AND(A23<>"",D23<>"",D23<>"NA"),VLOOKUP(A23,'Size, Schedule and Effort'!$B$3:$AH$496,44,0),"") | R23: =IF(Q23<>"",IF(Q23<5,1,IF(Q23<10,2,IF(Q23<15,3,IF(Q23<20,4,IF(Q23<25,5,IF(Q23>=25,6,7)))))),"")
A24: =IF(COUNT('Size, Schedule and Effort'!U:U)>=ROW()-18,INDIRECT("'Size, Schedule and Effort'!$C$" & SMALL('Size, Schedule and Effort'!U:U,ROW()-18)),"") | C24: =IF(M24<>"",IF(SUMIF('Size, Schedule and Effort'!$AV$3:$AV$496,M24,'Size, Schedule and Effort'!$AG$3:$AG$496)<>0,SUMIF('Size, Schedule and Effort'!$AV$3:$AV$496,M24,'Size, Schedule and Effort'!$AG$3:$AG$496),"NA"),"") | D24: =IF(M24<>"",IF(SUMIF('Size, Schedule and Effort'!$AV$3:$AV$496,M24,'Size, Schedule and Effort'!$G$3:$G$496)<>0,SUMIF('Size, Schedule and Effort'!$AV$3:$AV$496,M24,'Size, Schedule and Effort'!$G$3:$G$496),"NA"),"") | F24: =IF(R24<>"",CHOOSE(R24,D$7,D$6,D$5,D$4,D$3,D$2),"") | G24: =IF(A24<>"",IF(P24<>"",P24,""),"") | M24: =IF(COUNT('Size, Schedule and Effort'!U:U)>=ROW()-18,INDIRECT("'Size, Schedule and Effort'!$BH$" & SMALL('Size, Schedule and Effort'!U:U,ROW()-18)),"") | N24: =IF($E24<>"",VLOOKUP($E24,$A$1:$B$7,2,0),"") | O24: =IF($F24<>"",VLOOKUP($F24,$D$1:$E$8,2,0),"") | P24: =IF(COUNTA(B24,E24)+COUNT(D24)>=3,IF(COUNT($N24:$O24)<>0,SUM($N24:$O24)/(SUM($N$17:$O$17)-IF($N24="NA",$N$17,0)-IF($O24="NA",$O$17,0))*100,"NA"),"") | Q24: =IF(AND(A24<>"",D24<>"",D24<>"NA"),VLOOKUP(A24,'Size, Schedule and Effort'!$B$3:$AH$496,44,0),"") | R24: =IF(Q24<>"",IF(Q24<5,1,IF(Q24<10,2,IF(Q24<15,3,IF(Q24<20,4,IF(Q24<25,5,IF(Q24>=25,6,7)))))),"")
A25: =IF(COUNT('Size, Schedule and Effort'!U:U)>=ROW()-18,INDIRECT("'Size, Schedule and Effort'!$C$" & SMALL('Size, Schedule and Effort'!U:U,ROW()-18)),"") | C25: =IF(M25<>"",IF(SUMIF('Size, Schedule and Effort'!$AV$3:$AV$496,M25,'Size, Schedule and Effort'!$AG$3:$AG$496)<>0,SUMIF('Size, Schedule and Effort'!$AV$3:$AV$496,M25,'Size, Schedule and Effort'!$AG$3:$AG$496),"NA"),"") | D25: =IF(M25<>"",IF(SUMIF('Size, Schedule and Effort'!$AV$3:$AV$496,M25,'Size, Schedule and Effort'!$G$3:$G$496)<>0,SUMIF('Size, Schedule and Effort'!$AV$3:$AV$496,M25,'Size, Schedule and Effort'!$G$3:$G$496),"NA"),"") | F25: =IF(R25<>"",CHOOSE(R25,D$7,D$6,D$5,D$4,D$3,D$2),"") | G25: =IF(A25<>"",IF(P25<>"",P25,""),"") | M25: =IF(COUNT('Size, Schedule and Effort'!U:U)>=ROW()-18,INDIRECT("'Size, Schedule and Effort'!$BH$" & SMALL('Size, Schedule and Effort'!U:U,ROW()-18)),"") | N25: =IF($E25<>"",VLOOKUP($E25,$A$1:$B$7,2,0),"") | O25: =IF($F25<>"",VLOOKUP($F25,$D$1:$E$8,2,0),"") | P25: =IF(COUNTA(B25,E25)+COUNT(D25)>=3,IF(COUNT($N25:$O25)<>0,SUM($N25:$O25)/(SUM($N$17:$O$17)-IF($N25="NA",$N$17,0)-IF($O25="NA",$O$17,0))*100,"NA"),"") | Q25: =IF(AND(A25<>"",D25<>"",D25<>"NA"),VLOOKUP(A25,'Size, Schedule and Effort'!$B$3:$AH$496,44,0),"") | R25: =IF(Q25<>"",IF(Q25<5,1,IF(Q25<10,2,IF(Q25<15,3,IF(Q25<20,4,IF(Q25<25,5,IF(Q25>=25,6,7)))))),"")
A26: =IF(COUNT('Size, Schedule and Effort'!U:U)>=ROW()-18,INDIRECT("'Size, Schedule and Effort'!$C$" & SMALL('Size, Schedule and Effort'!U:U,ROW()-18)),"") | C26: =IF(M26<>"",IF(SUMIF('Size, Schedule and Effort'!$AV$3:$AV$496,M26,'Size, Schedule and Effort'!$AG$3:$AG$496)<>0,SUMIF('Size, Schedule and Effort'!$AV$3:$AV$496,M26,'Size, Schedule and Effort'!$AG$3:$AG$496),"NA"),"") | D26: =IF(M26<>"",IF(SUMIF('Size, Schedule and Effort'!$AV$3:$AV$496,M26,'Size, Schedule and Effort'!$G$3:$G$496)<>0,SUMIF('Size, Schedule and Effort'!$AV$3:$AV$496,M26,'Size, Schedule and Effort'!$G$3:$G$496),"NA"),"") | F26: =IF(R26<>"",CHOOSE(R26,D$7,D$6,D$5,D$4,D$3,D$2),"") | G26: =IF(A26<>"",IF(P26<>"",P26,""),"") | M26: =IF(COUNT('Size, Schedule and Effort'!U:U)>=ROW()-18,INDIRECT("'Size, Schedule and Effort'!$BH$" & SMALL('Size, Schedule and Effort'!U:U,ROW()-18)),"") | N26: =IF($E26<>"",VLOOKUP($E26,$A$1:$B$7,2,0),"") | O26: =IF($F26<>"",VLOOKUP($F26,$D$1:$E$8,2,0),"") | P26: =IF(COUNTA(B26,E26)+COUNT(D26)>=3,IF(COUNT($N26:$O26)<>0,SUM($N26:$O26)/(SUM($N$17:$O$17)-IF($N26="NA",$N$17,0)-IF($O26="NA",$O$17,0))*100,"NA"),"") | Q26: =IF(AND(A26<>"",D26<>"",D26<>"NA"),VLOOKUP(A26,'Size, Schedule and Effort'!$B$3:$AH$496,44,0),"") | R26: =IF(Q26<>"",IF(Q26<5,1,IF(Q26<10,2,IF(Q26<15,3,IF(Q26<20,4,IF(Q26<25,5,IF(Q26>=25,6,7)))))),"")
A27: =IF(COUNT('Size, Schedule and Effort'!U:U)>=ROW()-18,INDIRECT("'Size, Schedule and Effort'!$C$" & SMALL('Size, Schedule and Effort'!U:U,ROW()-18)),"") | C27: =IF(M27<>"",IF(SUMIF('Size, Schedule and Effort'!$AV$3:$AV$496,M27,'Size, Schedule and Effort'!$AG$3:$AG$496)<>0,SUMIF('Size, Schedule and Effort'!$AV$3:$AV$496,M27,'Size, Schedule and Effort'!$AG$3:$AG$496),"NA"),"") | D27: =IF(M27<>"",IF(SUMIF('Size, Schedule and Effort'!$AV$3:$AV$496,M27,'Size, Schedule and Effort'!$G$3:$G$496)<>0,SUMIF('Size, Schedule and Effort'!$AV$3:$AV$496,M27,'Size, Schedule and Effort'!$G$3:$G$496),"NA"),"") | F27: =IF(R27<>"",CHOOSE(R27,D$7,D$6,D$5,D$4,D$3,D$2),"") | G27: =IF(A27<>"",IF(P27<>"",P27,""),"") | M27: =IF(COUNT('Size, Schedule and Effort'!U:U)>=ROW()-18,INDIRECT("'Size, Schedule and Effort'!$BH$" & SMALL('Size, Schedule and Effort'!U:U,ROW()-18)),"") | N27: =IF($E27<>"",VLOOKUP($E27,$A$1:$B$7,2,0),"") | O27: =IF($F27<>"",VLOOKUP($F27,$D$1:$E$8,2,0),"") | P27: =IF(COUNTA(B27,E27)+COUNT(D27)>=3,IF(COUNT($N27:$O27)<>0,SUM($N27:$O27)/(SUM($N$17:$O$17)-IF($N27="NA",$N$17,0)-IF($O27="NA",$O$17,0))*100,"NA"),"") | Q27: =IF(AND(A27<>"",D27<>"",D27<>"NA"),VLOOKUP(A27,'Size, Schedule and Effort'!$B$3:$AH$496,44,0),"") | R27: =IF(Q27<>"",IF(Q27<5,1,IF(Q27<10,2,IF(Q27<15,3,IF(Q27<20,4,IF(Q27<25,5,IF(Q27>=25,6,7)))))),"")
A28: =IF(COUNT('Size, Schedule and Effort'!U:U)>=ROW()-18,INDIRECT("'Size, Schedule and Effort'!$C$" & SMALL('Size, Schedule and Effort'!U:U,ROW()-18)),"") | C28: =IF(M28<>"",IF(SUMIF('Size, Schedule and Effort'!$AV$3:$AV$496,M28,'Size, Schedule and Effort'!$AG$3:$AG$496)<>0,SUMIF('Size, Schedule and Effort'!$AV$3:$AV$496,M28,'Size, Schedule and Effort'!$AG$3:$AG$496),"NA"),"") | D28: =IF(M28<>"",IF(SUMIF('Size, Schedule and Effort'!$AV$3:$AV$496,M28,'Size, Schedule and Effort'!$G$3:$G$496)<>0,SUMIF('Size, Schedule and Effort'!$AV$3:$AV$496,M28,'Size, Schedule and Effort'!$G$3:$G$496),"NA"),"") | F28: =IF(R28<>"",CHOOSE(R28,D$7,D$6,D$5,D$4,D$3,D$2),"") | G28: =IF(A28<>"",IF(P28<>"",P28,""),"") | M28: =IF(COUNT('Size, Schedule and Effort'!U:U)>=ROW()-18,INDIRECT("'Size, Schedule and Effort'!$BH$" & SMALL('Size, Schedule and Effort'!U:U,ROW()-18)),"") | N28: =IF($E28<>"",VLOOKUP($E28,$A$1:$B$7,2,0),"") | O28: =IF($F28<>"",VLOOKUP($F28,$D$1:$E$8,2,0),"") | P28: =IF(COUNTA(B28,E28)+COUNT(D28)>=3,IF(COUNT($N28:$O28)<>0,SUM($N28:$O28)/(SUM($N$17:$O$17)-IF($N28="NA",$N$17,0)-IF($O28="NA",$O$17,0))*100,"NA"),"") | Q28: =IF(AND(A28<>"",D28<>"",D28<>"NA"),VLOOKUP(A28,'Size, Schedule and Effort'!$B$3:$AH$496,44,0),"") | R28: =IF(Q28<>"",IF(Q28<5,1,IF(Q28<10,2,IF(Q28<15,3,IF(Q28<20,4,IF(Q28<25,5,IF(Q28>=25,6,7)))))),"")
A29: =IF(COUNT('Size, Schedule and Effort'!U:U)>=ROW()-18,INDIRECT("'Size, Schedule and Effort'!$C$" & SMALL('Size, Schedule and Effort'!U:U,ROW()-18)),"") | C29: =IF(M29<>"",IF(SUMIF('Size, Schedule and Effort'!$AV$3:$AV$496,M29,'Size, Schedule and Effort'!$AG$3:$AG$496)<>0,SUMIF('Size, Schedule and Effort'!$AV$3:$AV$496,M29,'Size, Schedule and Effort'!$AG$3:$AG$496),"NA"),"") | D29: =IF(M29<>"",IF(SUMIF('Size, Schedule and Effort'!$AV$3:$AV$496,M29,'Size, Schedule and Effort'!$G$3:$G$496)<>0,SUMIF('Size, Schedule and Effort'!$AV$3:$AV$496,M29,'Size, Schedule and Effort'!$G$3:$G$496),"NA"),"") | F29: =IF(R29<>"",CHOOSE(R29,D$7,D$6,D$5,D$4,D$3,D$2),"") | G29: =IF(A29<>"",IF(P29<>"",P29,""),"") | M29: =IF(COUNT('Size, Schedule and Effort'!U:U)>=ROW()-18,INDIRECT("'Size, Schedule and Effort'!$BH$" & SMALL('Size, Schedule and Effort'!U:U,ROW()-18)),"") | N29: =IF($E29<>"",VLOOKUP($E29,$A$1:$B$7,2,0),"") | O29: =IF($F29<>"",VLOOKUP($F29,$D$1:$E$8,2,0),"") | P29: =IF(COUNTA(B29,E29)+COUNT(D29)>=3,IF(COUNT($N29:$O29)<>0,SUM($N29:$O29)/(SUM($N$17:$O$17)-IF($N29="NA",$N$17,0)-IF($O29="NA",$O$17,0))*100,"NA"),"") | Q29: =IF(AND(A29<>"",D29<>"",D29<>"NA"),VLOOKUP(A29,'Size, Schedule and Effort'!$B$3:$AH$496,44,0),"") | R29: =IF(Q29<>"",IF(Q29<5,1,IF(Q29<10,2,IF(Q29<15,3,IF(Q29<20,4,IF(Q29<25,5,IF(Q29>=25,6,7)))))),"")
A30: =IF(COUNT('Size, Schedule and Effort'!U:U)>=ROW()-18,INDIRECT("'Size, Schedule and Effort'!$C$" & SMALL('Size, Schedule and Effort'!U:U,ROW()-18)),"") | C30: =IF(M30<>"",IF(SUMIF('Size, Schedule and Effort'!$AV$3:$AV$496,M30,'Size, Schedule and Effort'!$AG$3:$AG$496)<>0,SUMIF('Size, Schedule and Effort'!$AV$3:$AV$496,M30,'Size, Schedule and Effort'!$AG$3:$AG$496),"NA"),"") | D30: =IF(M30<>"",IF(SUMIF('Size, Schedule and Effort'!$AV$3:$AV$496,M30,'Size, Schedule and Effort'!$G$3:$G$496)<>0,SUMIF('Size, Schedule and Effort'!$AV$3:$AV$496,M30,'Size, Schedule and Effort'!$G$3:$G$496),"NA"),"") | F30: =IF(R30<>"",CHOOSE(R30,D$7,D$6,D$5,D$4,D$3,D$2),"") | G30: =IF(A30<>"",IF(P30<>"",P30,""),"") | M30: =IF(COUNT('Size, Schedule and Effort'!U:U)>=ROW()-18,INDIRECT("'Size, Schedule and Effort'!$BH$" & SMALL('Size, Schedule and Effort'!U:U,ROW()-18)),"") | N30: =IF($E30<>"",VLOOKUP($E30,$A$1:$B$7,2,0),"") | O30: =IF($F30<>"",VLOOKUP($F30,$D$1:$E$8,2,0),"") | P30: =IF(COUNTA(B30,E30)+COUNT(D30)>=3,IF(COUNT($N30:$O30)<>0,SUM($N30:$O30)/(SUM($N$17:$O$17)-IF($N30="NA",$N$17,0)-IF($O30="NA",$O$17,0))*100,"NA"),"") | Q30: =IF(AND(A30<>"",D30<>"",D30<>"NA"),VLOOKUP(A30,'Size, Schedule and Effort'!$B$3:$AH$496,44,0),"") | R30: =IF(Q30<>"",IF(Q30<5,1,IF(Q30<10,2,IF(Q30<15,3,IF(Q30<20,4,IF(Q30<25,5,IF(Q30>=25,6,7)))))),"")
A31: =IF(COUNT('Size, Schedule and Effort'!U:U)>=ROW()-18,INDIRECT("'Size, Schedule and Effort'!$C$" & SMALL('Size, Schedule and Effort'!U:U,ROW()-18)),"") | C31: =IF(M31<>"",IF(SUMIF('Size, Schedule and Effort'!$AV$3:$AV$496,M31,'Size, Schedule and Effort'!$AG$3:$AG$496)<>0,SUMIF('Size, Schedule and Effort'!$AV$3:$AV$496,M31,'Size, Schedule and Effort'!$AG$3:$AG$496),"NA"),"") | D31: =IF(M31<>"",IF(SUMIF('Size, Schedule and Effort'!$AV$3:$AV$496,M31,'Size, Schedule and Effort'!$G$3:$G$496)<>0,SUMIF('Size, Schedule and Effort'!$AV$3:$AV$496,M31,'Size, Schedule and Effort'!$G$3:$G$496),"NA"),"") | F31: =IF(R31<>"",CHOOSE(R31,D$7,D$6,D$5,D$4,D$3,D$2),"") | G31: =IF(A31<>"",IF(P31<>"",P31,""),"") | M31: =IF(COUNT('Size, Schedule and Effort'!U:U)>=ROW()-18,INDIRECT("'Size, Schedule and Effort'!$BH$" & SMALL('Size, Schedule and Effort'!U:U,ROW()-18)),"") | N31: =IF($E31<>"",VLOOKUP($E31,$A$1:$B$7,2,0),"") | O31: =IF($F31<>"",VLOOKUP($F31,$D$1:$E$8,2,0),"") | P31: =IF(COUNTA(B31,E31)+COUNT(D31)>=3,IF(COUNT($N31:$O31)<>0,SUM($N31:$O31)/(SUM($N$17:$O$17)-IF($N31="NA",$N$17,0)-IF($O31="NA",$O$17,0))*100,"NA"),"") | Q31: =IF(AND(A31<>"",D31<>"",D31<>"NA"),VLOOKUP(A31,'Size, Schedule and Effort'!$B$3:$AH$496,44,0),"") | R31: =IF(Q31<>"",IF(Q31<5,1,IF(Q31<10,2,IF(Q31<15,3,IF(Q31<20,4,IF(Q31<25,5,IF(Q31>=25,6,7)))))),"")
A32: =IF(COUNT('Size, Schedule and Effort'!U:U)>=ROW()-18,INDIRECT("'Size, Schedule and Effort'!$C$" & SMALL('Size, Schedule and Effort'!U:U,ROW()-18)),"") | C32: =IF(M32<>"",IF(SUMIF('Size, Schedule and Effort'!$AV$3:$AV$496,M32,'Size, Schedule and Effort'!$AG$3:$AG$496)<>0,SUMIF('Size, Schedule and Effort'!$AV$3:$AV$496,M32,'Size, Schedule and Effort'!$AG$3:$AG$496),"NA"),"") | D32: =IF(M32<>"",IF(SUMIF('Size, Schedule and Effort'!$AV$3:$AV$496,M32,'Size, Schedule and Effort'!$G$3:$G$496)<>0,SUMIF('Size, Schedule and Effort'!$AV$3:$AV$496,M32,'Size, Schedule and Effort'!$G$3:$G$496),"NA"),"") | F32: =IF(R32<>"",CHOOSE(R32,D$7,D$6,D$5,D$4,D$3,D$2),"") | G32: =IF(A32<>"",IF(P32<>"",P32,""),"") | M32: =IF(COUNT('Size, Schedule and Effort'!U:U)>=ROW()-18,INDIRECT("'Size, Schedule and Effort'!$BH$" & SMALL('Size, Schedule and Effort'!U:U,ROW()-18)),"") | N32: =IF($E32<>"",VLOOKUP($E32,$A$1:$B$7,2,0),"") | O32: =IF($F32<>"",VLOOKUP($F32,$D$1:$E$8,2,0),"") | P32: =IF(COUNTA(B32,E32)+COUNT(D32)>=3,IF(COUNT($N32:$O32)<>0,SUM($N32:$O32)/(SUM($N$17:$O$17)-IF($N32="NA",$N$17,0)-IF($O32="NA",$O$17,0))*100,"NA"),"") | Q32: =IF(AND(A32<>"",D32<>"",D32<>"NA"),VLOOKUP(A32,'Size, Schedule and Effort'!$B$3:$AH$496,44,0),"") | R32: =IF(Q32<>"",IF(Q32<5,1,IF(Q32<10,2,IF(Q32<15,3,IF(Q32<20,4,IF(Q32<25,5,IF(Q32>=25,6,7)))))),"")
A33: =IF(COUNT('Size, Schedule and Effort'!U:U)>=ROW()-18,INDIRECT("'Size, Schedule and Effort'!$C$" & SMALL('Size, Schedule and Effort'!U:U,ROW()-18)),"") | C33: =IF(M33<>"",IF(SUMIF('Size, Schedule and Effort'!$AV$3:$AV$496,M33,'Size, Schedule and Effort'!$AG$3:$AG$496)<>0,SUMIF('Size, Schedule and Effort'!$AV$3:$AV$496,M33,'Size, Schedule and Effort'!$AG$3:$AG$496),"NA"),"") | D33: =IF(M33<>"",IF(SUMIF('Size, Schedule and Effort'!$AV$3:$AV$496,M33,'Size, Schedule and Effort'!$G$3:$G$496)<>0,SUMIF('Size, Schedule and Effort'!$AV$3:$AV$496,M33,'Size, Schedule and Effort'!$G$3:$G$496),"NA"),"") | F33: =IF(R33<>"",CHOOSE(R33,D$7,D$6,D$5,D$4,D$3,D$2),"") | G33: =IF(A33<>"",IF(P33<>"",P33,""),"") | M33: =IF(COUNT('Size, Schedule and Effort'!U:U)>=ROW()-18,INDIRECT("'Size, Schedule and Effort'!$BH$" & SMALL('Size, Schedule and Effort'!U:U,ROW()-18)),"") | N33: =IF($E33<>"",VLOOKUP($E33,$A$1:$B$7,2,0),"") | O33: =IF($F33<>"",VLOOKUP($F33,$D$1:$E$8,2,0),"") | P33: =IF(COUNTA(B33,E33)+COUNT(D33)>=3,IF(COUNT($N33:$O33)<>0,SUM($N33:$O33)/(SUM($N$17:$O$17)-IF($N33="NA",$N$17,0)-IF($O33="NA",$O$17,0))*100,"NA"),"") | Q33: =IF(AND(A33<>"",D33<>"",D33<>"NA"),VLOOKUP(A33,'Size, Schedule and Effort'!$B$3:$AH$496,44,0),"") | R33: =IF(Q33<>"",IF(Q33<5,1,IF(Q33<10,2,IF(Q33<15,3,IF(Q33<20,4,IF(Q33<25,5,IF(Q33>=25,6,7)))))),"")
A34: =IF(COUNT('Size, Schedule and Effort'!U:U)>=ROW()-18,INDIRECT("'Size, Schedule and Effort'!$C$" & SMALL('Size, Schedule and Effort'!U:U,ROW()-18)),"") | C34: =IF(M34<>"",IF(SUMIF('Size, Schedule and Effort'!$AV$3:$AV$496,M34,'Size, Schedule and Effort'!$AG$3:$AG$496)<>0,SUMIF('Size, Schedule and Effort'!$AV$3:$AV$496,M34,'Size, Schedule and Effort'!$AG$3:$AG$496),"NA"),"") | D34: =IF(M34<>"",IF(SUMIF('Size, Schedule and Effort'!$AV$3:$AV$496,M34,'Size, Schedule and Effort'!$G$3:$G$496)<>0,SUMIF('Size, Schedule and Effort'!$AV$3:$AV$496,M34,'Size, Schedule and Effort'!$G$3:$G$496),"NA"),"") | F34: =IF(R34<>"",CHOOSE(R34,D$7,D$6,D$5,D$4,D$3,D$2),"") | G34: =IF(A34<>"",IF(P34<>"",P34,""),"") | M34: =IF(COUNT('Size, Schedule and Effort'!U:U)>=ROW()-18,INDIRECT("'Size, Schedule and Effort'!$BH$" & SMALL('Size, Schedule and Effort'!U:U,ROW()-18)),"") | N34: =IF($E34<>"",VLOOKUP($E34,$A$1:$B$7,2,0),"") | O34: =IF($F34<>"",VLOOKUP($F34,$D$1:$E$8,2,0),"") | P34: =IF(COUNTA(B34,E34)+COUNT(D34)>=3,IF(COUNT($N34:$O34)<>0,SUM($N34:$O34)/(SUM($N$17:$O$17)-IF($N34="NA",$N$17,0)-IF($O34="NA",$O$17,0))*100,"NA"),"") | Q34: =IF(AND(A34<>"",D34<>"",D34<>"NA"),VLOOKUP(A34,'Size, Schedule and Effort'!$B$3:$AH$496,44,0),"") | R34: =IF(Q34<>"",IF(Q34<5,1,IF(Q34<10,2,IF(Q34<15,3,IF(Q34<20,4,IF(Q34<25,5,IF(Q34>=25,6,7)))))),"")
A35: =IF(COUNT('Size, Schedule and Effort'!U:U)>=ROW()-18,INDIRECT("'Size, Schedule and Effort'!$C$" & SMALL('Size, Schedule and Effort'!U:U,ROW()-18)),"") | C35: =IF(M35<>"",IF(SUMIF('Size, Schedule and Effort'!$AV$3:$AV$496,M35,'Size, Schedule and Effort'!$AG$3:$AG$496)<>0,SUMIF('Size, Schedule and Effort'!$AV$3:$AV$496,M35,'Size, Schedule and Effort'!$AG$3:$AG$496),"NA"),"") | D35: =IF(M35<>"",IF(SUMIF('Size, Schedule and Effort'!$AV$3:$AV$496,M35,'Size, Schedule and Effort'!$G$3:$G$496)<>0,SUMIF('Size, Schedule and Effort'!$AV$3:$AV$496,M35,'Size, Schedule and Effort'!$G$3:$G$496),"NA"),"") | F35: =IF(R35<>"",CHOOSE(R35,D$7,D$6,D$5,D$4,D$3,D$2),"") | G35: =IF(A35<>"",IF(P35<>"",P35,""),"") | M35: =IF(COUNT('Size, Schedule and Effort'!U:U)>=ROW()-18,INDIRECT("'Size, Schedule and Effort'!$BH$" & SMALL('Size, Schedule and Effort'!U:U,ROW()-18)),"") | N35: =IF($E35<>"",VLOOKUP($E35,$A$1:$B$7,2,0),"") | O35: =IF($F35<>"",VLOOKUP($F35,$D$1:$E$8,2,0),"") | P35: =IF(COUNTA(B35,E35)+COUNT(D35)>=3,IF(COUNT($N35:$O35)<>0,SUM($N35:$O35)/(SUM($N$17:$O$17)-IF($N35="NA",$N$17,0)-IF($O35="NA",$O$17,0))*100,"NA"),"") | Q35: =IF(AND(A35<>"",D35<>"",D35<>"NA"),VLOOKUP(A35,'Size, Schedule and Effort'!$B$3:$AH$496,44,0),"") | R35: =IF(Q35<>"",IF(Q35<5,1,IF(Q35<10,2,IF(Q35<15,3,IF(Q35<20,4,IF(Q35<25,5,IF(Q35>=25,6,7)))))),"")
... A117: =IF(COUNT('Size, Schedule and Effort'!U:U)>=ROW()-18,INDIRECT("'Size, Schedule and Effort'!$C$" & SMALL('Size, Schedule and Effort'!U:U,ROW()-18)),"") | C117: =IF(M117<>"",IF(SUMIF('Size, Schedule and Effort'!$AV$3:$AV$496,M117,'Size, Schedule and Effort'!$AG$3:$AG$496)<>0,SUMIF('Size, Schedule and Effort'!$AV$3:$AV$496,M117,'Size, Schedule and Effort'!$AG$3:$AG$496),"NA"),"") | D117: =IF(M117<>"",IF(SUMIF('Size, Schedule and Effort'!$AV$3:$AV$496,M117,'Size, Schedule and Effort'!$G$3:$G$496)<>0,SUMIF('Size, Schedule and Effort'!$AV$3:$AV$496,M117,'Size, Schedule and Effort'!$G$3:$G$496),"NA"),"") | F117: =IF(R117<>"",CHOOSE(R117,D$7,D$6,D$5,D$4,D$3,D$2),"") | G117: =IF(A117<>"",IF(P117<>"",P117,""),"") | M117: =IF(COUNT('Size, Schedule and Effort'!U:U)>=ROW()-18,INDIRECT("'Size, Schedule and Effort'!$BH$" & SMALL('Size, Schedule and Effort'!U:U,ROW()-18)),"") | N117: =IF($E117<>"",VLOOKUP($E117,$A$1:$B$7,2,0),"") | O117: =IF($F117<>"",VLOOKUP($F117,$D$1:$E$8,2,0),"") | P117: =IF(COUNTA(B117,E117)+COUNT(D117)>=3,IF(COUNT($N117:$O117)<>0,SUM($N117:$O117)/(SUM($N$17:$O$17)-IF($N117="NA",$N$17,0)-IF($O117="NA",$O$17,0))*100,"NA"),"") | Q117: =IF(AND(A117<>"",D117<>"",D117<>"NA"),VLOOKUP(A117,'Size, Schedule and Effort'!$B$3:$AH$496,44,0),"") | R117: =IF(Q117<>"",IF(Q117<5,1,IF(Q117<10,2,IF(Q117<15,3,IF(Q117<20,4,IF(Q117<25,5,IF(Q117>=25,6,7)))))),"")

Sheet Risk Management - Methodology
B2: Probability Scale
B3: Probability Scale | D3: Description
B5: Almost Certain | C5: 0.9 | D5: Very High Likelihood of occurrence (almost inevitable); occurrence is expected; It would be surprising if this does not happen; Likely to occur once in 3-6 months or known incident is last 3-6 months
B6: Often | C6: 0.7 | D6: High Likelihood of occurrence; occurrence is probable; more likely to happen than not Likely to occur within 1 year or known incident in last 1 year
B7: Likely | C7: 0.5 | D7: Moderate Likelihood of occurrence; occurrence is occasional; just as likely to happen as not. Likely to occur within 1-3 years or known incident in last 1-3 years
B8: Possible | C8: 0.3 | D8: Low Likelihood of occurrence; occurrence is unusual; less likely to happen that not. Likely to occur within 3-5 years or known incident in last 3-5 years
B9: Rare | C9: 0.1 | D9: Very Low Likelihood of occurrence; occurrence is unprecedented; It would be surprising if this does happen. Likely to occur within 10 years or known incident in last 10 years or has happened in past
B12: Possible impact values of risk on Cost, Schedule, Scope, Quality, Regulatory are as follows:
B14: Impact Scale
B15: Impact | C15: Description
B16: 0 | C16: Not Applicable
B17: 1 | C17: Insignificant
B18: 3 | C18: Minor
B19: 5 | C19: Moderate
B20: 7 | C20: Major
B21: 9 | C21: Catastrophic
B23: Note: The Initial Probability and Impact values in Columns J to O reflect the risk assessment as of the date the risk was identified, prior to any controls being implemented (i.e., risk calculated without controls). The Current Probability and Impact values in Columns R to W represent the risk assessment as of the date the risk was reviewed or addressed, after controls have been applied (i.e., risk calculated with controls).
B26: Normalized Impact Calculation
B27: It represents the average of the five impact categories: Cost Impact, Schedule Impact, Scope Impact, Quality Impact, and Regulatory Impact.
B29: Risk Index Calculation
B30: It is the multiplication of the Normalized Impact and Probability.
B33: Risk Treatment Plan
B34: Types | C34: Description
B35: Accept | C35: Formally acknowledging and accepting the residual risk based on an informed decision, where the risk level is deemed tolerable in relation to the organization’s risk criteria.
B36: Transfer | C36: Sharing or transferring the impact of a risk to a third party (e.g., through contractual arrangements, outsourcing, or insurance) while retaining accountability for managing the risk.
B37: Avoid | C37: Eliminating the risk by discontinuing the activities that cause it or by adopting alternative, less risky processes, technologies, or policies.
B38: Mitigate | C38: Implementing risk controls to reduce the likelihood of occurrence and/or the potential impact of a risk to an acceptable level
B41: Risk Acceptance Criteria
B42: Risks with a Risk Value (Risk Index – Current) of less than 1.5 are considered acceptable and will not be subjected to additional risk treatment. Risks with a Risk Value of 1.5 or higher will be addressed through one or more of the four defined risk treatment methods: Accept, Avoid, Mitigate and Transfer.

Sheet Issue Management
A1: S. No. | B1: Description of Issue | C1: Issue Raised By | D1: Date of Issue Raised | E1: Assigned To/ Responsibility | F1: Resolution steps | G1: Target Date of Closure | H1: Actual Closure Date | I1: Comments | J1: Status
K2: =IF(B2<>"",1,0) -> 0 | L2: =IF(J2<>"Open",0,1) -> 0 | M2: =IF(J2<>"Closed",0,1) -> 0 | O2: Issue Status
K3: =IF(B3<>"",1,0) -> 0 | L3: =IF(J3<>"Open",0,1) -> 0 | M3: =IF(J3<>"Closed",0,1) -> 0
K4: =IF(B4<>"",1,0) -> 0 | L4: =IF(J4<>"Open",0,1) -> 0 | M4: =IF(J4<>"Closed",0,1) -> 0 | O4: Open
K5: =IF(B5<>"",1,0) -> 0 | L5: =IF(J5<>"Open",0,1) -> 0 | M5: =IF(J5<>"Closed",0,1) -> 0 | O5: Closed
K6: =IF(B6<>"",1,0) -> 0 | L6: =IF(J6<>"Open",0,1) -> 0 | M6: =IF(J6<>"Closed",0,1) -> 0 | O6: In Progress
K7: =IF(B7<>"",1,0) -> 0 | L7: =IF(J7<>"Open",0,1) -> 0 | M7: =IF(J7<>"Closed",0,1) -> 0
K8: =IF(B8<>"",1,0) -> 0 | L8: =IF(J8<>"Open",0,1) -> 0 | M8: =IF(J8<>"Closed",0,1) -> 0
K9: =IF(B9<>"",1,0) -> 0 | L9: =IF(J9<>"Open",0,1) -> 0 | M9: =IF(J9<>"Closed",0,1) -> 0
K10: =IF(B10<>"",1,0) -> 0 | L10: =IF(J10<>"Open",0,1) -> 0 | M10: =IF(J10<>"Closed",0,1) -> 0
K11: =IF(B11<>"",1,0) -> 0 | L11: =IF(J11<>"Open",0,1) -> 0 | M11: =IF(J11<>"Closed",0,1) -> 0
K12: =IF(B12<>"",1,0) -> 0 | L12: =IF(J12<>"Open",0,1) -> 0 | M12: =IF(J12<>"Closed",0,1) -> 0
K13: =IF(B13<>"",1,0) -> 0 | L13: =IF(J13<>"Open",0,1) -> 0 | M13: =IF(J13<>"Closed",0,1) -> 0
K14: =IF(B14<>"",1,0) -> 0 | L14: =IF(J14<>"Open",0,1) -> 0 | M14: =IF(J14<>"Closed",0,1) -> 0
K15: =IF(B15<>"",1,0) -> 0 | L15: =IF(J15<>"Open",0,1) -> 0 | M15: =IF(J15<>"Closed",0,1) -> 0
K16: =IF(B16<>"",1,0) -> 0 | L16: =IF(J16<>"Open",0,1) -> 0 | M16: =IF(J16<>"Closed",0,1) -> 0

Sheet Opportunity Tracker
A1: No. | B1: Date Identified | C1: Opportunity Title | D1: Opportunity Description | E1: External (Impacts Customer)/ Internal | F1: Owner driving | G1: Process Where Identified | H1: Cost Benefit (Dept/ Org. context) | I1: Revenue Benefit (Dept/ Org context) | J1: Knowledge Benefit (Deptt. / org context) | K1: Process Efficiency or Productivity (Deptt./ org context) | L1: Sales Opportunity (org context) | M1: Next Action Item | N1: Status | O1: Last Updated On | P1: Remarks

Sheet Verification data
A1: Date | B1: Project Name (only applicable for MAZDA-ADS) | C1: Total Planned effort (only applicable for MAZDA-ADS individual projects) | D1: Phase | E1: Module/Submodule | F1: Verification activity | G1: Type | H1: Estimated effort (person hours) | I1: Actual effort (person hours) | J1: Major defects | K1: Minor defects | L1: Trivial defects | M1: Total defects | N1: Closed defects | O1: Weighted defects | P1: Estimated rework (person hours) | Q1: Actual rework (person hours) | R1: Remarks | T1: Applicable phases | U1: Size Units | V1: =COUNTA(T:T)-COUNTBLANK(T1:T23)-1 -> -10 | W1: =COUNTA(U:U)-COUNTBLANK(U1:U23)-1 -> 1 | X1: Size unit1 | Y1: Size unit2 | Z1: Size unit3 | AA1: Size unit4 | AB1: Size unit5
F2: Review-Peer review inspection | G2: Internal | M2: =IF(COUNTA(A2:L2)>0,SUM(J2:L2),"") -> 0 | O2: =IF(COUNTA(A2:L2)>0,1*J2+0.33*K2+0.2*L2,"") -> 0 | T2: Analysis and design | U2: =IF(ISERROR(SMALL('Control panel'!D$3:D$23,ROW()-1)),"",INDIRECT("'Control panel'!B" & SMALL('Control panel'!D$3:D$23,ROW()-1),1)) -> Hours | X2: {=IF(AND(COUNTIF('Control panel'!$A$4:$A$23,$T2)>=COLUMN(A2),$T2<>""),INDIRECT("'Control panel'!B" & SMALL(IF('Control panel'!$A$4:$A$23=$T2,'Control panel'!$C$4:$C$23,100),COLUMN(A2)),1),"")} -> Hours | Y2: {=IF(AND(COUNTIF('Control panel'!$A$4:$A$23,$T2)>=COLUMN(E2),$T2<>""),INDIRECT("'Control panel'!B" & SMALL(IF('Control panel'!$A$4:$A$23=$T2,'Control panel'!$C$4:$C$23,100),COLUMN(E2)),1),"")} | Z2: {=IF(AND(COUNTIF('Control panel'!$A$4:$A$23,$T2)>=COLUMN(F2),$T2<>""),INDIRECT("'Control panel'!B" & SMALL(IF('Control panel'!$A$4:$A$23=$T2,'Control panel'!$C$4:$C$23,100),COLUMN(F2)),1),"")} | AA2: {=IF(AND(COUNTIF('Control panel'!$A$4:$A$23,$T2)>=COLUMN(D2),$T2<>""),INDIRECT("'Control panel'!B" & SMALL(IF('Control panel'!$A$4:$A$23=$T2,'Control panel'!$C$4:$C$23,100),COLUMN(D2)),1),"")} | AB2: {=IF(AND(COUNTIF('Control panel'!$A$4:$A$23,$T2)>=COLUMN(G2),$T2<>""),INDIRECT("'Control panel'!B" & SMALL(IF('Control panel'!$A$4:$A$23=$T2,'Control panel'!$C$4:$C$23,100),COLUMN(G2)),1),"")}
F3: Testing | M3: =IF(COUNTA(A3:L3)>0,SUM(J3:L3),"") -> 0 | O3: =IF(COUNTA(A3:L3)>0,1*J3+0.33*K3+0.2*L3,"") -> 0 | T3: Coding and unit testing | U3: =IF(ISERROR(SMALL('Control panel'!D$3:D$23,ROW()-1)),"",INDIRECT("'Control panel'!B" & SMALL('Control panel'!D$3:D$23,ROW()-1),1)) | X3: {=IF(AND(COUNTIF('Control panel'!$A$4:$A$23,$T3)>=COLUMN(A3),$T3<>""),INDIRECT("'Control panel'!B" & SMALL(IF('Control panel'!$A$4:$A$23=$T3,'Control panel'!$C$4:$C$23,100),COLUMN(A3)),1),"")} -> Hours | Y3: {=IF(AND(COUNTIF('Control panel'!$A$4:$A$23,$T3)>=COLUMN(E3),$T3<>""),INDIRECT("'Control panel'!B" & SMALL(IF('Control panel'!$A$4:$A$23=$T3,'Control panel'!$C$4:$C$23,100),COLUMN(E3)),1),"")} | Z3: {=IF(AND(COUNTIF('Control panel'!$A$4:$A$23,$T3)>=COLUMN(F3),$T3<>""),INDIRECT("'Control panel'!B" & SMALL(IF('Control panel'!$A$4:$A$23=$T3,'Control panel'!$C$4:$C$23,100),COLUMN(F3)),1),"")} | AA3: {=IF(AND(COUNTIF('Control panel'!$A$4:$A$23,$T3)>=COLUMN(D3),$T3<>""),INDIRECT("'Control panel'!B" & SMALL(IF('Control panel'!$A$4:$A$23=$T3,'Control panel'!$C$4:$C$23,100),COLUMN(D3)),1),"")} | AB3: {=IF(AND(COUNTIF('Control panel'!$A$4:$A$23,$T3)>=COLUMN(G3),$T3<>""),INDIRECT("'Control panel'!B" & SMALL(IF('Control panel'!$A$4:$A$23=$T3,'Control panel'!$C$4:$C$23,100),COLUMN(G3)),1),"")}
M4: =IF(COUNTA(A4:L4)>0,SUM(J4:L4),"") | O4: =IF(COUNTA(A4:L4)>0,1*J4+0.33*K4+0.2*L4,"") | T4: System Integration testing | U4: =IF(ISERROR(SMALL('Control panel'!D$3:D$23,ROW()-1)),"",INDIRECT("'Control panel'!B" & SMALL('Control panel'!D$3:D$23,ROW()-1),1)) | X4: {=IF(AND(COUNTIF('Control panel'!$A$4:$A$23,$T4)>=COLUMN(A4),$T4<>""),INDIRECT("'Control panel'!B" & SMALL(IF('Control panel'!$A$4:$A$23=$T4,'Control panel'!$C$4:$C$23,100),COLUMN(A4)),1),"")} -> Hours | Y4: {=IF(AND(COUNTIF('Control panel'!$A$4:$A$23,$T4)>=COLUMN(E4),$T4<>""),INDIRECT("'Control panel'!B" & SMALL(IF('Control panel'!$A$4:$A$23=$T4,'Control panel'!$C$4:$C$23,100),COLUMN(E4)),1),"")} | Z4: {=IF(AND(COUNTIF('Control panel'!$A$4:$A$23,$T4)>=COLUMN(F4),$T4<>""),INDIRECT("'Control panel'!B" & SMALL(IF('Control panel'!$A$4:$A$23=$T4,'Control panel'!$C$4:$C$23,100),COLUMN(F4)),1),"")} | AA4: {=IF(AND(COUNTIF('Control panel'!$A$4:$A$23,$T4)>=COLUMN(D4),$T4<>""),INDIRECT("'Control panel'!B" & SMALL(IF('Control panel'!$A$4:$A$23=$T4,'Control panel'!$C$4:$C$23,100),COLUMN(D4)),1),"")} | AB4: {=IF(AND(COUNTIF('Control panel'!$A$4:$A$23,$T4)>=COLUMN(G4),$T4<>""),INDIRECT("'Control panel'!B" & SMALL(IF('Control panel'!$A$4:$A$23=$T4,'Control panel'!$C$4:$C$23,100),COLUMN(G4)),1),"")}
M5: =IF(COUNTA(A5:L5)>0,SUM(J5:L5),"") | O5: =IF(COUNTA(A5:L5)>0,1*J5+0.33*K5+0.2*L5,"") | T5: User acceptance testing | U5: =IF(ISERROR(SMALL('Control panel'!D$3:D$23,ROW()-1)),"",INDIRECT("'Control panel'!B" & SMALL('Control panel'!D$3:D$23,ROW()-1),1)) | X5: {=IF(AND(COUNTIF('Control panel'!$A$4:$A$23,$T5)>=COLUMN(A5),$T5<>""),INDIRECT("'Control panel'!B" & SMALL(IF('Control panel'!$A$4:$A$23=$T5,'Control panel'!$C$4:$C$23,100),COLUMN(A5)),1),"")} -> Hours | Y5: {=IF(AND(COUNTIF('Control panel'!$A$4:$A$23,$T5)>=COLUMN(E5),$T5<>""),INDIRECT("'Control panel'!B" & SMALL(IF('Control panel'!$A$4:$A$23=$T5,'Control panel'!$C$4:$C$23,100),COLUMN(E5)),1),"")} | Z5: {=IF(AND(COUNTIF('Control panel'!$A$4:$A$23,$T5)>=COLUMN(F5),$T5<>""),INDIRECT("'Control panel'!B" & SMALL(IF('Control panel'!$A$4:$A$23=$T5,'Control panel'!$C$4:$C$23,100),COLUMN(F5)),1),"")} | AA5: {=IF(AND(COUNTIF('Control panel'!$A$4:$A$23,$T5)>=COLUMN(D5),$T5<>""),INDIRECT("'Control panel'!B" & SMALL(IF('Control panel'!$A$4:$A$23=$T5,'Control panel'!$C$4:$C$23,100),COLUMN(D5)),1),"")} | AB5: {=IF(AND(COUNTIF('Control panel'!$A$4:$A$23,$T5)>=COLUMN(G5),$T5<>""),INDIRECT("'Control panel'!B" & SMALL(IF('Control panel'!$A$4:$A$23=$T5,'Control panel'!$C$4:$C$23,100),COLUMN(G5)),1),"")}
M6: =IF(COUNTA(A6:L6)>0,SUM(J6:L6),"") | O6: =IF(COUNTA(A6:L6)>0,1*J6+0.33*K6+0.2*L6,"") | T6: Production deployment | U6: =IF(ISERROR(SMALL('Control panel'!D$3:D$23,ROW()-1)),"",INDIRECT("'Control panel'!B" & SMALL('Control panel'!D$3:D$23,ROW()-1),1)) | X6: {=IF(AND(COUNTIF('Control panel'!$A$4:$A$23,$T6)>=COLUMN(A6),$T6<>""),INDIRECT("'Control panel'!B" & SMALL(IF('Control panel'!$A$4:$A$23=$T6,'Control panel'!$C$4:$C$23,100),COLUMN(A6)),1),"")} -> Hours | Y6: {=IF(AND(COUNTIF('Control panel'!$A$4:$A$23,$T6)>=COLUMN(E6),$T6<>""),INDIRECT("'Control panel'!B" & SMALL(IF('Control panel'!$A$4:$A$23=$T6,'Control panel'!$C$4:$C$23,100),COLUMN(E6)),1),"")} | Z6: {=IF(AND(COUNTIF('Control panel'!$A$4:$A$23,$T6)>=COLUMN(F6),$T6<>""),INDIRECT("'Control panel'!B" & SMALL(IF('Control panel'!$A$4:$A$23=$T6,'Control panel'!$C$4:$C$23,100),COLUMN(F6)),1),"")} | AA6: {=IF(AND(COUNTIF('Control panel'!$A$4:$A$23,$T6)>=COLUMN(D6),$T6<>""),INDIRECT("'Control panel'!B" & SMALL(IF('Control panel'!$A$4:$A$23=$T6,'Control panel'!$C$4:$C$23,100),COLUMN(D6)),1),"")} | AB6: {=IF(AND(COUNTIF('Control panel'!$A$4:$A$23,$T6)>=COLUMN(G6),$T6<>""),INDIRECT("'Control panel'!B" & SMALL(IF('Control panel'!$A$4:$A$23=$T6,'Control panel'!$C$4:$C$23,100),COLUMN(G6)),1),"")}
M7: =IF(COUNTA(A7:L7)>0,SUM(J7:L7),"") | O7: =IF(COUNTA(A7:L7)>0,1*J7+0.33*K7+0.2*L7,"") | T7: Post production support | U7: =IF(ISERROR(SMALL('Control panel'!D$3:D$23,ROW()-1)),"",INDIRECT("'Control panel'!B" & SMALL('Control panel'!D$3:D$23,ROW()-1),1)) | X7: {=IF(AND(COUNTIF('Control panel'!$A$4:$A$23,$T7)>=COLUMN(A7),$T7<>""),INDIRECT("'Control panel'!B" & SMALL(IF('Control panel'!$A$4:$A$23=$T7,'Control panel'!$C$4:$C$23,100),COLUMN(A7)),1),"")} | Y7: {=IF(AND(COUNTIF('Control panel'!$A$4:$A$23,$T7)>=COLUMN(E7),$T7<>""),INDIRECT("'Control panel'!B" & SMALL(IF('Control panel'!$A$4:$A$23=$T7,'Control panel'!$C$4:$C$23,100),COLUMN(E7)),1),"")} | Z7: {=IF(AND(COUNTIF('Control panel'!$A$4:$A$23,$T7)>=COLUMN(F7),$T7<>""),INDIRECT("'Control panel'!B" & SMALL(IF('Control panel'!$A$4:$A$23=$T7,'Control panel'!$C$4:$C$23,100),COLUMN(F7)),1),"")} | AA7: {=IF(AND(COUNTIF('Control panel'!$A$4:$A$23,$T7)>=COLUMN(D7),$T7<>""),INDIRECT("'Control panel'!B" & SMALL(IF('Control panel'!$A$4:$A$23=$T7,'Control panel'!$C$4:$C$23,100),COLUMN(D7)),1),"")} | AB7: {=IF(AND(COUNTIF('Control panel'!$A$4:$A$23,$T7)>=COLUMN(G7),$T7<>""),INDIRECT("'Control panel'!B" & SMALL(IF('Control panel'!$A$4:$A$23=$T7,'Control panel'!$C$4:$C$23,100),COLUMN(G7)),1),"")}
M8: =IF(COUNTA(A8:L8)>0,SUM(J8:L8),"") | O8: =IF(COUNTA(A8:L8)>0,1*J8+0.33*K8+0.2*L8,"") | U8: =IF(ISERROR(SMALL('Control panel'!D$3:D$23,ROW()-1)),"",INDIRECT("'Control panel'!B" & SMALL('Control panel'!D$3:D$23,ROW()-1),1)) | X8: {=IF(AND(COUNTIF('Control panel'!$A$4:$A$23,$T8)>=COLUMN(A8),$T8<>""),INDIRECT("'Control panel'!B" & SMALL(IF('Control panel'!$A$4:$A$23=$T8,'Control panel'!$C$4:$C$23,100),COLUMN(A8)),1),"")} | Y8: {=IF(AND(COUNTIF('Control panel'!$A$4:$A$23,$T8)>=COLUMN(E8),$T8<>""),INDIRECT("'Control panel'!B" & SMALL(IF('Control panel'!$A$4:$A$23=$T8,'Control panel'!$C$4:$C$23,100),COLUMN(E8)),1),"")} | Z8: {=IF(AND(COUNTIF('Control panel'!$A$4:$A$23,$T8)>=COLUMN(F8),$T8<>""),INDIRECT("'Control panel'!B" & SMALL(IF('Control panel'!$A$4:$A$23=$T8,'Control panel'!$C$4:$C$23,100),COLUMN(F8)),1),"")} | AA8: {=IF(AND(COUNTIF('Control panel'!$A$4:$A$23,$T8)>=COLUMN(D8),$T8<>""),INDIRECT("'Control panel'!B" & SMALL(IF('Control panel'!$A$4:$A$23=$T8,'Control panel'!$C$4:$C$23,100),COLUMN(D8)),1),"")} | AB8: {=IF(AND(COUNTIF('Control panel'!$A$4:$A$23,$T8)>=COLUMN(G8),$T8<>""),INDIRECT("'Control panel'!B" & SMALL(IF('Control panel'!$A$4:$A$23=$T8,'Control panel'!$C$4:$C$23,100),COLUMN(G8)),1),"")}
M9: =IF(COUNTA(A9:L9)>0,SUM(J9:L9),"") | O9: =IF(COUNTA(A9:L9)>0,1*J9+0.33*K9+0.2*L9,"") | U9: =IF(ISERROR(SMALL('Control panel'!D$3:D$23,ROW()-1)),"",INDIRECT("'Control panel'!B" & SMALL('Control panel'!D$3:D$23,ROW()-1),1)) | X9: {=IF(AND(COUNTIF('Control panel'!$A$4:$A$23,$T9)>=COLUMN(A9),$T9<>""),INDIRECT("'Control panel'!B" & SMALL(IF('Control panel'!$A$4:$A$23=$T9,'Control panel'!$C$4:$C$23,100),COLUMN(A9)),1),"")} | Y9: {=IF(AND(COUNTIF('Control panel'!$A$4:$A$23,$T9)>=COLUMN(E9),$T9<>""),INDIRECT("'Control panel'!B" & SMALL(IF('Control panel'!$A$4:$A$23=$T9,'Control panel'!$C$4:$C$23,100),COLUMN(E9)),1),"")} | Z9: {=IF(AND(COUNTIF('Control panel'!$A$4:$A$23,$T9)>=COLUMN(F9),$T9<>""),INDIRECT("'Control panel'!B" & SMALL(IF('Control panel'!$A$4:$A$23=$T9,'Control panel'!$C$4:$C$23,100),COLUMN(F9)),1),"")} | AA9: {=IF(AND(COUNTIF('Control panel'!$A$4:$A$23,$T9)>=COLUMN(D9),$T9<>""),INDIRECT("'Control panel'!B" & SMALL(IF('Control panel'!$A$4:$A$23=$T9,'Control panel'!$C$4:$C$23,100),COLUMN(D9)),1),"")} | AB9: {=IF(AND(COUNTIF('Control panel'!$A$4:$A$23,$T9)>=COLUMN(G9),$T9<>""),INDIRECT("'Control panel'!B" & SMALL(IF('Control panel'!$A$4:$A$23=$T9,'Control panel'!$C$4:$C$23,100),COLUMN(G9)),1),"")}
M10: =IF(COUNTA(A10:L10)>0,SUM(J10:L10),"") | O10: =IF(COUNTA(A10:L10)>0,1*J10+0.33*K10+0.2*L10,"") | U10: =IF(ISERROR(SMALL('Control panel'!D$3:D$23,ROW()-1)),"",INDIRECT("'Control panel'!B" & SMALL('Control panel'!D$3:D$23,ROW()-1),1)) | X10: {=IF(AND(COUNTIF('Control panel'!$A$4:$A$23,$T10)>=COLUMN(A10),$T10<>""),INDIRECT("'Control panel'!B" & SMALL(IF('Control panel'!$A$4:$A$23=$T10,'Control panel'!$C$4:$C$23,100),COLUMN(A10)),1),"")} | Y10: {=IF(AND(COUNTIF('Control panel'!$A$4:$A$23,$T10)>=COLUMN(E10),$T10<>""),INDIRECT("'Control panel'!B" & SMALL(IF('Control panel'!$A$4:$A$23=$T10,'Control panel'!$C$4:$C$23,100),COLUMN(E10)),1),"")} | Z10: {=IF(AND(COUNTIF('Control panel'!$A$4:$A$23,$T10)>=COLUMN(F10),$T10<>""),INDIRECT("'Control panel'!B" & SMALL(IF('Control panel'!$A$4:$A$23=$T10,'Control panel'!$C$4:$C$23,100),COLUMN(F10)),1),"")} | AA10: {=IF(AND(COUNTIF('Control panel'!$A$4:$A$23,$T10)>=COLUMN(D10),$T10<>""),INDIRECT("'Control panel'!B" & SMALL(IF('Control panel'!$A$4:$A$23=$T10,'Control panel'!$C$4:$C$23,100),COLUMN(D10)),1),"")} | AB10: {=IF(AND(COUNTIF('Control panel'!$A$4:$A$23,$T10)>=COLUMN(G10),$T10<>""),INDIRECT("'Control panel'!B" & SMALL(IF('Control panel'!$A$4:$A$23=$T10,'Control panel'!$C$4:$C$23,100),COLUMN(G10)),1),"")}
M11: =IF(COUNTA(A11:L11)>0,SUM(J11:L11),"") | O11: =IF(COUNTA(A11:L11)>0,1*J11+0.33*K11+0.2*L11,"") | U11: =IF(ISERROR(SMALL('Control panel'!D$3:D$23,ROW()-1)),"",INDIRECT("'Control panel'!B" & SMALL('Control panel'!D$3:D$23,ROW()-1),1)) | X11: {=IF(AND(COUNTIF('Control panel'!$A$4:$A$23,$T11)>=COLUMN(A11),$T11<>""),INDIRECT("'Control panel'!B" & SMALL(IF('Control panel'!$A$4:$A$23=$T11,'Control panel'!$C$4:$C$23,100),COLUMN(A11)),1),"")} | Y11: {=IF(AND(COUNTIF('Control panel'!$A$4:$A$23,$T11)>=COLUMN(E11),$T11<>""),INDIRECT("'Control panel'!B" & SMALL(IF('Control panel'!$A$4:$A$23=$T11,'Control panel'!$C$4:$C$23,100),COLUMN(E11)),1),"")} | Z11: {=IF(AND(COUNTIF('Control panel'!$A$4:$A$23,$T11)>=COLUMN(F11),$T11<>""),INDIRECT("'Control panel'!B" & SMALL(IF('Control panel'!$A$4:$A$23=$T11,'Control panel'!$C$4:$C$23,100),COLUMN(F11)),1),"")} | AA11: {=IF(AND(COUNTIF('Control panel'!$A$4:$A$23,$T11)>=COLUMN(D11),$T11<>""),INDIRECT("'Control panel'!B" & SMALL(IF('Control panel'!$A$4:$A$23=$T11,'Control panel'!$C$4:$C$23,100),COLUMN(D11)),1),"")} | AB11: {=IF(AND(COUNTIF('Control panel'!$A$4:$A$23,$T11)>=COLUMN(G11),$T11<>""),INDIRECT("'Control panel'!B" & SMALL(IF('Control panel'!$A$4:$A$23=$T11,'Control panel'!$C$4:$C$23,100),COLUMN(G11)),1),"")}
M12: =IF(COUNTA(A12:L12)>0,SUM(J12:L12),"") | O12: =IF(COUNTA(A12:L12)>0,1*J12+0.33*K12+0.2*L12,"") | U12: =IF(ISERROR(SMALL('Control panel'!D$3:D$23,ROW()-1)),"",INDIRECT("'Control panel'!B" & SMALL('Control panel'!D$3:D$23,ROW()-1),1)) | X12: {=IF(AND(COUNTIF('Control panel'!$A$4:$A$23,$T12)>=COLUMN(A12),$T12<>""),INDIRECT("'Control panel'!B" & SMALL(IF('Control panel'!$A$4:$A$23=$T12,'Control panel'!$C$4:$C$23,100),COLUMN(A12)),1),"")} | Y12: {=IF(AND(COUNTIF('Control panel'!$A$4:$A$23,$T12)>=COLUMN(E12),$T12<>""),INDIRECT("'Control panel'!B" & SMALL(IF('Control panel'!$A$4:$A$23=$T12,'Control panel'!$C$4:$C$23,100),COLUMN(E12)),1),"")} | Z12: {=IF(AND(COUNTIF('Control panel'!$A$4:$A$23,$T12)>=COLUMN(F12),$T12<>""),INDIRECT("'Control panel'!B" & SMALL(IF('Control panel'!$A$4:$A$23=$T12,'Control panel'!$C$4:$C$23,100),COLUMN(F12)),1),"")} | AA12: {=IF(AND(COUNTIF('Control panel'!$A$4:$A$23,$T12)>=COLUMN(D12),$T12<>""),INDIRECT("'Control panel'!B" & SMALL(IF('Control panel'!$A$4:$A$23=$T12,'Control panel'!$C$4:$C$23,100),COLUMN(D12)),1),"")} | AB12: {=IF(AND(COUNTIF('Control panel'!$A$4:$A$23,$T12)>=COLUMN(G12),$T12<>""),INDIRECT("'Control panel'!B" & SMALL(IF('Control panel'!$A$4:$A$23=$T12,'Control panel'!$C$4:$C$23,100),COLUMN(G12)),1),"")}
M13: =IF(COUNTA(A13:L13)>0,SUM(J13:L13),"") | O13: =IF(COUNTA(A13:L13)>0,1*J13+0.33*K13+0.2*L13,"") | U13: =IF(ISERROR(SMALL('Control panel'!D$3:D$23,ROW()-1)),"",INDIRECT("'Control panel'!B" & SMALL('Control panel'!D$3:D$23,ROW()-1),1)) | X13: {=IF(AND(COUNTIF('Control panel'!$A$4:$A$23,$T13)>=COLUMN(A13),$T13<>""),INDIRECT("'Control panel'!B" & SMALL(IF('Control panel'!$A$4:$A$23=$T13,'Control panel'!$C$4:$C$23,100),COLUMN(A13)),1),"")} | Y13: {=IF(AND(COUNTIF('Control panel'!$A$4:$A$23,$T13)>=COLUMN(E13),$T13<>""),INDIRECT("'Control panel'!B" & SMALL(IF('Control panel'!$A$4:$A$23=$T13,'Control panel'!$C$4:$C$23,100),COLUMN(E13)),1),"")} | Z13: {=IF(AND(COUNTIF('Control panel'!$A$4:$A$23,$T13)>=COLUMN(F13),$T13<>""),INDIRECT("'Control panel'!B" & SMALL(IF('Control panel'!$A$4:$A$23=$T13,'Control panel'!$C$4:$C$23,100),COLUMN(F13)),1),"")} | AA13: {=IF(AND(COUNTIF('Control panel'!$A$4:$A$23,$T13)>=COLUMN(D13),$T13<>""),INDIRECT("'Control panel'!B" & SMALL(IF('Control panel'!$A$4:$A$23=$T13,'Control panel'!$C$4:$C$23,100),COLUMN(D13)),1),"")} | AB13: {=IF(AND(COUNTIF('Control panel'!$A$4:$A$23,$T13)>=COLUMN(G13),$T13<>""),INDIRECT("'Control panel'!B" & SMALL(IF('Control panel'!$A$4:$A$23=$T13,'Control panel'!$C$4:$C$23,100),COLUMN(G13)),1),"")}
M14: =IF(COUNTA(A14:L14)>0,SUM(J14:L14),"") | O14: =IF(COUNTA(A14:L14)>0,1*J14+0.33*K14+0.2*L14,"") | U14: =IF(ISERROR(SMALL('Control panel'!D$3:D$23,ROW()-1)),"",INDIRECT("'Control panel'!B" & SMALL('Control panel'!D$3:D$23,ROW()-1),1)) | X14: {=IF(AND(COUNTIF('Control panel'!$A$4:$A$23,$T14)>=COLUMN(A14),$T14<>""),INDIRECT("'Control panel'!B" & SMALL(IF('Control panel'!$A$4:$A$23=$T14,'Control panel'!$C$4:$C$23,100),COLUMN(A14)),1),"")} | Y14: {=IF(AND(COUNTIF('Control panel'!$A$4:$A$23,$T14)>=COLUMN(E14),$T14<>""),INDIRECT("'Control panel'!B" & SMALL(IF('Control panel'!$A$4:$A$23=$T14,'Control panel'!$C$4:$C$23,100),COLUMN(E14)),1),"")} | Z14: {=IF(AND(COUNTIF('Control panel'!$A$4:$A$23,$T14)>=COLUMN(F14),$T14<>""),INDIRECT("'Control panel'!B" & SMALL(IF('Control panel'!$A$4:$A$23=$T14,'Control panel'!$C$4:$C$23,100),COLUMN(F14)),1),"")} | AA14: {=IF(AND(COUNTIF('Control panel'!$A$4:$A$23,$T14)>=COLUMN(D14),$T14<>""),INDIRECT("'Control panel'!B" & SMALL(IF('Control panel'!$A$4:$A$23=$T14,'Control panel'!$C$4:$C$23,100),COLUMN(D14)),1),"")} | AB14: {=IF(AND(COUNTIF('Control panel'!$A$4:$A$23,$T14)>=COLUMN(G14),$T14<>""),INDIRECT("'Control panel'!B" & SMALL(IF('Control panel'!$A$4:$A$23=$T14,'Control panel'!$C$4:$C$23,100),COLUMN(G14)),1),"")}
M15: =IF(COUNTA(A15:L15)>0,SUM(J15:L15),"") | O15: =IF(COUNTA(A15:L15)>0,1*J15+0.33*K15+0.2*L15,"") | U15: =IF(ISERROR(SMALL('Control panel'!D$3:D$23,ROW()-1)),"",INDIRECT("'Control panel'!B" & SMALL('Control panel'!D$3:D$23,ROW()-1),1)) | X15: {=IF(AND(COUNTIF('Control panel'!$A$4:$A$23,$T15)>=COLUMN(A15),$T15<>""),INDIRECT("'Control panel'!B" & SMALL(IF('Control panel'!$A$4:$A$23=$T15,'Control panel'!$C$4:$C$23,100),COLUMN(A15)),1),"")} | Y15: {=IF(AND(COUNTIF('Control panel'!$A$4:$A$23,$T15)>=COLUMN(E15),$T15<>""),INDIRECT("'Control panel'!B" & SMALL(IF('Control panel'!$A$4:$A$23=$T15,'Control panel'!$C$4:$C$23,100),COLUMN(E15)),1),"")} | Z15: {=IF(AND(COUNTIF('Control panel'!$A$4:$A$23,$T15)>=COLUMN(F15),$T15<>""),INDIRECT("'Control panel'!B" & SMALL(IF('Control panel'!$A$4:$A$23=$T15,'Control panel'!$C$4:$C$23,100),COLUMN(F15)),1),"")} | AA15: {=IF(AND(COUNTIF('Control panel'!$A$4:$A$23,$T15)>=COLUMN(D15),$T15<>""),INDIRECT("'Control panel'!B" & SMALL(IF('Control panel'!$A$4:$A$23=$T15,'Control panel'!$C$4:$C$23,100),COLUMN(D15)),1),"")} | AB15: {=IF(AND(COUNTIF('Control panel'!$A$4:$A$23,$T15)>=COLUMN(G15),$T15<>""),INDIRECT("'Control panel'!B" & SMALL(IF('Control panel'!$A$4:$A$23=$T15,'Control panel'!$C$4:$C$23,100),COLUMN(G15)),1),"")}
M16: =IF(COUNTA(A16:L16)>0,SUM(J16:L16),"") | O16: =IF(COUNTA(A16:L16)>0,1*J16+0.33*K16+0.2*L16,"") | U16: =IF(ISERROR(SMALL('Control panel'!D$3:D$23,ROW()-1)),"",INDIRECT("'Control panel'!B" & SMALL('Control panel'!D$3:D$23,ROW()-1),1)) | X16: {=IF(AND(COUNTIF('Control panel'!$A$4:$A$23,$T16)>=COLUMN(A16),$T16<>""),INDIRECT("'Control panel'!B" & SMALL(IF('Control panel'!$A$4:$A$23=$T16,'Control panel'!$C$4:$C$23,100),COLUMN(A16)),1),"")} | Y16: {=IF(AND(COUNTIF('Control panel'!$A$4:$A$23,$T16)>=COLUMN(E16),$T16<>""),INDIRECT("'Control panel'!B" & SMALL(IF('Control panel'!$A$4:$A$23=$T16,'Control panel'!$C$4:$C$23,100),COLUMN(E16)),1),"")} | Z16: {=IF(AND(COUNTIF('Control panel'!$A$4:$A$23,$T16)>=COLUMN(F16),$T16<>""),INDIRECT("'Control panel'!B" & SMALL(IF('Control panel'!$A$4:$A$23=$T16,'Control panel'!$C$4:$C$23,100),COLUMN(F16)),1),"")} | AA16: {=IF(AND(COUNTIF('Control panel'!$A$4:$A$23,$T16)>=COLUMN(D16),$T16<>""),INDIRECT("'Control panel'!B" & SMALL(IF('Control panel'!$A$4:$A$23=$T16,'Control panel'!$C$4:$C$23,100),COLUMN(D16)),1),"")} | AB16: {=IF(AND(COUNTIF('Control panel'!$A$4:$A$23,$T16)>=COLUMN(G16),$T16<>""),INDIRECT("'Control panel'!B" & SMALL(IF('Control panel'!$A$4:$A$23=$T16,'Control panel'!$C$4:$C$23,100),COLUMN(G16)),1),"")}
M17: =IF(COUNTA(A17:L17)>0,SUM(J17:L17),"") | O17: =IF(COUNTA(A17:L17)>0,1*J17+0.33*K17+0.2*L17,"") | U17: =IF(ISERROR(SMALL('Control panel'!D$3:D$23,ROW()-1)),"",INDIRECT("'Control panel'!B" & SMALL('Control panel'!D$3:D$23,ROW()-1),1))
M18: =IF(COUNTA(A18:L18)>0,SUM(J18:L18),"") | O18: =IF(COUNTA(A18:L18)>0,1*J18+0.33*K18+0.2*L18,"") | U18: =IF(ISERROR(SMALL('Control panel'!D$3:D$23,ROW()-1)),"",INDIRECT("'Control panel'!B" & SMALL('Control panel'!D$3:D$23,ROW()-1),1))
M19: =IF(COUNTA(A19:L19)>0,SUM(J19:L19),"") | O19: =IF(COUNTA(A19:L19)>0,1*J19+0.33*K19+0.2*L19,"") | U19: =IF(ISERROR(SMALL('Control panel'!D$3:D$23,ROW()-1)),"",INDIRECT("'Control panel'!B" & SMALL('Control panel'!D$3:D$23,ROW()-1),1))
M20: =IF(COUNTA(A20:L20)>0,SUM(J20:L20),"") | O20: =IF(COUNTA(A20:L20)>0,1*J20+0.33*K20+0.2*L20,"") | U20: =IF(ISERROR(SMALL('Control panel'!D$3:D$23,ROW()-1)),"",INDIRECT("'Control panel'!B" & SMALL('Control panel'!D$3:D$23,ROW()-1),1))
M21: =IF(COUNTA(A21:L21)>0,SUM(J21:L21),"") | O21: =IF(COUNTA(A21:L21)>0,1*J21+0.33*K21+0.2*L21,"") | U21: =IF(ISERROR(SMALL('Control panel'!D$3:D$23,ROW()-1)),"",INDIRECT("'Control panel'!B" & SMALL('Control panel'!D$3:D$23,ROW()-1),1))
M22: =IF(COUNTA(A22:L22)>0,SUM(J22:L22),"") | O22: =IF(COUNTA(A22:L22)>0,1*J22+0.33*K22+0.2*L22,"") | U22: =IF(ISERROR(SMALL('Control panel'!D$3:D$23,ROW()-1)),"",INDIRECT("'Control panel'!B" & SMALL('Control panel'!D$3:D$23,ROW()-1),1))
M23: =IF(COUNTA(A23:L23)>0,SUM(J23:L23),"") | O23: =IF(COUNTA(A23:L23)>0,1*J23+0.33*K23+0.2*L23,"") | U23: =IF(ISERROR(SMALL('Control panel'!D$3:D$23,ROW()-1)),"",INDIRECT("'Control panel'!B" & SMALL('Control panel'!D$3:D$23,ROW()-1),1))
M24: =IF(COUNTA(A24:L24)>0,SUM(J24:L24),"") | O24: =IF(COUNTA(A24:L24)>0,1*J24+0.33*K24+0.2*L24,"")
M25: =IF(COUNTA(A25:L25)>0,SUM(J25:L25),"") | O25: =IF(COUNTA(A25:L25)>0,1*J25+0.33*K25+0.2*L25,"")
M26: =IF(COUNTA(A26:L26)>0,SUM(J26:L26),"") | O26: =IF(COUNTA(A26:L26)>0,1*J26+0.33*K26+0.2*L26,"")
M27: =IF(COUNTA(A27:L27)>0,SUM(J27:L27),"") | O27: =IF(COUNTA(A27:L27)>0,1*J27+0.33*K27+0.2*L27,"")
M28: =IF(COUNTA(A28:L28)>0,SUM(J28:L28),"") | O28: =IF(COUNTA(A28:L28)>0,1*J28+0.33*K28+0.2*L28,"")
M29: =IF(COUNTA(A29:L29)>0,SUM(J29:L29),"") | O29: =IF(COUNTA(A29:L29)>0,1*J29+0.33*K29+0.2*L29,"")

Sheet Verification Summary
A1: =IF('Project information1'!A1<>"",'Project information1'!A1,"") -> Project Name | B1: =IF('Project information1'!B1<>"",'Project information1'!B1,"") | D1: =IF('Project information1'!C1<>"",'Project information1'!C1,"") -> Customer name | E1: =IF('Project information1'!D1<>"",'Project information1'!D1,"")
A2: =IF('Project information1'!A3<>"",'Project information1'!A3,"") -> Business Unit (SAP) | B2: =IF('Project information1'!B3<>"",'Project information1'!B3,"") | D2: =IF('Project information1'!A7<>"",'Project information1'!A7,"") -> Project Manager | E2: =IF('Project information1'!B7<>"",'Project information1'!B7,"")
A3: =IF('Project information1'!A4<>"",'Project information1'!A4,"") -> Business Model | B3: =IF('Project information1'!B4<>"",'Project information1'!B4,"") | D3: =IF('Project information1'!A8<>"",'Project information1'!A8,"") -> Senior Manager | E3: =IF('Project information1'!B8<>"",'Project information1'!B8,"")
A4: =IF('Project information1'!A5<>"",'Project information1'!A5,"") -> Project Type | B4: =IF('Project information1'!B5<>"",'Project information1'!B5,"") | D4: =IF('Project information1'!A9<>"",'Project information1'!A9,"") -> Engineering Staff | E4: =IF('Project information1'!B9<>"",'Project information1'!B9,"")
A7: Internal Verification defects
C8: Review | I8: Testing
A9: Phase | B9: Work product type / unit | C9: Verification effort | D9: Total Size | E9: Major defects | F9: Minor defects | G9: Trivial defects | H9: Rework effort | I9: Testing effort | J9: Total Size | K9: Major defects | L9: Minor defects | M9: Trivial defects | N9: Rework effort | P9: Phase - wk pdt | Q9: Major issues / defects | R9: Minor issues /d efects | S9: Trivial issues / defects
A10: =IF('Control panel'!A4<>"",'Control panel'!A4,"") -> Analysis and design | B10: =IF('Control panel'!B4<>"",'Control panel'!B4,"") -> Hours | C10: {=IF($A10<>"",SUM(IF('Verification data'!$D$2:$D$5000=$A10,IF(NOT(ISERR(SEARCH("Review",'Verification data'!$F$2:$F$5000,1))),IF('Verification data'!#REF! = 'Verification Summary'!B10, IF('Verification data'!$G$2:$G$5000="Internal",'Verification data'!$I$2:$I$5000,0),0),0),0)),"")} -> 0 | D10: {=IF($A10<>"",SUM(IF('Verification data'!$D$2:$D$5000=$A10,IF(NOT(ISERR(SEARCH("Review",'Verification data'!$F$2:$F$5000,1))),IF('Verification data'!#REF! = 'Verification Summary'!B10, IF('Verification data'!$G$2:$G$5000="Internal",'Verification data'!#REF!,0),0),0),0)),"")} -> 0 | E10: {=IF($A10<>"",SUM(IF('Verification data'!$D$2:$D$5000=$A10,IF(NOT(ISERR(SEARCH("Review",'Verification data'!$F$2:$F$5000,1))),IF('Verification data'!#REF! = 'Verification Summary'!B10, IF('Verification data'!$G$2:$G$5000="Internal",'Verification data'!$J$2:$J$5000,0),0),0),0)),"")} -> 0 | F10: {=IF($A10<>"",SUM(IF('Verification data'!$D$2:$D$5000=$A10,IF(NOT(ISERR(SEARCH("Review",'Verification data'!$F$2:$F$5000,1))),IF('Verification data'!#REF! = 'Verification Summary'!B10, IF('Verification data'!$G$2:$G$5000="Internal",'Verification data'!$K$2:$K$5000,0),0),0),0)),"")} -> 0 | G10: {=IF($A10<>"",SUM(IF('Verification data'!$D$2:$D$5000=$A10,IF(NOT(ISERR(SEARCH("Review",'Verification data'!$F$2:$F$5000,1))),IF('Verification data'!#REF! = 'Verification Summary'!B10, IF('Verification data'!$G$2:$G$5000="Internal",'Verification data'!$L$2:$L$5000,0),0),0),0)),"")} -> 0 | H10: 0 | I10: {=IF($A10<>"",SUM(IF('Verification data'!$D$2:$D$5000=$A10,IF('Verification data'!$F$2:$F$5000="Testing",IF('Verification data'!#REF! = 'Verification Summary'!$B10, IF('Verification data'!$G$2:$G$5000="Internal",'Verification data'!$I$2:$I$5000,0),0),0),0)),"")} -> 0 | J10: {=IF($A10<>"",SUM(IF('Verification data'!$D$2:$D$5000=$A10,IF('Verification data'!$F$2:$F$5000="Testing",IF('Verification data'!#REF! = 'Verification Summary'!$B10, IF('Verification data'!$G$2:$G$5000="Internal",'Verification data'!#REF!,0),0),0),0)),"")} -> 0 | K10: {=IF($A10<>"",SUM(IF('Verification data'!$D$2:$D$5000=$A10,IF('Verification data'!$F$2:$F$5000="Testing",IF('Verification data'!#REF! = 'Verification Summary'!$B10, IF('Verification data'!$G$2:$G$5000="Internal",'Verification data'!$J$2:$J$5000,0),0),0),0)),"")} -> 0 | L10: {=IF($A10<>"",SUM(IF('Verification data'!$D$2:$D$5000=$A10,IF('Verification data'!$F$2:$F$5000="Testing",IF('Verification data'!#REF! = 'Verification Summary'!$B10, IF('Verification data'!$G$2:$G$5000="Internal",'Verification data'!$K$2:$K$5000,0),0),0),0)),"")} -> 0 | M10: {=IF($A10<>"",SUM(IF('Verification data'!$D$2:$D$5000=$A10,IF('Verification data'!$F$2:$F$5000="Testing",IF('Verification data'!#REF! = 'Verification Summary'!$B10, IF('Verification data'!$G$2:$G$5000="Internal",'Verification data'!$L$2:$L$5000,0),0),0),0)),"")} -> 0 | N10: {=IF($A10<>"",SUM(IF('Verification data'!$D$2:$D$5000=$A10,IF('Verification data'!$F$2:$F$5000="Testing",IF('Verification data'!#REF! = 'Verification Summary'!$B10, IF('Verification data'!$G$2:$G$5000="Internal",'Verification data'!$Q$2:$Q$5000,0),0),0),0)),"")} -> 0 | P10: =IF(A10<>"",A10 & "-" & B10,"") -> Analysis and design-Hours | Q10: =IF(A10<>"",SUM(E10,K10),"") -> 0 | R10: =IF(B10<>"",SUM(F10,L10),"") -> 0 | S10: =IF(C10<>"",SUM(G10,M10),"") -> 0
A11: =IF('Control panel'!A5<>"",'Control panel'!A5,"") -> Coding and unit testing | B11: =IF('Control panel'!B5<>"",'Control panel'!B5,"") -> Hours | C11: {=IF($A11<>"",SUM(IF('Verification data'!$D$2:$D$5000=$A11,IF(NOT(ISERR(SEARCH("Review",'Verification data'!$F$2:$F$5000,1))),IF('Verification data'!#REF! = 'Verification Summary'!B11, IF('Verification data'!$G$2:$G$5000="Internal",'Verification data'!$I$2:$I$5000,0),0),0),0)),"")} -> 0 | D11: {=IF($A11<>"",SUM(IF('Verification data'!$D$2:$D$5000=$A11,IF(NOT(ISERR(SEARCH("Review",'Verification data'!$F$2:$F$5000,1))),IF('Verification data'!#REF! = 'Verification Summary'!B11, IF('Verification data'!$G$2:$G$5000="Internal",'Verification data'!#REF!,0),0),0),0)),"")} -> 0 | E11: {=IF($A11<>"",SUM(IF('Verification data'!$D$2:$D$5000=$A11,IF(NOT(ISERR(SEARCH("Review",'Verification data'!$F$2:$F$5000,1))),IF('Verification data'!#REF! = 'Verification Summary'!B11, IF('Verification data'!$G$2:$G$5000="Internal",'Verification data'!$J$2:$J$5000,0),0),0),0)),"")} -> 0 | F11: {=IF($A11<>"",SUM(IF('Verification data'!$D$2:$D$5000=$A11,IF(NOT(ISERR(SEARCH("Review",'Verification data'!$F$2:$F$5000,1))),IF('Verification data'!#REF! = 'Verification Summary'!B11, IF('Verification data'!$G$2:$G$5000="Internal",'Verification data'!$K$2:$K$5000,0),0),0),0)),"")} -> 0 | G11: {=IF($A11<>"",SUM(IF('Verification data'!$D$2:$D$5000=$A11,IF(NOT(ISERR(SEARCH("Review",'Verification data'!$F$2:$F$5000,1))),IF('Verification data'!#REF! = 'Verification Summary'!B11, IF('Verification data'!$G$2:$G$5000="Internal",'Verification data'!$L$2:$L$5000,0),0),0),0)),"")} -> 0 | H11: {=IF($A11<>"",SUM(IF('Verification data'!$D$2:$D$5000=$A11,IF(NOT(ISERR(SEARCH("Review",'Verification data'!$F$2:$F$5000,1))),IF('Verification data'!#REF! = 'Verification Summary'!B11, IF('Verification data'!$G$2:$G$5000="Internal",'Verification data'!$Q$2:$Q$5000,0),0),0),0)),"")} -> 0 | I11: {=IF($A11<>"",SUM(IF('Verification data'!$D$2:$D$5000=$A11,IF('Verification data'!$F$2:$F$5000="Testing",IF('Verification data'!#REF! = 'Verification Summary'!$B11, IF('Verification data'!$G$2:$G$5000="Internal",'Verification data'!$I$2:$I$5000,0),0),0),0)),"")} -> 0 | J11: {=IF($A11<>"",SUM(IF('Verification data'!$D$2:$D$5000=$A11,IF('Verification data'!$F$2:$F$5000="Testing",IF('Verification data'!#REF! = 'Verification Summary'!$B11, IF('Verification data'!$G$2:$G$5000="Internal",'Verification data'!#REF!,0),0),0),0)),"")} -> 0 | K11: {=IF($A11<>"",SUM(IF('Verification data'!$D$2:$D$5000=$A11,IF('Verification data'!$F$2:$F$5000="Testing",IF('Verification data'!#REF! = 'Verification Summary'!$B11, IF('Verification data'!$G$2:$G$5000="Internal",'Verification data'!$J$2:$J$5000,0),0),0),0)),"")} -> 0 | L11: {=IF($A11<>"",SUM(IF('Verification data'!$D$2:$D$5000=$A11,IF('Verification data'!$F$2:$F$5000="Testing",IF('Verification data'!#REF! = 'Verification Summary'!$B11, IF('Verification data'!$G$2:$G$5000="Internal",'Verification data'!$K$2:$K$5000,0),0),0),0)),"")} -> 0 | M11: {=IF($A11<>"",SUM(IF('Verification data'!$D$2:$D$5000=$A11,IF('Verification data'!$F$2:$F$5000="Testing",IF('Verification data'!#REF! = 'Verification Summary'!$B11, IF('Verification data'!$G$2:$G$5000="Internal",'Verification data'!$L$2:$L$5000,0),0),0),0)),"")} -> 0 | N11: {=IF($A11<>"",SUM(IF('Verification data'!$D$2:$D$5000=$A11,IF('Verification data'!$F$2:$F$5000="Testing",IF('Verification data'!#REF! = 'Verification Summary'!$B11, IF('Verification data'!$G$2:$G$5000="Internal",'Verification data'!$Q$2:$Q$5000,0),0),0),0)),"")} -> 0 | P11: =IF(A11<>"",A11 & "-" & B11,"") -> Coding and unit testing-Hours | Q11: =IF(A11<>"",SUM(E11,K11),"") -> 0 | R11: =IF(B11<>"",SUM(F11,L11),"") -> 0 | S11: =IF(C11<>"",SUM(G11,M11),"") -> 0
